Workbook
Name _: EZJ!$X$91
Name Company_Name: EZJ!$E$7
Name Cost_of_Debt: WACC!$F$8
Name Cost_of_Preferred: WACC!$F$9
Name Diluted_Shares: DCF!$E$15
Name Discount_Rate: DCF!$E$17
Name Equity_Risk_Premium: WACC!$F$7
Name Hist_Year: DCF!$K$7
Name Max_Debt_EBITDAR: EZJ!$E$13
Name Max_Debt_Total_Cap: EZJ!$E$18
Name Next_Year: DCF!$K$8
Name Pct_Debt_Funding: EZJ!$E$10
Name Pub_Comps_Data: Public_Comps!$B$8:$AA$23
Name Pub_Comps_Info_Range: Public_Comps!$B$8:$AA$8
Name Risk_Free_Rate: WACC!$F$6
Name Scenario: DCF!$E$8
Name Share_Price: DCF!$E$14
Name Stub_Period: DCF!$E$12
Name Tax_Rate: EZJ!$N$61
Name Ticker: EZJ!$E$8
Name Ticker_Range: Public_Comps!$C$8:$C$23
Name Units: EZJ!$E$9
Name Val_Date: DCF!$E$11
Name Valuation_Date: DCF!$K$10

Sheet EZJ
B2: =Company_Name&" - Operating Model and Credit Analysis" -> easyJet plc - Operating Model and Credit Analysis
B3: (£ GBP in Millions Except for Per Share and Per Unit Data)
B5: Model Assumptions: | D5: Units:
C7: Company Name: | D7: Name | E7: easyJet plc | K7: Bond Price = 96.39 as per BBG
C8: Ticker: | D8: Name | E8: LSE:EZJ | K8: YTM = 3.074
C9: Conversion Units: | D9: # | E9: 100
C10: Debt Funding Percentage: | D10: % | E10: 1
C11: Operating Scenario: | D11: Name | E11: (See DCF tab to select)
C13: Maximum (Total Debt + Lease Liabilities) / EBITDAR: | D13: x | E13: =INDEX(E14:E16,MATCH(Scenario,$C14:$C16,0),1) -> 0
C14: =$C$31 -> Base | D14: x
C15: =$C$32 -> Downside | D15: x | E15: 6
C16: =$C$33 -> XT Downside | D16: x | E16: 7
C18: Maximum (Total Debt + Lease Liabilities) / Total Capital: | D18: % | E18: =INDEX(E19:E21,MATCH(Scenario,$C19:$C21,0),1) -> 0
C19: =$C$31 -> Base | D19: %
C20: =$C$32 -> Downside | D20: % | E20: 0.6
C21: =$C$33 -> XT Downside | D21: % | E21: 0.7
C23: Fiscal Year: | D23: Year | E23: =YEAR(E26) -> 2019 | F23: =YEAR(F26) -> 2019 | G23: =YEAR(G26) -> 2020 | H23: =YEAR(H26) -> 2020 | I23: =YEAR(I26) -> 2021 | J23: =YEAR(J26) -> 2021 | K23: =YEAR(K26) -> 2022 | L23: =YEAR(L26) -> 2022 | ... R23: =YEAR(R26) -> 2026 | T23: =YEAR(T26) -> 2019 | U23: =YEAR(U26) -> 2020 | V23: =YEAR(V26) -> 2021 | W23: =YEAR(W26) -> 2022 | X23: =YEAR(X26) -> 2023 | Y23: =YEAR(Y26) -> 2024 | Z23: =YEAR(Z26) -> 2025 | AA23: =YEAR(AA26) -> 2026
E25: =$E$25 -> Historical (Half-Years): | Q25: Projected (Annual): | T25: Historical: | Z25: =$Q$25 -> Projected (Annual):
B26: Financial Statement Assumptions: | D26: =$D$5 -> Units: | E26: 43555 | F26: =EOMONTH(E26,6) -> 43738 | G26: =EOMONTH(F26,6) -> 43921 | H26: =EOMONTH(G26,6) -> 44104 | I26: =EOMONTH(H26,6) -> 44286 | J26: =EOMONTH(I26,6) -> 44469 | K26: =EOMONTH(J26,6) -> 44651 | L26: =EOMONTH(K26,6) -> 44834 | M26: =EOMONTH(L26,6) -> 45016 | ... P26: =EOMONTH(O26,6) -> 45565 | Q26: =EOMONTH(P26,12) -> 45930 | R26: =EOMONTH(Q26,12) -> 46295 | T26: =F26 -> 43738 | U26: =EOMONTH(T26,12) -> 44104 | V26: =EOMONTH(U26,12) -> 44469 | W26: =EOMONTH(V26,12) -> 44834 | X26: =EOMONTH(W26,12) -> 45199 | Y26: =EOMONTH(X26,12) -> 45565 | Z26: =EOMONTH(Y26,12) -> 45930 | AA26: =EOMONTH(Z26,12) -> 46295
B27: Revenue Drivers:
C29: Available Seat Kilometres (ASK): | D29: Millions KM | E29: 49367 | F29: 66689 | G29: 46753 | H29: 16077 | I29: 8088 | J29: =33348-I29 -> 25260 | K29: 34287 | L29: =J29*(1+L30) -> 47994 | M29: =K29*(1+M30) -> 48001.8 | N29: =L29*(1+N30) -> 67191.6 | O29: =M29*(1+O30) -> 57602.16 | P29: =N29*(1+P30) -> 77270.34 | Q29: =SUM(O29:P29)*(1+Q30) -> 155103.37 | R29: =Q29*(1+R30) -> 174491.3 | T29: =SUMIF($E$23:$R$23,T$23,$E29:$R29) -> 116056 | U29: =SUMIF($E$23:$R$23,U$23,$E29:$R29) -> 62830 | V29: =SUMIF($E$23:$R$23,V$23,$E29:$R29) -> 33348 | W29: =SUMIF($E$23:$R$23,W$23,$E29:$R29) -> 82281 | X29: =SUMIF($E$23:$R$23,X$23,$E29:$R29) -> 115193.4 | Y29: =SUMIF($E$23:$R$23,Y$23,$E29:$R29) -> 134872.5 | Z29: =SUMIF($E$23:$R$23,Z$23,$E29:$R29) -> 155103.37 | AA29: =SUMIF($E$23:$R$23,AA$23,$E29:$R29) -> 174491.3
C30: Selected YoY Growth Rate: | D30: % | G30: =G29/E29-1 -> -0.052950351 | H30: =H29/F29-1 -> -0.75892576 | I30: =I29/G29-1 -> -0.82700575 | J30: =J29/H29-1 -> 0.57118865 | K30: =K29/I29-1 -> 3.2392433 | L30: =INDEX(L31:L33,MATCH(Scenario,$C31:$C33,0),1) -> 0.9 | M30: =INDEX(M31:M33,MATCH(Scenario,$C31:$C33,0),1) -> 0.4 | N30: =INDEX(N31:N33,MATCH(Scenario,$C31:$C33,0),1) -> 0.4 | O30: =INDEX(O31:O33,MATCH(Scenario,$C31:$C33,0),1) -> 0.2 | P30: =INDEX(P31:P33,MATCH(Scenario,$C31:$C33,0),1) -> 0.15 | Q30: =INDEX(Q31:Q33,MATCH(Scenario,$C31:$C33,0),1) -> 0.15 | R30: =INDEX(R31:R33,MATCH(Scenario,$C31:$C33,0),1) -> 0.125 | U30: =U29/T29-1 -> -0.45862342 | V30: =V29/U29-1 -> -0.46923444 | W30: =W29/V29-1 -> 1.4673444 | X30: =X29/W29-1 -> 0.4 | Y30: =Y29/X29-1 -> 0.17083531 | Z30: =Z29/Y29-1 -> 0.15 | AA30: =AA29/Z29-1 -> 0.125
C31: Base | D31: % | L31: 0.9 | M31: 0.4 | N31: 0.4 | O31: 0.2 | P31: 0.15 | Q31: 0.15 | R31: 0.125
C32: Downside | D32: % | L32: 0.4 | M32: 0.35 | N32: 0.3 | O32: 0.25 | P32: 0.25 | Q32: 0.175 | R32: 0.125
C33: XT Downside | D33: % | L33: 0.3 | M33: 0.3 | N33: 0.25 | O33: 0.2 | P33: 0.15 | Q33: 0.125 | R33: 0.1
C35: Selected Load Factor: | D35: % | E35: =E40/E29 -> 0.91338343 | F35: =F40/F29 -> 0.93943529 | G35: =G40/G29 -> 0.91801596 | H35: =H40/H29 -> 0.99483735 | I35: =I40/I29 -> 0.63501484 | J35: =J40/J29 -> 0.73072051 | K35: =K40/K29 -> 0.78195818 | L35: =INDEX(L36:L38,MATCH(Scenario,$C36:$C38,0),1) -> 0.85 | M35: =INDEX(M36:M38,MATCH(Scenario,$C36:$C38,0),1) -> 0.87 | N35: =INDEX(N36:N38,MATCH(Scenario,$C36:$C38,0),1) -> 0.9 | O35: =INDEX(O36:O38,MATCH(Scenario,$C36:$C38,0),1) -> 0.91 | P35: =INDEX(P36:P38,MATCH(Scenario,$C36:$C38,0),1) -> 0.92 | Q35: =INDEX(Q36:Q38,MATCH(Scenario,$C36:$C38,0),1) -> 0.925 | R35: =INDEX(R36:R38,MATCH(Scenario,$C36:$C38,0),1) -> 0.925 | T35: =T40/T29 -> 0.92835355 | U35: =U40/U29 -> 0.93767309 | V35: =V40/V29 -> 0.7075087 | W35: =W40/W29 -> 0.82164655 | X35: =X40/X29 -> 0.88749882 | Y35: =Y40/Y29 -> 0.91572914 | Z35: =Z40/Z29 -> 0.925 | AA35: =AA40/AA29 -> 0.925
C36: =$C$31 -> Base | D36: % | L36: 0.85 | M36: 0.87 | N36: 0.9 | O36: 0.91 | P36: 0.92 | Q36: 0.925 | R36: 0.925
C37: =$C$32 -> Downside | D37: % | L37: 0.85 | M37: 0.86 | N37: 0.88 | O37: 0.9 | P37: 0.91 | Q37: 0.92 | R37: 0.92
C38: =$C$33 -> XT Downside | D38: % | L38: 0.85 | M38: 0.855 | N38: 0.87 | O38: 0.88 | P38: 0.89 | Q38: 0.9 | R38: 0.91
C40: Revenue Passenger Kilometres (RPK): | D40: Millions KM | E40: 45091 | F40: 62650 | G40: 42920 | H40: 15994 | I40: 5136 | J40: =23594-I40 -> 18458 | K40: 26811 | L40: =L29*L35 -> 40794.9 | M40: =M29*M35 -> 41761.566 | N40: =N29*N35 -> 60472.44 | O40: =O29*O35 -> 52417.966 | P40: =P29*P35 -> 71088.713 | Q40: =Q29*Q35 -> 143470.62 | R40: =R29*R35 -> 161404.45 | T40: =SUMIF($E$23:$R$23,T$23,$E40:$R40) -> 107741 | U40: =SUMIF($E$23:$R$23,U$23,$E40:$R40) -> 58914 | V40: =SUMIF($E$23:$R$23,V$23,$E40:$R40) -> 23594 | W40: =SUMIF($E$23:$R$23,W$23,$E40:$R40) -> 67605.9 | X40: =SUMIF($E$23:$R$23,X$23,$E40:$R40) -> 102234.01 | Y40: =SUMIF($E$23:$R$23,Y$23,$E40:$R40) -> 123506.68 | Z40: =SUMIF($E$23:$R$23,Z$23,$E40:$R40) -> 143470.62 | AA40: =SUMIF($E$23:$R$23,AA$23,$E40:$R40) -> 161404.45
C41: YoY Growth Rate: | D41: % | G41: =G40/E40-1 -> -0.04814708 | H41: =H40/F40-1 -> -0.7447087 | I41: =I40/G40-1 -> -0.88033551 | J41: =J40/H40-1 -> 0.15405777 | K41: =K40/I40-1 -> 4.2202103 | L41: =L40/J40-1 -> 1.2101474 | M41: =M40/K40-1 -> 0.55762806 | N41: =N40/L40-1 -> 0.48235294 | ... P41: =P40/N40-1 -> 0.17555556 | Q41: =Q40/SUM(O40:P40)-1 -> 0.16164262 | R41: =R40/Q40-1 -> 0.125 | U41: =U40/T40-1 -> -0.45318867 | V41: =V40/U40-1 -> -0.59951794 | W41: =W40/V40-1 -> 1.8653853 | X41: =X40/W40-1 -> 0.51220538 | Y41: =Y40/X40-1 -> 0.20807824 | Z41: =Z40/Y40-1 -> 0.16164262 | AA41: =AA40/Z40-1 -> 0.125
C43: Passenger Revenue: | D43: £ M | E43: 1824 | F43: 3185 | G43: 1833 | H43: 470 | I43: 170 | J43: =1000-I43 -> 830 | K43: 985 | L43: =L40*L44/Units -> 1937.7577 | M43: =M40*M44/Units -> 1628.7011 | N43: =N40*N44/Units -> 2993.3858 | O43: =O40*O44/Units -> 2122.9276 | P43: =P40*P44/Units -> 3625.5244 | Q43: =Q40*Q44/Units -> 6671.3839 | R43: =R40*R44/Units -> 7666.7114 | T43: =SUMIF($E$23:$R$23,T$23,$E43:$R43) -> 5009 | U43: =SUMIF($E$23:$R$23,U$23,$E43:$R43) -> 2303 | V43: =SUMIF($E$23:$R$23,V$23,$E43:$R43) -> 1000 | W43: =SUMIF($E$23:$R$23,W$23,$E43:$R43) -> 2922.7577 | X43: =SUMIF($E$23:$R$23,X$23,$E43:$R43) -> 4622.0869 | Y43: =SUMIF($E$23:$R$23,Y$23,$E43:$R43) -> 5748.452 | Z43: =SUMIF($E$23:$R$23,Z$23,$E43:$R43) -> 6671.3839 | AA43: =SUMIF($E$23:$R$23,AA$23,$E43:$R43) -> 7666.7114
C44: Yield (Revenue per RPK): | D44: p / KM | E44: =E43/E$40*Units -> 4.0451531 | F44: =F43/F$40*Units -> 5.0837989 | G44: =G43/G$40*Units -> 4.2707363 | H44: =H43/H$40*Units -> 2.938602 | I44: =I43/I$40*Units -> 3.3099688 | J44: =J43/J$40*Units -> 4.4966952 | K44: =K43/K$40*Units -> 3.6738652 | L44: 4.75 | M44: 3.9 | N44: 4.95 | O44: 4.05 | P44: 5.1 | Q44: 4.65 | R44: 4.75 | T44: =T43/T$40*Units -> 4.6491122 | U44: =U43/U$40*Units -> 3.9090878 | V44: =V43/V$40*Units -> 4.2383657 | W44: =W43/W$40*Units -> 4.3232288 | X44: =X43/X$40*Units -> 4.5210855 | Y44: =Y43/Y$40*Units -> 4.6543653 | Z44: =Z43/Z$40*Units -> 4.65 | AA44: =AA43/AA$40*Units -> 4.75
C46: Ancillary Revenue: | D46: £ M | E46: 519 | F46: 857 | G46: 549 | H46: 157 | I46: 70 | J46: =458-I46 -> 388 | K46: 513 | L46: =L47*L40/Units -> 713.91075 | M46: =M47*M40/Units -> 647.30427 | N46: =N47*N40/Units -> 816.37794 | O46: =O47*O40/Units -> 602.8066 | P46: =P47*P40/Units -> 995.24198 | Q46: =Q47*Q40/Units -> 1865.1181 | R46: =R47*R40/Units -> 2178.9601 | T46: =SUMIF($E$23:$R$23,T$23,$E46:$R46) -> 1376 | U46: =SUMIF($E$23:$R$23,U$23,$E46:$R46) -> 706 | V46: =SUMIF($E$23:$R$23,V$23,$E46:$R46) -> 458 | W46: =SUMIF($E$23:$R$23,W$23,$E46:$R46) -> 1226.9108 | X46: =SUMIF($E$23:$R$23,X$23,$E46:$R46) -> 1463.6822 | Y46: =SUMIF($E$23:$R$23,Y$23,$E46:$R46) -> 1598.0486 | Z46: =SUMIF($E$23:$R$23,Z$23,$E46:$R46) -> 1865.1181 | AA46: =SUMIF($E$23:$R$23,AA$23,$E46:$R46) -> 2178.9601
C47: Yield (Revenue per RPK): | D47: p / KM | E47: =E46/E$40*Units -> 1.1510057 | F47: =F46/F$40*Units -> 1.367917 | G47: =G46/G$40*Units -> 1.279124 | H47: =H46/H$40*Units -> 0.98161811 | I47: =I46/I$40*Units -> 1.3629283 | J47: =J46/J$40*Units -> 2.1020696 | K47: =K46/K$40*Units -> 1.9133938 | L47: 1.75 | M47: 1.55 | N47: 1.35 | O47: 1.15 | P47: 1.4 | Q47: 1.3 | R47: 1.35 | T47: =T46/T$40*Units -> 1.2771368 | U47: =U46/U$40*Units -> 1.1983569 | V47: =V46/V$40*Units -> 1.9411715 | W47: =W46/W$40*Units -> 1.8147983 | X47: =X46/X$40*Units -> 1.431698 | Y47: =Y46/Y$40*Units -> 1.2938965 | Z47: =Z46/Z$40*Units -> 1.3 | AA47: =AA46/AA$40*Units -> 1.35
B49: Expense Drivers: | E49: =$E$26 -> 43555 | F49: =$F$26 -> 43738 | G49: =$G$26 -> 43921 | H49: =$H$26 -> 44104 | I49: =$I$26 -> 44286 | J49: =$J$26 -> 44469 | K49: =$K$26 -> 44651 | L49: =$L$26 -> 44834 | M49: =$M$26 -> 45016 | N49: =$N$26 -> 45199 | O49: =$O$26 -> 45382 | P49: =$P$26 -> 45565 | Q49: =$Q$26 -> 45930 | R49: =$R$26 -> 46295 | T49: =$T$26 -> 43738 | U49: =$U$26 -> 44104 | V49: =$V$26 -> 44469 | W49: =$W$26 -> 44834 | X49: =$X$26 -> 45199 | Y49: =$Y$26 -> 45565 | Z49: =$Z$26 -> 45930 | AA49: =$AA$26 -> 46295
C51: Non-Fuel Costs per ASK: | D51: p per ASK | E51: =-E95/E29*Units -> 3.5590577 | F51: =-F95/F29*Units -> 3.3618738 | G51: =-G95/G29*Units -> 3.7623254 | H51: =-H95/H29*Units -> 5.5171985 | I51: =-I95/I29*Units -> 6.5158259 | J51: =-J95/J29*Units -> 3.8994458 | K51: =-K95/K29*Units -> 3.9577683 | L51: 3.5 | M51: 3.7 | N51: 3.45 | O51: 3.6 | P51: 3.5 | Q51: 3.55 | R51: 3.6 | T51: =-T95/T29*Units -> 3.4457503 | U51: =-U95/U29*Units -> 4.211364 | V51: =-V95/V29*Units -> 4.534005 | W51: =-W95/W29*Units -> 3.6907549 | X51: =-X95/X29*Units -> 3.5541765 | Y51: =-Y95/Y29*Units -> 3.5427086 | Z51: =-Z95/Z29*Units -> 3.55 | AA51: =-AA95/AA29*Units -> 3.6
C53: Selected Fuel Costs per ASK: | D53: p per ASK | E53: =-E96/E29*Units -> 1.2194381 | F53: =-F96/F29*Units -> 1.2205911 | G53: =-G96/G29*Units -> 1.1421727 | H53: =-H96/H29*Units -> 1.1631523 | I53: =-I96/I29*Units -> 1.1993076 | J53: =-J96/J29*Units -> 1.0847189 | K53: =-K96/K29*Units -> 1.0557937 | L53: =INDEX(L54:L56,MATCH(Scenario,$C54:$C56,0),1) -> 1.1 | M53: =INDEX(M54:M56,MATCH(Scenario,$C54:$C56,0),1) -> 1.12 | N53: =INDEX(N54:N56,MATCH(Scenario,$C54:$C56,0),1) -> 1.12 | O53: =INDEX(O54:O56,MATCH(Scenario,$C54:$C56,0),1) -> 1.15 | P53: =INDEX(P54:P56,MATCH(Scenario,$C54:$C56,0),1) -> 1.2 | Q53: =INDEX(Q54:Q56,MATCH(Scenario,$C54:$C56,0),1) -> 1.2 | R53: =INDEX(R54:R56,MATCH(Scenario,$C54:$C56,0),1) -> 1.22 | T53: =-T96/T29*Units -> 1.2201006 | U53: =-U96/U29*Units -> 1.147541 | V53: =-V96/V29*Units -> 1.1125105 | W53: =-W96/W29*Units -> 1.081579 | X53: =-X96/X29*Units -> 1.12 | Y53: =-Y96/Y29*Units -> 1.1786457 | Z53: =-Z96/Z29*Units -> 1.2 | AA53: =-AA96/AA29*Units -> 1.22
C54: =$C$31 -> Base | D54: p per ASK | L54: 1.1 | M54: 1.12 | N54: 1.12 | O54: 1.15 | P54: 1.2 | Q54: 1.2 | R54: 1.22
C55: =$C$32 -> Downside | D55: p per ASK | L55: 1.12 | M55: 1.15 | N55: 1.2 | O55: 1.25 | P55: 1.3 | Q55: 1.35 | R55: 1.4
C56: =$C$33 -> XT Downside | D56: p per ASK | L56: 1.15 | M56: 1.2 | N56: 1.25 | O56: 1.33 | P56: 1.4 | Q56: 1.45 | R56: 1.5
C58: Lease Depreciation per ASK: | D58: p per ASK | E58: =-E100/E29*Units -> 0.23294914 | F58: =-F100/F29*Units -> 0.19793369 | G58: =-G100/G29*Units -> 0.26308472 | H58: =-H100/H29*Units -> 0.65932699 | I58: =-I100/I29*Units -> 1.1498516 | J58: =-J100/J29*Units -> 0.51068884 | K58: =-K100/K29*Units -> 0.38790212 | L58: 0.3 | M58: 0.25 | N58: 0.2 | O58: 0.23 | P58: 0.19 | Q58: 0.2 | R58: 0.2 | T58: =-T100/T29*Units -> 0.21282829 | U58: =-U100/U29*Units -> 0.36447557 | V58: =-V100/V29*Units -> 0.66570709 | W58: =-W100/W29*Units -> 0.33662936 | X58: =-X100/X29*Units -> 0.22083531 | Y58: =-Y100/Y29*Units -> 0.20708344 | Z58: =-Z100/Z29*Units -> 0.2 | AA58: =-AA100/AA29*Units -> 0.2
C59: Depreciation & Amortisation per ASK: | D59: p per ASK | E59: =-E102/E29*Units -> 0.25117994 | F59: =-F102/F29*Units -> 0.19943319 | G59: =-G102/G29*Units -> 0.29730712 | H59: =-H102/H29*Units -> 0.84592897 | I59: =-I102/I29*Units -> 1.5331355 | J59: =-J102/J29*Units -> 0.55027712 | K59: =-K102/K29*Units -> 0.42290081 | L59: 0.33 | M59: 0.28 | N59: 0.23 | O59: 0.26 | P59: 0.22 | Q59: 0.23 | R59: 0.23 | T59: =-T102/T29*Units -> 0.22144482 | U59: =-U102/U29*Units -> 0.437689 | V59: =-V102/V29*Units -> 0.78865299 | W59: =-W102/W29*Units -> 0.36871234 | X59: =-X102/X29*Units -> 0.25083531 | Y59: =-Y102/Y29*Units -> 0.23708344 | Z59: =-Z102/Z29*Units -> 0.23 | AA59: =-AA102/AA29*Units -> 0.23
C61: Tax Rate: | D61: % | E61: =-E113/E112 -> 0.19852941 | F61: =-F113/F112 -> 0.19230769 | G61: =-G113/G112 -> 0.082152975 | H61: =-H113/H112 -> 0.17934783 | I61: =-I113/I112 -> 0.14883721 | J61: =-J113/J112 -> 0.20971867 | K61: =-K113/K112 -> 0.22621185 | L61: 0.19 | M61: 0.19 | N61: 0.25 | O61: =N61 -> 0.25 | P61: =O61 -> 0.25 | Q61: =P61 -> 0.25 | R61: =Q61 -> 0.25 | T61: =-T113/T112 -> 0.18837209 | U61: =-U113/U112 -> 0.15239592 | V61: =-V113/V112 -> 0.17181467 | W61: =-W113/W112 -> 0.23571342 | X61: =-X113/X112 -> 0.36477472 | Y61: =-Y113/Y112 -> 0.25 | Z61: =-Z113/Z112 -> 0.25 | AA61: =-AA113/AA112 -> 0.25
B63: Balance Sheet and Cash Flow Statement Drivers: | E63: =$E$26 -> 43555 | F63: =$F$26 -> 43738 | G63: =$G$26 -> 43921 | H63: =$H$26 -> 44104 | I63: =$I$26 -> 44286 | J63: =$J$26 -> 44469 | K63: =$K$26 -> 44651 | L63: =$L$26 -> 44834 | M63: =$M$26 -> 45016 | N63: =$N$26 -> 45199 | O63: =$O$26 -> 45382 | P63: =$P$26 -> 45565 | Q63: =$Q$26 -> 45930 | R63: =$R$26 -> 46295 | T63: =$T$26 -> 43738 | U63: =$U$26 -> 44104 | V63: =$V$26 -> 44469 | W63: =$W$26 -> 44834 | X63: =$X$26 -> 45199 | Y63: =$Y$26 -> 45565 | Z63: =$Z$26 -> 45930 | AA63: =$AA$26 -> 46295
C65: Accounts Receivable % LTM Revenue: | D65: % | F65: =F121/SUM(E94:F94) -> 0.047298356 | G65: =G121/SUM(F94:G94) -> 0.051681196 | H65: =H121/SUM(G94:H94) -> 0.064140911 | I65: =I121/SUM(H94:I94) -> 0.17301038 | J65: =J121/SUM(I94:J94) -> 0.19958848 | K65: =K121/SUM(J94:K94) -> 0.12371134 | L65: 0.1 | M65: 0.08 | N65: 0.07 | O65: 0.06 | P65: 0.05 | Q65: 0.05 | R65: 0.05 | T65: =T121/T94 -> 0.047298356 | U65: =U121/U94 -> 0.064140911 | V65: =V121/V94 -> 0.19958848 | W65: =W121/W94 -> 0.1 | X65: =X121/X94 -> 0.07 | Y65: =Y121/Y94 -> 0.05 | Z65: =Z121/Z94 -> 0.05 | AA65: =AA121/AA94 -> 0.05
C66: Deferred Revenue % LTM Revenue: | D66: % | F66: =F127/SUM(E94:F94) -> 0.16742365 | G66: =G127/SUM(F94:G94) -> 0.15161893 | H66: =H127/SUM(G94:H94) -> 0.2040545 | I66: =I127/SUM(H94:I94) -> 0.76355248 | J66: =J127/SUM(I94:J94) -> 0.58024691 | K66: =K127/SUM(J94:K94) -> 0.65537555 | L66: 0.55 | M66: 0.45 | N66: 0.35 | O66: 0.25 | P66: 0.2 | Q66: 0.2 | R66: 0.2 | T66: =T127/T94 -> 0.16742365 | U66: =U127/U94 -> 0.2040545 | V66: =V127/V94 -> 0.58024691 | W66: =W127/W94 -> 0.55 | X66: =X127/X94 -> 0.35 | Y66: =Y127/Y94 -> 0.2 | Z66: =Z127/Z94 -> 0.2 | AA66: =AA127/AA94 -> 0.2
C67: Payables % LTM Operating Expenses: | D67: % | F67: =-F128/SUM(E95:F96) -> 0.19390582 | G67: =-G128/SUM(F95:G96) -> 0.31033838 | H67: =-H128/SUM(G95:H96) -> 0.36887437 | I67: =-I128/SUM(H95:I96) -> 0.47173145 | J67: =-J128/SUM(I95:J96) -> 0.59904408 | K67: =-K128/SUM(J95:K96) -> 0.4593687 | L67: 0.4 | M67: 0.35 | N67: 0.3 | O67: 0.25 | P67: 0.25 | Q67: 0.25 | R67: 0.25 | T67: =-T128/SUM(T95:T96) -> 0.19390582 | U67: =-U128/SUM(U95:U96) -> 0.36887437 | V67: =-V128/SUM(V95:V96) -> 0.59904408 | W67: =-W128/SUM(W95:W96) -> 0.4 | X67: =-X128/SUM(X95:X96) -> 0.3 | Y67: =-Y128/SUM(Y95:Y96) -> 0.25 | Z67: =-Z128/SUM(Z95:Z96) -> 0.25 | AA67: =-AA128/SUM(AA95:AA96) -> 0.25
C68: Other Liabilities % LTM Operating Expenses: | D68: % | F68: =-F129/SUM(E95:F96) -> 0.17488458 | G68: =-G129/SUM(F95:G96) -> 0.15928211 | H68: =-H129/SUM(G95:H96) -> 0.24948025 | I68: =-I129/SUM(H95:I96) -> 0.42285041 | J68: =-J129/SUM(I95:J96) -> 0.34306957 | K68: =-K129/SUM(J95:K96) -> 0.21692411 | L68: 0.2 | M68: 0.2 | N68: 0.175 | O68: 0.175 | P68: 0.17 | Q68: 0.17 | R68: 0.17 | T68: =-T129/SUM(T95:T96) -> 0.17488458 | U68: =-U129/SUM(U95:U96) -> 0.24948025 | V68: =-V129/SUM(V95:V96) -> 0.34306957 | W68: =-W129/SUM(W95:W96) -> 0.2 | X68: =-X129/SUM(X95:X96) -> 0.175 | Y68: =-Y129/SUM(Y95:Y96) -> 0.17 | Z68: =-Z129/SUM(Z95:Z96) -> 0.17 | AA68: =-AA129/SUM(AA95:AA96) -> 0.17
C70: Cash Adjustment to Interest % Book Interest: | D70: % | E70: =-E146/E110 -> 0.41176471 | F70: =-F146/F110 -> -0.89473684 | G70: =-G146/G110 -> 1.05 | H70: =-H146/H110 -> 0.64948454 | I70: =-I146/I110 -> -0.61363636 | J70: =-J146/J110 -> -1.5609756 | K70: =-K146/K110 -> -1.5517241 | L70: -0.15 | M70: =L70 -> -0.15 | N70: =M70 -> -0.15 | O70: =N70 -> -0.15 | P70: =O70 -> -0.15 | Q70: =P70 -> -0.15 | R70: =Q70 -> -0.15 | T70: =-T146/T110 -> -0.27777778 | U70: =-U146/U110 -> 0.84224599 | V70: =-V146/V110 -> -1.2301587 | W70: =-W146/W110 -> -1.1200585 | X70: =-X146/X110 -> -0.15 | Y70: =-Y146/Y110 -> -0.15 | Z70: =-Z146/Z110 -> -0.15 | AA70: =-AA146/AA110 -> -0.15
C71: Other Operational Items % Revenue: | D71: % | E71: =E148/E94 -> 0.0034144259 | F71: =F148/F94 -> 0.00049480455 | G71: =G148/G94 -> 0.0071368598 | H71: =H148/H94 -> 0.044657097 | I71: =I148/I94 -> -0.2125 | J71: =J148/J94 -> 0.022167488 | K71: =K148/K94 -> 0.022696929 | L71: 0.002 | M71: =L71 -> 0.002 | N71: =M71 -> 0.002 | O71: =N71 -> 0.002 | P71: =O71 -> 0.002 | Q71: =P71 -> 0.002 | R71: =Q71 -> 0.002 | T71: =T148/T94 -> 0.0015661707 | U71: =U148/U94 -> 0.014955135 | V71: =V148/V94 -> -0.016460905 | W71: =W148/W94 -> 0.0094714402 | X71: =X148/X94 -> 0.002 | Y71: =Y148/Y94 -> 0.002 | Z71: =Z148/Z94 -> 0.002 | AA71: =AA148/AA94 -> 0.002
C72: CapEx & Intangible Purchases per ASK: | D72: p per ASK | E72: =-E153/E29*Units -> 0.94192477 | F72: =-F153/F29*Units -> 0.77823929 | G72: =-G153/G29*Units -> 0.96678288 | H72: =-H153/H29*Units -> 1.511476 | I72: =-I153/I29*Units -> 0.90257171 | J72: =-J153/J29*Units -> 0.30087094 | K72: =-K153/K29*Units -> 0.72038965 | L72: 0.68 | M72: 0.73 | N72: 0.63 | O72: 0.8 | P72: 0.75 | Q72: 0.9 | R72: 0.93 | T72: =-T153/T29*Units -> 0.84786655 | U72: =-U153/U29*Units -> 1.1061595 | V72: =-V153/V29*Units -> 0.44680341 | W72: =-W153/W29*Units -> 0.69683062 | X72: =-X153/X29*Units -> 0.67167062 | Y72: =-Y153/Y29*Units -> 0.7713543 | Z72: =-Z153/Z29*Units -> 0.9 | AA72: =-AA153/AA29*Units -> 0.93
C73: ROU Asset Additions per ASK: | D73: p per ASK | E73: =-E155/E29*Units -> 0.14179513 | F73: =-F155/F29*Units -> 0.085471367 | G73: =-G155/G29*Units -> 0.083417107 | H73: =-H155/H29*Units -> 0.17416185 | I73: =-I155/I29*Units -> 0.11127596 | J73: =-J155/J29*Units -> 0.58194774 | K73: =-K155/K29*Units -> 0.16332721 | L73: 0.2 | M73: 0.25 | N73: 0.23 | O73: 0.27 | P73: 0.25 | Q73: 0.28 | R73: 0.3 | T73: =-T155/T29*Units -> 0.10942993 | U73: =-U155/U29*Units -> 0.10663696 | V73: =-V155/V29*Units -> 0.46779417 | W73: =-W155/W29*Units -> 0.18471822 | X73: =-X155/X29*Units -> 0.23833412 | Y73: =-Y155/Y29*Units -> 0.25854172 | Z73: =-Z155/Z29*Units -> 0.28 | AA73: =-AA155/AA29*Units -> 0.3
C75: Dividends % LTM Net Income: | D75: % | F75: =-F161/SUM(E143:F143) -> 0 | G75: =-G161/SUM(F143:G143) -> 0.71604938 | H75: =-H161/SUM(G143:H143) -> 0 | I75: =-I161/SUM(H143:I143) -> 0 | J75: =-J161/SUM(I143:J143) -> 0 | K75: =-K161/SUM(J143:K143) -> 0 | L75: 0 | M75: 0.5 | N75: 0 | O75: 0.5 | P75: 0 | Q75: 0.5 | R75: 0.5 | T75: =-T161/T143 -> 0.66762178 | U75: =-U161/U143 -> -0.16126043 | V75: =-V161/V143 -> 0 | W75: =-W161/W143 -> 0 | X75: =-X161/X143 -> 0 | Y75: =-Y161/Y143 -> 0.22715453 | Z75: =-Z161/Z143 -> 0.5 | AA75: =-AA161/AA143 -> 0.5
C76: Other Financing Items % Revenue: | D76: % | E76: =E162/E94 -> 0.001707213 | F76: =F162/F94 -> 0.00074220683 | G76: =G162/G94 -> 0 | H76: =H162/H94 -> -0.023923445 | I76: =I162/I94 -> 0.025 | J76: =J162/J94 -> -0.00082101806 | K76: =K162/K94 -> 0.0060080107 | L76: =AVERAGE(E76:K76) -> 0.0012447096 | M76: =L76 -> 0.0012447096 | N76: =M76 -> 0.0012447096 | O76: =N76 -> 0.0012447096 | P76: =O76 -> 0.0012447096 | Q76: =P76 -> 0.0012447096 | R76: =Q76 -> 0.0012447096 | T76: =T162/T94 -> 0.0010963195 | U76: =U162/U94 -> -0.0049850449 | V76: =V162/V94 -> 0.0034293553 | W76: =W162/W94 -> 0.0029642265 | X76: =X162/X94 -> 0.0012447096 | Y76: =Y162/Y94 -> 0.0012447096 | Z76: =Z162/Z94 -> 0.0012447096 | AA76: =AA162/AA94 -> 0.0012447096
C77: Lease Principal Repayments per ASK: | D77: p per ASK | E77: =-E164/E29*Units -> 0.1721798 | F77: =-F164/F29*Units -> 0.13345529 | G77: =-G164/G29*Units -> 0.23741792 | H77: =-H164/H29*Units -> 0.74018785 | I77: =-I164/I29*Units -> 2.1513353 | J77: =-J164/J29*Units -> 0.34441805 | K77: =-K164/K29*Units -> 0.26832327 | L77: 0.2 | M77: 0.2 | N77: 0.2 | O77: 0.2 | P77: 0.21 | Q77: 0.22 | R77: 0.22 | T77: =-T164/T29*Units -> 0.14992762 | U77: =-U164/U29*Units -> 0.36606717 | V77: =-V164/V29*Units -> 0.78265563 | W77: =-W164/W29*Units -> 0.22847073 | X77: =-X164/X29*Units -> 0.2 | Y77: =-Y164/Y29*Units -> 0.20572914 | Z77: =-Z164/Z29*Units -> 0.22 | AA77: =-AA164/AA29*Units -> 0.22
C78: FX Rate Effects % Revenue: | D78: % | E78: =E167/E94 -> 0.00042680324 | F78: =F167/F94 -> 0.012122712 | G78: =G167/G94 -> -0.0079764903 | H78: =H167/H94 -> -0.066985646 | I78: =I167/I94 -> -0.475 | J78: =J167/J94 -> 0.033661741 | K78: =K167/K94 -> 0.012683578 | L78: 0.01 | M78: =L78 -> 0.01 | N78: =M78 -> 0.01 | O78: =N78 -> 0.01 | P78: =O78 -> 0.01 | Q78: =P78 -> 0.01 | R78: =Q78 -> 0.01 | T78: =T167/T94 -> 0.0078308536 | U78: =U167/U94 -> -0.020272516 | V78: =V167/V94 -> -0.050068587 | W78: =W167/W94 -> 0.010968752 | X78: =X167/X94 -> 0.01 | Y78: =Y167/Y94 -> 0.01 | Z78: =Z167/Z94 -> 0.01 | AA78: =AA167/AA94 -> 0.01
C80: Beginning Net Operating Losses: | D80: £ M | K80: =425/K61 -> 1878.7698 | L80: =K83 -> 2435.7698 | M80: =L83 -> 2319.9969 | N80: =M83 -> 2617.8105 | O80: =N83 -> 2164.3109 | P80: =O83 -> 2451.2588 | Q80: =P83 -> 1797.7064 | R80: =Q83 -> 1325.3969
C81: (+) NOLs Created: | D81: £ M | K81: =MAX(0,-K112) -> 557 | L81: =MAX(0,-L112) -> 0 | M81: =MAX(0,-M112) -> 297.8136 | N81: =MAX(0,-N112) -> 0 | O81: =MAX(0,-O112) -> 286.94785 | P81: =MAX(0,-P112) -> 0 | Q81: =MAX(0,-Q112) -> 0 | R81: =MAX(0,-R112) -> 0
C82: (-) NOLs Used: | D82: £ M | K82: =-MIN(K80+K81,MAX(K112,0)) -> 0 | L82: =-MIN(L80+L81,MAX(L112,0)) -> -115.77292 | M82: =-MIN(M80+M81,MAX(M112,0)) -> 0 | N82: =-MIN(N80+N81,MAX(N112,0)) -> -453.4996 | O82: =-MIN(O80+O81,MAX(O112,0)) -> 0 | P82: =-MIN(P80+P81,MAX(P112,0)) -> -653.55236 | Q82: =-MIN(Q80+Q81,MAX(Q112,0)) -> -472.30948 | R82: =-MIN(R80+R81,MAX(R112,0)) -> -617.75017
C83: Ending NOL Balance: | D83: £ M | K83: =SUM(K80:K82) -> 2435.7698 | L83: =SUM(L80:L82) -> 2319.9969 | M83: =SUM(M80:M82) -> 2617.8105 | N83: =SUM(N80:N82) -> 2164.3109 | O83: =SUM(O80:O82) -> 2451.2588 | P83: =SUM(P80:P82) -> 1797.7064 | Q83: =SUM(Q80:Q82) -> 1325.3969 | R83: =SUM(R80:R82) -> 707.64676
C85: NOL-Adjusted Pre-Tax Income: | D85: £ M | L85: =L112+L82 -> 0 | M85: =M112+M82 -> -297.8136 | N85: =N112+N82 -> 0 | O85: =O112+O82 -> -286.94785 | P85: =P112+P82 -> 0 | Q85: =Q112+Q82 -> 0 | R85: =R112+R82 -> 0
C87: Cash Taxes Payable: | D87: £ M | L87: =-MAX(L85,0)*L61 -> 0 | M87: =-MAX(M85,0)*M61 -> 0 | N87: =-MAX(N85,0)*N61 -> 0 | O87: =-MAX(O85,0)*O61 -> 0 | P87: =-MAX(P85,0)*P61 -> 0 | Q87: =-MAX(Q85,0)*Q61 -> 0 | R87: =-MAX(R85,0)*R61 -> 0
C89: Deferred Taxes: | D89: £ M | L89: =L87-L113 -> 21.996856 | M89: =M87-M113 -> -56.584585 | N89: =N87-N113 -> 113.3749 | O89: =O87-O113 -> -71.736962 | P89: =P87-P113 -> 163.38809 | Q89: =Q87-Q113 -> 118.07737 | R89: =R87-R113 -> 154.43754
E91: =$E$25 -> Historical (Half-Years): | Q91: =$Q$25 -> Projected (Annual): | T91: =$T$25 -> Historical: | Z91: =$Q$25 -> Projected (Annual):
B92: Income Statement: | D92: =$D$5 -> Units: | E92: =$E$26 -> 43555 | F92: =$F$26 -> 43738 | G92: =$G$26 -> 43921 | H92: =$H$26 -> 44104 | I92: =$I$26 -> 44286 | J92: =$J$26 -> 44469 | K92: =$K$26 -> 44651 | L92: =$L$26 -> 44834 | M92: =$M$26 -> 45016 | N92: =$N$26 -> 45199 | O92: =$O$26 -> 45382 | P92: =$P$26 -> 45565 | Q92: =$Q$26 -> 45930 | R92: =$R$26 -> 46295 | T92: =$T$26 -> 43738 | U92: =$U$26 -> 44104 | V92: =$V$26 -> 44469 | W92: =$W$26 -> 44834 | X92: =$X$26 -> 45199 | Y92: =$Y$26 -> 45565 | Z92: =$Z$26 -> 45930 | AA92: =$AA$26 -> 46295
C94: Total Revenue: | D94: £ M | E94: =E43+E46 -> 2343 | F94: =F43+F46 -> 4042 | G94: =G43+G46 -> 2382 | H94: =H43+H46 -> 627 | I94: =I43+I46 -> 240 | J94: =J43+J46 -> 1218 | K94: =K43+K46 -> 1498 | L94: =L43+L46 -> 2651.6685 | ... R94: =R43+R46 -> 9845.6714 | T94: =SUMIF($E$23:$R$23,T$23,$E94:$R94) -> 6385 | U94: =SUMIF($E$23:$R$23,U$23,$E94:$R94) -> 3009 | V94: =SUMIF($E$23:$R$23,V$23,$E94:$R94) -> 1458 | W94: =SUMIF($E$23:$R$23,W$23,$E94:$R94) -> 4149.6685 | X94: =SUMIF($E$23:$R$23,X$23,$E94:$R94) -> 6085.7691 | Y94: =SUMIF($E$23:$R$23,Y$23,$E94:$R94) -> 7346.5005 | Z94: =SUMIF($E$23:$R$23,Z$23,$E94:$R94) -> 8536.502 | AA94: =SUMIF($E$23:$R$23,AA$23,$E94:$R94) -> 9845.6714
C95: (-) Non-Fuel Costs: | D95: £ M | E95: -1757 | F95: -2242 | G95: -1759 | H95: -887 | I95: -527 | J95: -985 | K95: -1357 | L95: =-L51*L29/Units -> -1679.79 | M95: =-M51*M29/Units -> -1776.0666 | N95: =-N51*N29/Units -> -2318.1102 | O95: =-O51*O29/Units -> -2073.6778 | P95: =-P51*P29/Units -> -2704.4619 | Q95: =-Q51*Q29/Units -> -5506.1698 | R95: =-R51*R29/Units -> -6281.6867 | T95: =SUMIF($E$23:$R$23,T$23,$E95:$R95) -> -3999 | U95: =SUMIF($E$23:$R$23,U$23,$E95:$R95) -> -2646 | V95: =SUMIF($E$23:$R$23,V$23,$E95:$R95) -> -1512 | W95: =SUMIF($E$23:$R$23,W$23,$E95:$R95) -> -3036.79 | X95: =SUMIF($E$23:$R$23,X$23,$E95:$R95) -> -4094.1768 | Y95: =SUMIF($E$23:$R$23,Y$23,$E95:$R95) -> -4778.1397 | Z95: =SUMIF($E$23:$R$23,Z$23,$E95:$R95) -> -5506.1698 | AA95: =SUMIF($E$23:$R$23,AA$23,$E95:$R95) -> -6281.6867
C96: (-) Fuel Costs: | D96: £ M | E96: -602 | F96: -814 | G96: -534 | H96: -187 | I96: -97 | J96: -274 | K96: -362 | L96: =-L53*L29/Units -> -527.934 | M96: =-M53*M29/Units -> -537.62016 | N96: =-N53*N29/Units -> -752.54592 | O96: =-O53*O29/Units -> -662.42484 | P96: =-P53*P29/Units -> -927.24408 | Q96: =-Q53*Q29/Units -> -1861.2405 | R96: =-R53*R29/Units -> -2128.7938 | T96: =SUMIF($E$23:$R$23,T$23,$E96:$R96) -> -1416 | U96: =SUMIF($E$23:$R$23,U$23,$E96:$R96) -> -721 | V96: =SUMIF($E$23:$R$23,V$23,$E96:$R96) -> -371 | W96: =SUMIF($E$23:$R$23,W$23,$E96:$R96) -> -889.934 | X96: =SUMIF($E$23:$R$23,X$23,$E96:$R96) -> -1290.1661 | Y96: =SUMIF($E$23:$R$23,Y$23,$E96:$R96) -> -1589.6689 | Z96: =SUMIF($E$23:$R$23,Z$23,$E96:$R96) -> -1861.2405 | AA96: =SUMIF($E$23:$R$23,AA$23,$E96:$R96) -> -2128.7938
C97: EBITDAR: | D97: £ M | E97: =SUM(E94:E96) -> -16 | F97: =SUM(F94:F96) -> 986 | G97: =SUM(G94:G96) -> 89 | H97: =SUM(H94:H96) -> -447 | I97: =SUM(I94:I96) -> -384 | J97: =SUM(J94:J96) -> -41 | K97: =SUM(K94:K96) -> -221 | L97: =SUM(L94:L96) -> 443.9445 | ... R97: =SUM(R94:R96) -> 1435.1909 | T97: =SUM(T94:T96) -> 970 | U97: =SUM(U94:U96) -> -358 | V97: =SUM(V94:V96) -> -425 | W97: =SUM(W94:W96) -> 222.9445 | X97: =SUM(X94:X96) -> 701.42619 | Y97: =SUM(Y94:Y96) -> 978.69196 | Z97: =SUM(Z94:Z96) -> 1169.0917 | AA97: =SUM(AA94:AA96) -> 1435.1909
C99: Lease and Depreciation Costs:
C100: (-) Lease Depreciation: | D100: £ M | E100: -115 | F100: -132 | G100: -123 | H100: -106 | I100: -93 | J100: =-222-I100 -> -129 | K100: -133 | L100: =-L58*L29/Units -> -143.982 | M100: =-M58*M29/Units -> -120.0045 | N100: =-N58*N29/Units -> -134.3832 | O100: =-O58*O29/Units -> -132.48497 | P100: =-P58*P29/Units -> -146.81365 | Q100: =-Q58*Q29/Units -> -310.20675 | R100: =-R58*R29/Units -> -348.98259 | T100: =SUMIF($E$23:$R$23,T$23,$E100:$R100) -> -247 | U100: =SUMIF($E$23:$R$23,U$23,$E100:$R100) -> -229 | V100: =SUMIF($E$23:$R$23,V$23,$E100:$R100) -> -222 | W100: =SUMIF($E$23:$R$23,W$23,$E100:$R100) -> -276.982 | X100: =SUMIF($E$23:$R$23,X$23,$E100:$R100) -> -254.3877 | Y100: =SUMIF($E$23:$R$23,Y$23,$E100:$R100) -> -279.29861 | Z100: =SUMIF($E$23:$R$23,Z$23,$E100:$R100) -> -310.20675 | AA100: =SUMIF($E$23:$R$23,AA$23,$E100:$R100) -> -348.98259
C101: (-) Impairments: | D101: £ M | E101: 0 | F101: 0 | G101: 0 | H101: -37 | I101: 0 | J101: 0 | K101: 0 | L101: 0 | M101: =L101 -> 0 | N101: =M101 -> 0 | O101: =N101 -> 0 | P101: =O101 -> 0 | Q101: =P101 -> 0 | R101: =Q101 -> 0 | T101: =SUMIF($E$23:$R$23,T$23,$E101:$R101) -> 0 | U101: =SUMIF($E$23:$R$23,U$23,$E101:$R101) -> -37 | V101: =SUMIF($E$23:$R$23,V$23,$E101:$R101) -> 0 | W101: =SUMIF($E$23:$R$23,W$23,$E101:$R101) -> 0 | X101: =SUMIF($E$23:$R$23,X$23,$E101:$R101) -> 0 | Y101: =SUMIF($E$23:$R$23,Y$23,$E101:$R101) -> 0 | Z101: =SUMIF($E$23:$R$23,Z$23,$E101:$R101) -> 0 | AA101: =SUMIF($E$23:$R$23,AA$23,$E101:$R101) -> 0
C102: (-) Depreciation & Amortisation: | D102: £ M | E102: -124 | F102: -133 | G102: -139 | H102: -136 | I102: =-2-204-11-I100 -> -124 | J102: =-5-456-24-I102-I100-J100 -> -139 | K102: =-1-265-12-K100 -> -145 | L102: =-L59*L29/Units -> -158.3802 | M102: =-M59*M29/Units -> -134.40504 | N102: =-N59*N29/Units -> -154.54068 | O102: =-O59*O29/Units -> -149.76562 | P102: =-P59*P29/Units -> -169.99475 | Q102: =-Q59*Q29/Units -> -356.73776 | R102: =-R59*R29/Units -> -401.32998 | T102: =SUMIF($E$23:$R$23,T$23,$E102:$R102) -> -257 | U102: =SUMIF($E$23:$R$23,U$23,$E102:$R102) -> -275 | V102: =SUMIF($E$23:$R$23,V$23,$E102:$R102) -> -263 | W102: =SUMIF($E$23:$R$23,W$23,$E102:$R102) -> -303.3802 | X102: =SUMIF($E$23:$R$23,X$23,$E102:$R102) -> -288.94572 | Y102: =SUMIF($E$23:$R$23,Y$23,$E102:$R102) -> -319.76036 | Z102: =SUMIF($E$23:$R$23,Z$23,$E102:$R102) -> -356.73776 | AA102: =SUMIF($E$23:$R$23,AA$23,$E102:$R102) -> -401.32998
C103: Total Lease and Depreciation Costs: | D103: £ M | E103: =SUM(E100:E102) -> -239 | F103: =SUM(F100:F102) -> -265 | G103: =SUM(G100:G102) -> -262 | H103: =SUM(H100:H102) -> -279 | I103: =SUM(I100:I102) -> -217 | J103: =SUM(J100:J102) -> -268 | K103: =SUM(K100:K102) -> -278 | L103: =SUM(L100:L102) -> -302.3622 | ... R103: =SUM(R100:R102) -> -750.31258 | T103: =SUM(T100:T102) -> -504 | U103: =SUM(U100:U102) -> -541 | V103: =SUM(V100:V102) -> -485 | W103: =SUM(W100:W102) -> -580.3622 | X103: =SUM(X100:X102) -> -543.33342 | Y103: =SUM(Y100:Y102) -> -599.05898 | Z103: =SUM(Z100:Z102) -> -666.94451 | AA103: =SUM(AA100:AA102) -> -750.31258
C105: Operating Income (EBIT): | D105: £ M | E105: =E97+E103 -> -255 | F105: =F97+F103 -> 721 | G105: =G97+G103 -> -173 | H105: =H97+H103 -> -726 | I105: =I97+I103 -> -601 | J105: =J97+J103 -> -309 | K105: =K97+K103 -> -499 | L105: =L97+L103 -> 141.5823 | ... R105: =R97+R103 -> 684.87834 | T105: =T97+T103 -> 466 | U105: =U97+U103 -> -899 | V105: =V97+V103 -> -910 | W105: =W97+W103 -> -357.4177 | X105: =X97+X103 -> 158.09277 | Y105: =Y97+Y103 -> 379.63299 | Z105: =Z97+Z103 -> 502.14718 | AA105: =AA97+AA103 -> 684.87834
C107: Financing Costs:
C108: (+) Interest Income: | D108: £ M | E108: 14 | F108: 10 | G108: 77 | H108: 40 | I108: 51 | J108: 32 | K108: 8 | L108: =L195 -> 21.90625 | M108: =M195 -> 35.124223 | N108: =N195 -> 41.377773 | O108: =O195 -> 44.186564 | P108: =P195 -> 32.008117 | Q108: =Q195 -> 54.155753 | R108: =R195 -> 55.18251 | T108: =SUMIF($E$23:$R$23,T$23,$E108:$R108) -> 24 | U108: =SUMIF($E$23:$R$23,U$23,$E108:$R108) -> 117 | V108: =SUMIF($E$23:$R$23,V$23,$E108:$R108) -> 83 | W108: =SUMIF($E$23:$R$23,W$23,$E108:$R108) -> 29.90625 | X108: =SUMIF($E$23:$R$23,X$23,$E108:$R108) -> 76.501996 | Y108: =SUMIF($E$23:$R$23,Y$23,$E108:$R108) -> 76.194681 | Z108: =SUMIF($E$23:$R$23,Z$23,$E108:$R108) -> 54.155753 | AA108: =SUMIF($E$23:$R$23,AA$23,$E108:$R108) -> 55.18251
C109: (-) Interest Expense: | D109: £ M | E109: -31 | F109: -29 | G109: -257 | H109: -234 | I109: -95 | J109: -114 | K109: -66 | L109: =L196 -> -47.715625 | M109: =M196 -> -40.846875 | N109: =N196 -> -38.061895 | O109: =O196 -> -38.515439 | P109: =P196 -> -50.707717 | Q109: =Q196 -> -83.993448 | R109: =R196 -> -122.31068 | T109: =SUMIF($E$23:$R$23,T$23,$E109:$R109) -> -60 | U109: =SUMIF($E$23:$R$23,U$23,$E109:$R109) -> -491 | V109: =SUMIF($E$23:$R$23,V$23,$E109:$R109) -> -209 | W109: =SUMIF($E$23:$R$23,W$23,$E109:$R109) -> -113.71563 | X109: =SUMIF($E$23:$R$23,X$23,$E109:$R109) -> -78.90877 | Y109: =SUMIF($E$23:$R$23,Y$23,$E109:$R109) -> -89.223155 | Z109: =SUMIF($E$23:$R$23,Z$23,$E109:$R109) -> -83.993448 | AA109: =SUMIF($E$23:$R$23,AA$23,$E109:$R109) -> -122.31068
C110: Net Financing Costs: | D110: £ M | E110: =SUM(E108:E109) -> -17 | F110: =SUM(F108:F109) -> -19 | G110: =SUM(G108:G109) -> -180 | H110: =SUM(H108:H109) -> -194 | I110: =SUM(I108:I109) -> -44 | J110: =SUM(J108:J109) -> -82 | K110: =SUM(K108:K109) -> -58 | L110: =SUM(L108:L109) -> -25.809375 | ... R110: =SUM(R108:R109) -> -67.128173 | T110: =SUM(T108:T109) -> -36 | U110: =SUM(U108:U109) -> -374 | V110: =SUM(V108:V109) -> -126 | W110: =SUM(W108:W109) -> -83.809375 | X110: =SUM(X108:X109) -> -2.4067745 | Y110: =SUM(Y108:Y109) -> -13.028474 | Z110: =SUM(Z108:Z109) -> -29.837695 | AA110: =SUM(AA108:AA109) -> -67.128173
C112: Pre-Tax Income: | D112: £ M | E112: =E105+E110 -> -272 | F112: =F105+F110 -> 702 | G112: =G105+G110 -> -353 | H112: =H105+H110 -> -920 | I112: =I105+I110 -> -645 | J112: =J105+J110 -> -391 | K112: =K105+K110 -> -557 | L112: =L105+L110 -> 115.77292 | ... R112: =R105+R110 -> 617.75017 | T112: =T105+T110 -> 430 | U112: =U105+U110 -> -1273 | V112: =V105+V110 -> -1036 | W112: =W105+W110 -> -441.22708 | X112: =X105+X110 -> 155.68599 | Y112: =Y105+Y110 -> 366.60451 | Z112: =Z105+Z110 -> 472.30948 | AA112: =AA105+AA110 -> 617.75017
C113: (-) Income Taxes: | D113: £ M | E113: 54 | F113: -135 | G113: 29 | H113: 165 | I113: 96 | J113: 82 | K113: 126 | L113: =-L112*L61 -> -21.996856 | M113: =-M112*M61 -> 56.584585 | N113: =-N112*N61 -> -113.3749 | O113: =-O112*O61 -> 71.736962 | P113: =-P112*P61 -> -163.38809 | Q113: =-Q112*Q61 -> -118.07737 | R113: =-R112*R61 -> -154.43754 | T113: =SUMIF($E$23:$R$23,T$23,$E113:$R113) -> -81 | U113: =SUMIF($E$23:$R$23,U$23,$E113:$R113) -> 194 | V113: =SUMIF($E$23:$R$23,V$23,$E113:$R113) -> 178 | W113: =SUMIF($E$23:$R$23,W$23,$E113:$R113) -> 104.00314 | X113: =SUMIF($E$23:$R$23,X$23,$E113:$R113) -> -56.790314 | Y113: =SUMIF($E$23:$R$23,Y$23,$E113:$R113) -> -91.651128 | Z113: =SUMIF($E$23:$R$23,Z$23,$E113:$R113) -> -118.07737 | AA113: =SUMIF($E$23:$R$23,AA$23,$E113:$R113) -> -154.43754
C114: Net Income: | D114: £ M | E114: =SUM(E112:E113) -> -218 | F114: =SUM(F112:F113) -> 567 | G114: =SUM(G112:G113) -> -324 | H114: =SUM(H112:H113) -> -755 | I114: =SUM(I112:I113) -> -549 | J114: =SUM(J112:J113) -> -309 | K114: =SUM(K112:K113) -> -431 | L114: =SUM(L112:L113) -> 93.776069 | ... R114: =SUM(R112:R113) -> 463.31263 | T114: =SUM(T112:T113) -> 349 | U114: =SUM(U112:U113) -> -1079 | V114: =SUM(V112:V113) -> -858 | W114: =SUM(W112:W113) -> -337.22393 | X114: =SUM(X112:X113) -> 98.895678 | Y114: =SUM(Y112:Y113) -> 274.95338 | Z114: =SUM(Z112:Z113) -> 354.23211 | AA114: =SUM(AA112:AA113) -> 463.31263
E116: =$E$25 -> Historical (Half-Years): | Q116: =$Q$25 -> Projected (Annual): | T116: =$T$25 -> Historical: | Z116: =$Q$25 -> Projected (Annual):
B117: Balance Sheet: | D117: =$D$5 -> Units: | E117: =$E$26 -> 43555 | F117: =$F$26 -> 43738 | G117: =$G$26 -> 43921 | H117: =$H$26 -> 44104 | I117: =$I$26 -> 44286 | J117: =$J$26 -> 44469 | K117: =$K$26 -> 44651 | L117: =$L$26 -> 44834 | M117: =$M$26 -> 45016 | N117: =$N$26 -> 45199 | O117: =$O$26 -> 45382 | P117: =$P$26 -> 45565 | Q117: =$Q$26 -> 45930 | R117: =$R$26 -> 46295 | T117: =$T$26 -> 43738 | U117: =$U$26 -> 44104 | V117: =$V$26 -> 44469 | W117: =$W$26 -> 44834 | X117: =$X$26 -> 45199 | Y117: =$Y$26 -> 45565 | Z117: =$Z$26 -> 45930 | AA117: =$AA$26 -> 46295
B118: ASSETS: | T118: =$B118 -> ASSETS:
C119: Cash & Equivalents: | D119: £ M | E119: 1280 | F119: 1576 | G119: 1388 | H119: 2316 | I119: 2335 | J119: 3536 | K119: 3505 | L119: =L171 -> 3512.4223 | M119: =M171 -> 2758.5182 | N119: =N171 -> 2945.7709 | O119: =O171 -> 2133.8745 | P119: =P171 -> 1969.3001 | Q119: =Q171 -> 2207.3004 | R119: =R171 -> 2469.1343 | T119: =INDEX($E119:$R119,1,MATCH(T$117,$E$117:$R$117,0)) -> 1576 | U119: =INDEX($E119:$R119,1,MATCH(U$117,$E$117:$R$117,0)) -> 2316 | V119: =INDEX($E119:$R119,1,MATCH(V$117,$E$117:$R$117,0)) -> 3536 | W119: =INDEX($E119:$R119,1,MATCH(W$117,$E$117:$R$117,0)) -> 3512.4223 | X119: =INDEX($E119:$R119,1,MATCH(X$117,$E$117:$R$117,0)) -> 2945.7709 | Y119: =INDEX($E119:$R119,1,MATCH(Y$117,$E$117:$R$117,0)) -> 1969.3001 | Z119: =INDEX($E119:$R119,1,MATCH(Z$117,$E$117:$R$117,0)) -> 2207.3004 | AA119: =INDEX($E119:$R119,1,MATCH(AA$117,$E$117:$R$117,0)) -> 2469.1343
C120: Other Assets: | D120: £ M | E120: 251 | F120: 281 | G120: -347 | H120: -135 | I120: 128 | J120: 421 | K120: 711 | L120: =K120-L147 -> 689.00314 | M120: =L120-M147 -> 745.58773 | N120: =M120-N147 -> 632.21283 | O120: =N120-O147 -> 703.94979 | P120: =O120-P147 -> 540.5617 | Q120: =P120-Q147 -> 422.48433 | R120: =Q120-R147 -> 268.04679 | T120: =INDEX($E120:$R120,1,MATCH(T$117,$E$117:$R$117,0)) -> 281 | U120: =INDEX($E120:$R120,1,MATCH(U$117,$E$117:$R$117,0)) -> -135 | V120: =INDEX($E120:$R120,1,MATCH(V$117,$E$117:$R$117,0)) -> 421 | W120: =INDEX($E120:$R120,1,MATCH(W$117,$E$117:$R$117,0)) -> 689.00314 | X120: =INDEX($E120:$R120,1,MATCH(X$117,$E$117:$R$117,0)) -> 632.21283 | Y120: =INDEX($E120:$R120,1,MATCH(Y$117,$E$117:$R$117,0)) -> 540.5617 | Z120: =INDEX($E120:$R120,1,MATCH(Z$117,$E$117:$R$117,0)) -> 422.48433 | AA120: =INDEX($E120:$R120,1,MATCH(AA$117,$E$117:$R$117,0)) -> 268.04679
C121: Accounts Receivable: | D121: £ M | E121: 335 | F121: 302 | G121: 332 | H121: 193 | I121: 150 | J121: 291 | K121: 336 | L121: =SUM(K94:L94)*L65 -> 414.96685 | M121: =SUM(L94:M94)*M65 -> 394.21391 | N121: =SUM(M94:N94)*N65 -> 426.00383 | O121: =SUM(N94:O94)*O65 -> 392.12988 | P121: =SUM(O94:P94)*P65 -> 367.32503 | Q121: =Q94*Q65 -> 426.8251 | R121: =R94*R65 -> 492.28357 | T121: =INDEX($E121:$R121,1,MATCH(T$117,$E$117:$R$117,0)) -> 302 | U121: =INDEX($E121:$R121,1,MATCH(U$117,$E$117:$R$117,0)) -> 193 | V121: =INDEX($E121:$R121,1,MATCH(V$117,$E$117:$R$117,0)) -> 291 | W121: =INDEX($E121:$R121,1,MATCH(W$117,$E$117:$R$117,0)) -> 414.96685 | X121: =INDEX($E121:$R121,1,MATCH(X$117,$E$117:$R$117,0)) -> 426.00383 | Y121: =INDEX($E121:$R121,1,MATCH(Y$117,$E$117:$R$117,0)) -> 367.32503 | Z121: =INDEX($E121:$R121,1,MATCH(Z$117,$E$117:$R$117,0)) -> 426.8251 | AA121: =INDEX($E121:$R121,1,MATCH(AA$117,$E$117:$R$117,0)) -> 492.28357
C122: Net PP&E & Intangible Assets: | D122: £ M | E122: 4837 | F122: 5292 | G122: 5592 | H122: 5018 | I122: 4422 | J122: 4361 | K122: 4738 | L122: =K122-L145-L153-L154 -> 4905.979 | M122: =L122-M145-M153-M154 -> 5121.9871 | N122: =M122-N145-N153-N154 -> 5390.7535 | O122: =N122-O145-O153-O154 -> 5701.8052 | P122: =O122-P145-P153-P154 -> 6111.338 | Q122: =P122-Q145-Q153-Q154 -> 7150.5306 | R122: =Q122-R145-R153-R154 -> 8371.9697 | T122: =INDEX($E122:$R122,1,MATCH(T$117,$E$117:$R$117,0)) -> 5292 | U122: =INDEX($E122:$R122,1,MATCH(U$117,$E$117:$R$117,0)) -> 5018 | V122: =INDEX($E122:$R122,1,MATCH(V$117,$E$117:$R$117,0)) -> 4361 | W122: =INDEX($E122:$R122,1,MATCH(W$117,$E$117:$R$117,0)) -> 4905.979 | X122: =INDEX($E122:$R122,1,MATCH(X$117,$E$117:$R$117,0)) -> 5390.7535 | Y122: =INDEX($E122:$R122,1,MATCH(Y$117,$E$117:$R$117,0)) -> 6111.338 | Z122: =INDEX($E122:$R122,1,MATCH(Z$117,$E$117:$R$117,0)) -> 7150.5306 | AA122: =INDEX($E122:$R122,1,MATCH(AA$117,$E$117:$R$117,0)) -> 8371.9697
C123: ROU Assets: | D123: £ M | E123: 572 | F123: 502 | G123: 468 | H123: 644 | I123: 1078 | J123: 1096 | K123: 1045 | L123: =K123-L144-L155 -> 997.006 | M123: =L123-M144-M155 -> 997.006 | N123: =M123-N144-N155 -> 1017.1635 | O123: =N123-O144-O155 -> 1040.2043 | P123: =O123-P144-P155 -> 1086.5665 | Q123: =P123-Q144-Q155 -> 1210.6492 | R123: =Q123-R144-R155 -> 1385.1405 | T123: =INDEX($E123:$R123,1,MATCH(T$117,$E$117:$R$117,0)) -> 502 | U123: =INDEX($E123:$R123,1,MATCH(U$117,$E$117:$R$117,0)) -> 644 | V123: =INDEX($E123:$R123,1,MATCH(V$117,$E$117:$R$117,0)) -> 1096 | W123: =INDEX($E123:$R123,1,MATCH(W$117,$E$117:$R$117,0)) -> 997.006 | X123: =INDEX($E123:$R123,1,MATCH(X$117,$E$117:$R$117,0)) -> 1017.1635 | Y123: =INDEX($E123:$R123,1,MATCH(Y$117,$E$117:$R$117,0)) -> 1086.5665 | Z123: =INDEX($E123:$R123,1,MATCH(Z$117,$E$117:$R$117,0)) -> 1210.6492 | AA123: =INDEX($E123:$R123,1,MATCH(AA$117,$E$117:$R$117,0)) -> 1385.1405
C124: TOTAL ASSETS: | D124: £ M | E124: =SUM(E119:E123) -> 7275 | F124: =SUM(F119:F123) -> 7953 | G124: =SUM(G119:G123) -> 7433 | H124: =SUM(H119:H123) -> 8036 | I124: =SUM(I119:I123) -> 8113 | J124: =SUM(J119:J123) -> 9705 | K124: =SUM(K119:K123) -> 10335 | L124: =SUM(L119:L123) -> 10519.377 | ... R124: =SUM(R119:R123) -> 12986.575 | T124: =SUM(T119:T123) -> 7953 | U124: =SUM(U119:U123) -> 8036 | V124: =SUM(V119:V123) -> 9705 | W124: =SUM(W119:W123) -> 10519.377 | X124: =SUM(X119:X123) -> 10411.905 | Y124: =SUM(Y119:Y123) -> 10075.091 | Z124: =SUM(Z119:Z123) -> 11417.79 | AA124: =SUM(AA119:AA123) -> 12986.575
B126: LIABILITIES & EQUITY: | T126: =$B126 -> LIABILITIES & EQUITY:
C127: Deferred Revenue: | D127: £ M | E127: 1726 | F127: 1069 | G127: 974 | H127: 614 | I127: 662 | J127: 846 | K127: 1780 | L127: =SUM(K94:L94)*L66 -> 2282.3177 | M127: =SUM(L94:M94)*M66 -> 2217.4532 | N127: =SUM(M94:N94)*N66 -> 2130.0192 | O127: =SUM(N94:O94)*O66 -> 1633.8745 | P127: =SUM(O94:P94)*P66 -> 1469.3001 | Q127: =Q94*Q66 -> 1707.3004 | R127: =R94*R66 -> 1969.1343 | T127: =INDEX($E127:$R127,1,MATCH(T$117,$E$117:$R$117,0)) -> 1069 | U127: =INDEX($E127:$R127,1,MATCH(U$117,$E$117:$R$117,0)) -> 614 | V127: =INDEX($E127:$R127,1,MATCH(V$117,$E$117:$R$117,0)) -> 846 | W127: =INDEX($E127:$R127,1,MATCH(W$117,$E$117:$R$117,0)) -> 2282.3177 | X127: =INDEX($E127:$R127,1,MATCH(X$117,$E$117:$R$117,0)) -> 2130.0192 | Y127: =INDEX($E127:$R127,1,MATCH(Y$117,$E$117:$R$117,0)) -> 1469.3001 | Z127: =INDEX($E127:$R127,1,MATCH(Z$117,$E$117:$R$117,0)) -> 1707.3004 | AA127: =INDEX($E127:$R127,1,MATCH(AA$117,$E$117:$R$117,0)) -> 1969.1343
C128: Payables: | D128: £ M | E128: 817 | F128: 1050 | G128: 1660 | H128: 1242 | I128: 801 | J128: 1128 | K128: 1368 | L128: =-SUM(K95:L96)*L67 -> 1570.6896 | M128: =-SUM(L95:M96)*M67 -> 1582.4938 | N128: =-SUM(M95:N96)*N67 -> 1615.3029 | O128: =-SUM(N95:O96)*O67 -> 1451.6897 | P128: =-SUM(O95:P96)*P67 -> 1591.9521 | Q128: =-SUM(Q95:Q96)*Q67 -> 1841.8526 | R128: =-SUM(R95:R96)*R67 -> 2102.6201 | T128: =INDEX($E128:$R128,1,MATCH(T$117,$E$117:$R$117,0)) -> 1050 | U128: =INDEX($E128:$R128,1,MATCH(U$117,$E$117:$R$117,0)) -> 1242 | V128: =INDEX($E128:$R128,1,MATCH(V$117,$E$117:$R$117,0)) -> 1128 | W128: =INDEX($E128:$R128,1,MATCH(W$117,$E$117:$R$117,0)) -> 1570.6896 | X128: =INDEX($E128:$R128,1,MATCH(X$117,$E$117:$R$117,0)) -> 1615.3029 | Y128: =INDEX($E128:$R128,1,MATCH(Y$117,$E$117:$R$117,0)) -> 1591.9521 | Z128: =INDEX($E128:$R128,1,MATCH(Z$117,$E$117:$R$117,0)) -> 1841.8526 | AA128: =INDEX($E128:$R128,1,MATCH(AA$117,$E$117:$R$117,0)) -> 2102.6201
C129: Other Liabilities: | D129: £ M | E129: 735 | F129: 947 | G129: 852 | H129: 840 | I129: 718 | J129: 646 | K129: 646 | L129: =-SUM(K95:L96)*L68 -> 785.3448 | M129: =-SUM(L95:M96)*M68 -> 904.28215 | N129: =-SUM(M95:N96)*N68 -> 942.26 | O129: =-SUM(N95:O96)*O68 -> 1016.1828 | P129: =-SUM(O95:P96)*P68 -> 1082.5275 | Q129: =-SUM(Q95:Q96)*Q68 -> 1252.4598 | R129: =-SUM(R95:R96)*R68 -> 1429.7817 | T129: =INDEX($E129:$R129,1,MATCH(T$117,$E$117:$R$117,0)) -> 947 | U129: =INDEX($E129:$R129,1,MATCH(U$117,$E$117:$R$117,0)) -> 840 | V129: =INDEX($E129:$R129,1,MATCH(V$117,$E$117:$R$117,0)) -> 646 | W129: =INDEX($E129:$R129,1,MATCH(W$117,$E$117:$R$117,0)) -> 785.3448 | X129: =INDEX($E129:$R129,1,MATCH(X$117,$E$117:$R$117,0)) -> 942.26 | Y129: =INDEX($E129:$R129,1,MATCH(Y$117,$E$117:$R$117,0)) -> 1082.5275 | Z129: =INDEX($E129:$R129,1,MATCH(Z$117,$E$117:$R$117,0)) -> 1252.4598 | AA129: =INDEX($E129:$R129,1,MATCH(AA$117,$E$117:$R$117,0)) -> 1429.7817
C130: Lease Liabilities: | D130: £ M | E130: 623 | F130: 578 | G130: 536 | H130: 710 | I130: 1027 | J130: 1079 | K130: 1055 | L130: =K130+L163+L164 -> 1055 | M130: =L130+M163+M164 -> 1079.0009 | N130: =M130+N163+N164 -> 1099.1584 | O130: =N130+O163+O164 -> 1139.4799 | P130: =O130+P163+P164 -> 1170.388 | Q130: =P130+Q163+Q164 -> 1263.4501 | R130: =Q130+R163+R164 -> 1403.0431 | T130: =INDEX($E130:$R130,1,MATCH(T$117,$E$117:$R$117,0)) -> 578 | U130: =INDEX($E130:$R130,1,MATCH(U$117,$E$117:$R$117,0)) -> 710 | V130: =INDEX($E130:$R130,1,MATCH(V$117,$E$117:$R$117,0)) -> 1079 | W130: =INDEX($E130:$R130,1,MATCH(W$117,$E$117:$R$117,0)) -> 1055 | X130: =INDEX($E130:$R130,1,MATCH(X$117,$E$117:$R$117,0)) -> 1099.1584 | Y130: =INDEX($E130:$R130,1,MATCH(Y$117,$E$117:$R$117,0)) -> 1170.388 | Z130: =INDEX($E130:$R130,1,MATCH(Z$117,$E$117:$R$117,0)) -> 1263.4501 | AA130: =INDEX($E130:$R130,1,MATCH(AA$117,$E$117:$R$117,0)) -> 1403.0431
C131: Debt: | D131: £ M | E131: 858 | F131: 1324 | G131: 1319 | H131: 2731 | I131: 3323 | J131: 3367 | K131: 3046 | L131: =K131+L160 -> 2261 | M131: =L131+M160 -> 1881 | N131: =M131+N160 -> 1881 | O131: =N131+O160 -> 2227.2882 | P131: =O131+P160 -> 1708.915 | Q131: =P131+Q160 -> 2015.0144 | R131: =Q131+R160 -> 2392.293 | T131: =INDEX($E131:$R131,1,MATCH(T$117,$E$117:$R$117,0)) -> 1324 | U131: =INDEX($E131:$R131,1,MATCH(U$117,$E$117:$R$117,0)) -> 2731 | V131: =INDEX($E131:$R131,1,MATCH(V$117,$E$117:$R$117,0)) -> 3367 | W131: =INDEX($E131:$R131,1,MATCH(W$117,$E$117:$R$117,0)) -> 2261 | X131: =INDEX($E131:$R131,1,MATCH(X$117,$E$117:$R$117,0)) -> 1881 | Y131: =INDEX($E131:$R131,1,MATCH(Y$117,$E$117:$R$117,0)) -> 1708.915 | Z131: =INDEX($E131:$R131,1,MATCH(Z$117,$E$117:$R$117,0)) -> 2015.0144 | AA131: =INDEX($E131:$R131,1,MATCH(AA$117,$E$117:$R$117,0)) -> 2392.293
C132: TOTAL LIABILITIES: | D132: £ M | E132: =SUM(E127:E131) -> 4759 | F132: =SUM(F127:F131) -> 4968 | G132: =SUM(G127:G131) -> 5341 | H132: =SUM(H127:H131) -> 6137 | I132: =SUM(I127:I131) -> 6531 | J132: =SUM(J127:J131) -> 7066 | K132: =SUM(K127:K131) -> 7895 | L132: =SUM(L127:L131) -> 7954.3521 | ... R132: =SUM(R127:R131) -> 9296.8722 | T132: =SUM(T127:T131) -> 4968 | U132: =SUM(U127:U131) -> 6137 | V132: =SUM(V127:V131) -> 7066 | W132: =SUM(W127:W131) -> 7954.3521 | X132: =SUM(X127:X131) -> 7667.7404 | Y132: =SUM(Y127:Y131) -> 7023.0827 | Z132: =SUM(Z127:Z131) -> 8080.0771 | AA132: =SUM(AA127:AA131) -> 9296.8722
C134: EQUITY: | D134: £ M | E134: 2516 | F134: 2985 | G134: 2092 | H134: 1899 | I134: 1582 | J134: 2639 | K134: 2440 | L134: =K134+L143+L146+L148+L159+L161+L162+L167 -> 2565.0252 | M134: =L134+M143+M146+M148+M159+M161+M162+M167 -> 2353.0829 | N134: =M134+N143+N146+N148+N159+N161+N162+N167 -> 2744.1641 | O134: =N134+O143+O146+O148+O159+O161+O162+O167 -> 2503.4486 | P134: =O134+P143+P146+P148+P159+P161+P162+P167 -> 3052.0086 | Q134: =P134+Q143+Q146+Q148+Q159+Q161+Q162+Q167 -> 3337.7125 | R134: =Q134+R143+R146+R148+R159+R161+R162+R167 -> 3689.7027 | T134: =INDEX($E134:$R134,1,MATCH(T$117,$E$117:$R$117,0)) -> 2985 | U134: =INDEX($E134:$R134,1,MATCH(U$117,$E$117:$R$117,0)) -> 1899 | V134: =INDEX($E134:$R134,1,MATCH(V$117,$E$117:$R$117,0)) -> 2639 | W134: =INDEX($E134:$R134,1,MATCH(W$117,$E$117:$R$117,0)) -> 2565.0252 | X134: =INDEX($E134:$R134,1,MATCH(X$117,$E$117:$R$117,0)) -> 2744.1641 | Y134: =INDEX($E134:$R134,1,MATCH(Y$117,$E$117:$R$117,0)) -> 3052.0086 | Z134: =INDEX($E134:$R134,1,MATCH(Z$117,$E$117:$R$117,0)) -> 3337.7125 | AA134: =INDEX($E134:$R134,1,MATCH(AA$117,$E$117:$R$117,0)) -> 3689.7027
...

Sheet DCF
B2: ="DCF Analysis - "&Company_Name -> DCF Analysis - easyJet plc
B3: =Public_Comps!$B$3 -> (£ GBP in Millions Except Per Share Amounts in GBP as Stated)
B6: =Company_Name&" - DCF Assumptions & Output:" -> easyJet plc - DCF Assumptions & Output: | D6: Units:
C8: Operating Scenario: | D8: Name | E8: Base | H8: Terminal Value - Multiples Method: | M8: Terminal Value - Perpetuity Growth Method:
C9: Company Name: | D9: Name | E9: =Company_Name -> easyJet plc
H10: Median CY23 TEV / EBITDA of Comps: | K10: =Public_Comps!S38 -> 5.8767237 | M10: Expected Long-Term GDP Growth: | P10: 0.02
C11: Valuation Date: | D11: Date | E11: =TODAY() -> 45765 | H11: Median CY23 TEV / EBITDA of Target: | K11: =Public_Comps!S42 -> 4.7911753
C12: Stub Period Fraction: | D12: # | E12: =_xlfn.DAYS(H43,Val_Date)/_xlfn.DAYS(H43,G43) -> -2.5506849
H13: Baseline Terminal EBITDA Multiple: | K13: =INDEX(K14:K16,MATCH(Scenario,$H14:$H16,0),1) -> 4.8960241 | M13: Baseline Terminal FCF Growth Rate: | P13: =INDEX(P14:P16,MATCH(Scenario,$M14:$M16,0),1) -> 0.01
C14: Current Share Price: | D14: £ / Share | E14: 4.531 | H14: =EZJ!$C$31 -> Base | K14: 4.8960241 | M14: =EZJ!$C$31 -> Base | P14: 0.01
C15: Diluted Shares Outstanding: | D15: M Shares | E15: 759 | H15: =EZJ!$C$32 -> Downside | K15: 4.3090372 | M15: =EZJ!$C$32 -> Downside | P15: 0.005
H16: =EZJ!$C$33 -> XT Downside | K16: 3.8878596 | M16: =EZJ!$C$33 -> XT Downside | P16: 0
C17: Discount Rate (WACC): | D17: % | E17: =WACC!L41 -> 0.11585847
H18: Baseline Terminal Value: | K18: =K13*Q135 -> 11341.839 | M18: Baseline Terminal Value: | P18: =Q122*(1+P13)/(Discount_Rate-P13) -> 7644.4092
C19: Current Equity Value: | D19: £ M | E19: =Share_Price*Diluted_Shares -> 3439.029 | H19: Implied Terminal FCF Growth Rate: | K19: =(K18*Discount_Rate-Q122)/(K18+Q122) -> 0.042232773 | M19: Implied Terminal EBITDA Multiple: | P19: =P18/Q135 -> 3.2999245
C20: (-) Cash & Investments: | D20: £ M | E20: =-EZJ!K119 -> -3505
C21: (-) Net Operating Losses: | D21: £ M | E21: =-EZJ!K83*Tax_Rate -> -608.94246 | H21: (+) PV of Terminal Value: | K21: =K18*Q129 -> 5592.9032 | M21: (+) PV of Terminal Value: | P21: =P18*Q130 -> 3982.0097
C22: (+) Total Debt: | D22: £ M | E22: =EZJ!K131 -> 3046 | H22: (+) PV of Year 10 NOL Balance: | K22: =$Q$102*Tax_Rate*$Q$129 -> 0 | M22: (+) PV of Year 10 NOL Balance: | P22: =$Q$102*Tax_Rate*$Q$130 -> 0
C23: (+) Preferred Stock: | D23: £ M | E23: 0 | H23: (+) PV of UFCFs: | K23: =SUM($H$127:$Q$127) -> 1417.8541 | M23: (+) PV of UFCFs: | P23: =SUM($H$127:$Q$127) -> 1417.8541
C24: (+) Finance & Operating Leases: | D24: £ M | E24: =EZJ!K130 -> 1055 | H24: Implied Enterprise Value: | K24: =SUM(K21:K23) -> 7010.7573 | M24: Implied Enterprise Value: | P24: =SUM(P21:P23) -> 5399.8638
C25: (+) Noncontrolling Interests: | D25: £ M | E25: 0
C26: (+) Unfunded Pensions: | D26: £ M | E26: 0 | H26: % of Implied TEV from Terminal Value: | K26: =K21/K24 -> 0.7977602 | M26: % of Implied TEV from Terminal Value: | P26: =P21/P24 -> 0.7374278
C27: Current Enterprise Value Incl. Leases: | D27: £ M | E27: =SUM(E19:E26) -> 3426.0865
H28: (+) Cash & Investments: | K28: =-E20 -> 3505 | M28: =H28 -> (+) Cash & Investments: | P28: =K28 -> 3505
E29: P/E | F29: =Share_Price/F33 -> -37.345067 | H29: (+) Net Operating Losses: | K29: 0 | M29: =H29 -> (+) Net Operating Losses: | P29: 0
E30: P/B | F30: =Share_Price/F35 -> 0.61903618 | H30: (-) Total Debt: | K30: =-E22 -> -3046 | M30: =H30 -> (-) Total Debt: | P30: =K30 -> -3046
E31: TTM EPS | F31: =SUM(EZJ!O114:P114)/Diluted_Shares -> 0.36225742 | H31: (-) Preferred Stock: | K31: =-E23 -> 0 | M31: =H31 -> (-) Preferred Stock: | P31: =K31 -> 0
E32: Last Year EPS | F32: =SUM(EZJ!O114:P114)/Diluted_Shares -> 0.36225742 | H32: (-) Finance & Operating Leases: | K32: 0 | M32: =H32 -> (-) Finance & Operating Leases: | P32: 0
E33: 10 Yr Avg EPS | F33: =AVERAGE(EZJ!E114:Q114)/Diluted_Shares -> -0.12132794 | H33: (-) Noncontrolling Interests: | K33: =-E25 -> 0 | M33: =H33 -> (-) Noncontrolling Interests: | P33: =K33 -> 0
E34: FWRD 12 M EPS | F34: =SUM(EZJ!Q114:R114)/Diluted_Shares -> 1.077134 | H34: (-) Unfunded Pensions: | K34: =-E26 -> 0 | M34: =H34 -> (-) Unfunded Pensions: | P34: =K34 -> 0
E35: BVPS | F35: =F36/K37 -> 7.319443 | H35: Implied Equity Value: | K35: =K24+SUM(K28:K34) -> 7469.7573 | M35: Implied Equity Value: | P35: =P24+SUM(P28:P34) -> 5858.8638
E36: Shareholders Equity | F36: =SUM(EZJ!O124,EZJ!P124)-SUM(EZJ!O132:'EZJ'!P132) -> 5555.4572
H37: Diluted Shares Outstanding: | K37: =Diluted_Shares -> 759 | M37: Diluted Shares Outstanding: | P37: =Diluted_Shares -> 759
H39: Implied Share Price from DCF: | K39: =MAX(0,K35/K37) -> 9.8415775 | L39: =K35/758 -> 9.8545611 | M39: Implied Share Price from DCF: | P39: =MAX(0,P35/P37) -> 7.7191882
H40: Premium / (Discount) to Current: | K40: =K39/Share_Price-1 -> 1.1720542 | M40: Premium / (Discount) to Current: | P40: =P39/Share_Price-1 -> 0.70363897
G42: Historical: | J42: 0
B43: Assumptions and Drivers: | D43: =$D$6 -> Units: | E43: =EZJ!T26 -> 43738 | F43: =EZJ!U26 -> 44104 | G43: =EZJ!V26 -> 44469 | H43: =EZJ!W26 -> 44834 | I43: =EZJ!X26 -> 45199 | J43: =EZJ!Y26 -> 45565 | K43: =EZJ!Z26 -> 45930 | L43: =EZJ!AA26 -> 46295 | M43: =EOMONTH(L43,12) -> 46660 | N43: =EOMONTH(M43,12) -> 47026 | O43: =EOMONTH(N43,12) -> 47391 | P43: =EOMONTH(O43,12) -> 47756 | Q43: =EOMONTH(P43,12) -> 48121
C45: Available Seat Kilometres (ASK): | D45: Millions KM | E45: =EZJ!T29 -> 116056 | F45: =EZJ!U29 -> 62830 | G45: =EZJ!V29 -> 33348 | H45: =EZJ!W29 -> 82281 | I45: =EZJ!X29 -> 115193.4 | J45: =EZJ!Y29 -> 134872.5 | K45: =EZJ!Z29 -> 155103.37 | L45: =EZJ!AA29 -> 174491.3 | M45: =L45*(1+M46) -> 191940.43 | N45: =M45*(1+N46) -> 211134.47 | O45: =N45*(1+O46) -> 226969.55 | P45: =O45*(1+P46) -> 238318.03 | Q45: =P45*(1+Q46) -> 250233.93
C46: Selected YoY Growth Rate: | D46: % | E46: =EZJ!T30 -> 0 | F46: =EZJ!U30 -> -0.45862342 | G46: =EZJ!V30 -> -0.46923444 | H46: =EZJ!W30 -> 1.4673444 | I46: =EZJ!X30 -> 0.4 | J46: =EZJ!Y30 -> 0.17083531 | K46: =EZJ!Z30 -> 0.15 | L46: =EZJ!AA30 -> 0.125 | M46: =INDEX(M47:M49,MATCH(Scenario,$C47:$C49,0),1) -> 0.1 | N46: =INDEX(N47:N49,MATCH(Scenario,$C47:$C49,0),1) -> 0.1 | O46: =INDEX(O47:O49,MATCH(Scenario,$C47:$C49,0),1) -> 0.075 | P46: =INDEX(P47:P49,MATCH(Scenario,$C47:$C49,0),1) -> 0.05 | Q46: =INDEX(Q47:Q49,MATCH(Scenario,$C47:$C49,0),1) -> 0.05
C47: =EZJ!$C$31 -> Base | D47: % | M47: 0.1 | N47: 0.1 | O47: 0.075 | P47: 0.05 | Q47: 0.05
C48: =EZJ!$C$32 -> Downside | D48: % | M48: 0.1 | N48: 0.1 | O48: 0.075 | P48: 0.075 | Q48: 0.05
C49: =EZJ!$C$33 -> XT Downside | D49: % | M49: 0.1 | N49: 0.1 | O49: 0.1 | P49: 0.1 | Q49: 0.075
C51: Selected Load Factor: | D51: % | E51: =EZJ!T35 -> 0.92835355 | F51: =EZJ!U35 -> 0.93767309 | G51: =EZJ!V35 -> 0.7075087 | H51: =EZJ!W35 -> 0.82164655 | I51: =EZJ!X35 -> 0.88749882 | J51: =EZJ!Y35 -> 0.91572914 | K51: =EZJ!Z35 -> 0.925 | L51: =EZJ!AA35 -> 0.925 | M51: 0.925 | N51: 0.925 | O51: 0.925 | P51: 0.925 | Q51: 0.925
C53: Revenue Passenger Kilometres (RPK): | D53: Millions KM | E53: =E45*E51 -> 107741 | F53: =F45*F51 -> 58914 | G53: =G45*G51 -> 23594 | H53: =H45*H51 -> 67605.9 | I53: =I45*I51 -> 102234.01 | J53: =J45*J51 -> 123506.68 | K53: =K45*K51 -> 143470.62 | L53: =L45*L51 -> 161404.45 | ... Q53: =Q45*Q51 -> 231466.39
C55: Passenger Revenue: | D55: £ M | E55: =EZJ!T43 -> 5009 | F55: =EZJ!U43 -> 2303 | G55: =EZJ!V43 -> 1000 | H55: =EZJ!W43 -> 2922.7577 | I55: =EZJ!X43 -> 4622.0869 | J55: =EZJ!Y43 -> 5748.452 | K55: =EZJ!Z43 -> 6671.3839 | L55: =EZJ!AA43 -> 7666.7114 | M55: =M56*M$53/Units -> 8644.2171 | N55: =N56*N$53/Units -> 9667.3195 | O55: =O56*O$53/Units -> 10497.342 | P55: =P56*P$53/Units -> 11132.431 | Q55: =Q56*Q$53/Units -> 11804.786
C56: Yield (Revenue per RPK): | D56: p / KM | E56: =E55/E$53*Units -> 4.6491122 | F56: =F55/F$53*Units -> 3.9090878 | G56: =G55/G$53*Units -> 4.2383657 | H56: =H55/H$53*Units -> 4.3232288 | I56: =I55/I$53*Units -> 4.5210855 | J56: =J55/J$53*Units -> 4.6543653 | K56: =K55/K$53*Units -> 4.65 | L56: =L55/L$53*Units -> 4.75 | M56: 4.86875 | N56: 4.95 | O56: 5 | P56: 5.05 | Q56: 5.1
C58: Ancillary Revenue: | D58: £ M | E58: =EZJ!T46 -> 1376 | F58: =EZJ!U46 -> 706 | G58: =EZJ!V46 -> 458 | H58: =EZJ!W46 -> 1226.9108 | I58: =EZJ!X46 -> 1463.6822 | J58: =EZJ!Y46 -> 1598.0486 | K58: =EZJ!Z46 -> 1865.1181 | L58: =EZJ!AA46 -> 2178.9601 | M58: =M59*M$53/Units -> 2450.1195 | N58: =N59*N$53/Units -> 2773.2513 | O58: =O59*O$53/Units -> 3044.2291 | P58: =P59*P$53/Units -> 3240.5294 | Q58: =Q59*Q$53/Units -> 3448.8492
C59: Yield (Revenue per RPK): | D59: p / KM | E59: =E58/E$53*Units -> 1.2771368 | F59: =F58/F$53*Units -> 1.1983569 | G59: =G58/G$53*Units -> 1.9411715 | H59: =H58/H$53*Units -> 1.8147983 | I59: =I58/I$53*Units -> 1.431698 | J59: =J58/J$53*Units -> 1.2938965 | K59: =K58/K$53*Units -> 1.3 | L59: =L58/L$53*Units -> 1.35 | M59: 1.38 | N59: 1.42 | O59: 1.45 | P59: 1.47 | Q59: 1.49
C61: Non-Fuel Costs per ASK: | D61: p / KM | E61: =-E80/E45*Units -> 3.4457503 | F61: =-F80/F45*Units -> 4.211364 | G61: =-G80/G45*Units -> 4.534005 | H61: =-H80/H45*Units -> 3.6907549 | I61: =-I80/I45*Units -> 3.5541765 | J61: =-J80/J45*Units -> 3.5427086 | K61: =-K80/K45*Units -> 3.55 | L61: =-L80/L45*Units -> 3.6 | M61: 3.65 | N61: 3.7 | O61: 3.75 | P61: 3.8 | Q61: 3.85
C63: Selected Fuel Costs per ASK: | D63: p / KM | E63: =-E81/E45*Units -> 1.2201006 | F63: =-F81/F45*Units -> 1.147541 | G63: =-G81/G45*Units -> 1.1125105 | H63: =-H81/H45*Units -> 1.081579 | I63: =-I81/I45*Units -> 1.12 | J63: =-J81/J45*Units -> 1.1786457 | K63: =-K81/K45*Units -> 1.2 | L63: =-L81/L45*Units -> 1.22 | M63: =INDEX(M64:M66,MATCH(Scenario,$C64:$C66,0),1) -> 1.25 | N63: =INDEX(N64:N66,MATCH(Scenario,$C64:$C66,0),1) -> 1.27 | O63: =INDEX(O64:O66,MATCH(Scenario,$C64:$C66,0),1) -> 1.3 | P63: =INDEX(P64:P66,MATCH(Scenario,$C64:$C66,0),1) -> 1.32 | Q63: =INDEX(Q64:Q66,MATCH(Scenario,$C64:$C66,0),1) -> 1.32
C64: =EZJ!$C$31 -> Base | D64: % | M64: 1.25 | N64: 1.27 | O64: 1.3 | P64: 1.32 | Q64: 1.32
C65: =EZJ!$C$32 -> Downside | D65: % | M65: 1.45 | N65: 1.5 | O65: 1.5 | P65: 1.5 | Q65: 1.5
C66: =EZJ!$C$33 -> XT Downside | D66: % | M66: 1.55 | N66: 1.6 | O66: 1.6 | P66: 1.6 | Q66: 1.6
C68: Lease Depreciation per ASK: | D68: p / KM | E68: =-E87/E$45*Units -> 0.21282829 | F68: =-F87/F$45*Units -> 0.36447557 | G68: =-G87/G$45*Units -> 0.66570709 | H68: =-H87/H$45*Units -> 0.33662936 | I68: =-I87/I$45*Units -> 0.22083531 | J68: =-J87/J$45*Units -> 0.20708344 | K68: =-K87/K$45*Units -> 0.2 | L68: =-L87/L$45*Units -> 0.2 | M68: 0.21 | N68: 0.21 | O68: 0.22 | P68: 0.22 | Q68: 0.22
C69: Lease Interest per ASK: | D69: p / KM | F69: =-F95/F$45*Units -> 0.038198313 | G69: =-G95/G$45*Units -> 0.12594458 | H69: =-H95/H$45*Units -> 0.058354906 | I69: =-I95/I$45*Units -> 0.041682093 | J69: =-J95/J$45*Units -> 0.037345909 | K69: =-K95/K$45*Units -> 0.033956361 | L69: =-L95/L$45*Units -> 0.032583432 | M69: 0.03 | N69: 0.035 | O69: 0.035 | P69: 0.04 | Q69: 0.04
C71: CapEx & Intangible Purchases per ASK: | D71: p / KM | E71: =-E118/E45*Units -> 0.84786655 | F71: =-F118/F45*Units -> 1.1061595 | G71: =-G118/G45*Units -> 0.44680341 | H71: =-H118/H45*Units -> 0.69683062 | I71: =-I118/I45*Units -> 0.67167062 | J71: =-J118/J45*Units -> 0.7713543 | K71: =-K118/K45*Units -> 0.9 | L71: =-L118/L45*Units -> 0.93 | M71: 0.8 | N71: 0.6 | O71: 0.4 | P71: 0.4 | Q71: 0.4
C72: Depreciation & Amortisation per ASK: | D72: p / KM | E72: =-E88/E$45*Units -> 0.22144482 | F72: =-F88/F$45*Units -> 0.437689 | G72: =-G88/G$45*Units -> 0.78865299 | H72: =-H88/H$45*Units -> 0.36871234 | I72: =-I88/I$45*Units -> 0.25083531 | J72: =-J88/J$45*Units -> 0.23708344 | K72: =-K88/K$45*Units -> 0.23 | L72: =-L88/L$45*Units -> 0.23 | M72: 0.24 | N72: 0.24 | O72: 0.25 | P72: 0.25 | Q72: 0.25
C74: Tax Rate: | D74: % | E74: =EZJ!T61 -> 0.18837209 | F74: =EZJ!U61 -> 0.15239592 | G74: =EZJ!V61 -> 0.17181467 | H74: =EZJ!W61 -> 0.23571342 | I74: =EZJ!X61 -> 0.36477472 | J74: =EZJ!Y61 -> 0.25 | K74: =EZJ!Z61 -> 0.25 | L74: =EZJ!AA61 -> 0.25 | M74: =L74 -> 0.25 | N74: =M74 -> 0.25 | O74: =N74 -> 0.25 | P74: =O74 -> 0.25 | Q74: =P74 -> 0.25
G76: Historical: | J76: 0
B77: =Company_Name&" - UFCF Projections:" -> easyJet plc - UFCF Projections: | D77: =$D$6 -> Units: | E77: =$E$43 -> 43738 | F77: =$F$43 -> 44104 | G77: =$G$43 -> 44469 | H77: =$H$43 -> 44834 | I77: =$I$43 -> 45199 | J77: =$J$43 -> 45565 | K77: =$K$43 -> 45930 | L77: =$L$43 -> 46295 | M77: =$M$43 -> 46660 | N77: =$N$43 -> 47026 | O77: =$O$43 -> 47391 | P77: =$P$43 -> 47756 | Q77: =$Q$43 -> 48121
C79: Revenue: | D79: £ M | E79: =EZJ!T94 -> 6385 | F79: =EZJ!U94 -> 3009 | G79: =EZJ!V94 -> 1458 | H79: =EZJ!W94 -> 4149.6685 | I79: =EZJ!X94 -> 6085.7691 | J79: =EZJ!Y94 -> 7346.5005 | K79: =EZJ!Z94 -> 8536.502 | L79: =EZJ!AA94 -> 9845.6714 | M79: =M55+M58 -> 11094.337 | N79: =N55+N58 -> 12440.571 | O79: =O55+O58 -> 13541.571 | P79: =P55+P58 -> 14372.961 | Q79: =Q55+Q58 -> 15253.635
C80: (-) Non-Fuel Costs: | D80: £ M | E80: =EZJ!T95 -> -3999 | F80: =EZJ!U95 -> -2646 | G80: =EZJ!V95 -> -1512 | H80: =EZJ!W95 -> -3036.79 | I80: =EZJ!X95 -> -4094.1768 | J80: =EZJ!Y95 -> -4778.1397 | K80: =EZJ!Z95 -> -5506.1698 | L80: =EZJ!AA95 -> -6281.6867 | M80: =-M61*M$45/Units -> -7005.8256 | N80: =-N61*N$45/Units -> -7811.9754 | O80: =-O61*O$45/Units -> -8511.3583 | P80: =-P61*P$45/Units -> -9056.0852 | Q80: =-Q61*Q$45/Units -> -9634.0064
C81: (-) Fuel Costs: | D81: £ M | E81: =EZJ!T96 -> -1416 | F81: =EZJ!U96 -> -721 | G81: =EZJ!V96 -> -371 | H81: =EZJ!W96 -> -889.934 | I81: =EZJ!X96 -> -1290.1661 | J81: =EZJ!Y96 -> -1589.6689 | K81: =EZJ!Z96 -> -1861.2405 | L81: =EZJ!AA96 -> -2128.7938 | M81: =-M63*M$45/Units -> -2399.2553 | N81: =-N63*N$45/Units -> -2681.4078 | O81: =-O63*O$45/Units -> -2950.6042 | P81: =-P63*P$45/Units -> -3145.798 | Q81: =-Q63*Q$45/Units -> -3303.0879
C82: EBITDAR: | D82: £ M | E82: =SUM(E79:E81) -> 970 | F82: =SUM(F79:F81) -> -358 | G82: =SUM(G79:G81) -> -425 | H82: =SUM(H79:H81) -> 222.9445 | I82: =SUM(I79:I81) -> 701.42619 | J82: =SUM(J79:J81) -> 978.69196 | K82: =SUM(K79:K81) -> 1169.0917 | L82: =SUM(L79:L81) -> 1435.1909 | ... Q82: =SUM(Q79:Q81) -> 2316.5406
C84: Revenue Growth Rate: | D84: % | F84: =F79/E79-1 -> -0.52873923 | G84: =G79/F79-1 -> -0.51545364 | H84: =H79/G79-1 -> 1.8461375 | I84: =I79/H79-1 -> 0.46656753 | J84: =J79/I79-1 -> 0.20716058 | K84: =K79/J79-1 -> 0.16198208 | L84: =L79/K79-1 -> 0.15336134 | M84: =M79/L79-1 -> 0.12682377 | ... Q84: =Q79/P79-1 -> 0.061273006
C86: Lease and Depreciation Costs:
C87: (-) Lease Depreciation: | D87: £ M | E87: =EZJ!T100 -> -247 | F87: =EZJ!U100 -> -229 | G87: =EZJ!V100 -> -222 | H87: =EZJ!W100 -> -276.982 | I87: =EZJ!X100 -> -254.3877 | J87: =EZJ!Y100 -> -279.29861 | K87: =EZJ!Z100 -> -310.20675 | L87: =EZJ!AA100 -> -348.98259 | M87: =-M68*M$45/Units -> -403.0749 | N87: =-N68*N$45/Units -> -443.38239 | O87: =-O68*O$45/Units -> -499.33302 | P87: =-P68*P$45/Units -> -524.29967 | Q87: =-Q68*Q$45/Units -> -550.51465
C88: (-) Depreciation & Amortisation: | D88: £ M | E88: =EZJ!T102 -> -257 | F88: =EZJ!U102 -> -275 | G88: =EZJ!V102 -> -263 | H88: =EZJ!W102 -> -303.3802 | I88: =EZJ!X102 -> -288.94572 | J88: =EZJ!Y102 -> -319.76036 | K88: =EZJ!Z102 -> -356.73776 | L88: =EZJ!AA102 -> -401.32998 | M88: =-M72*M$45/Units -> -460.65702 | N88: =-N72*N$45/Units -> -506.72273 | O88: =-O72*O$45/Units -> -567.42389 | P88: =-P72*P$45/Units -> -595.79508 | Q88: =-Q72*Q$45/Units -> -625.58483
C89: Total Lease and Depreciation Costs: | D89: £ M | E89: =SUM(E87:E88) -> -504 | F89: =SUM(F87:F88) -> -504 | G89: =SUM(G87:G88) -> -485 | H89: =SUM(H87:H88) -> -580.3622 | I89: =SUM(I87:I88) -> -543.33342 | J89: =SUM(J87:J88) -> -599.05898 | K89: =SUM(K87:K88) -> -666.94451 | L89: =SUM(L87:L88) -> -750.31258 | ... Q89: =SUM(Q87:Q88) -> -1176.0995
C91: Operating Income (EBIT): | D91: £ M | E91: =E82+E89 -> 466 | F91: =F82+F89 -> -862 | G91: =G82+G89 -> -910 | H91: =H82+H89 -> -357.4177 | I91: =I82+I89 -> 158.09277 | J91: =J82+J89 -> 379.63299 | K91: =K82+K89 -> 502.14718 | L91: =L82+L89 -> 684.87834 | ... Q91: =Q82+Q89 -> 1140.4412
C92: Operating Margin: | D92: % | E92: =E91/E79 -> 0.072983555 | F92: =F91/F79 -> -0.28647391 | G92: =G91/G79 -> -0.62414266 | H92: =H91/H79 -> -0.086131627 | I92: =I91/I79 -> 0.025977451 | J92: =J91/J79 -> 0.05167535 | K92: =K91/K79 -> 0.058823529 | L92: =L91/L79 -> 0.069561365 | ... Q92: =Q91/Q79 -> 0.074765205
C93: Growth Rate: | D93: % | F93: =F91/E91-1 -> -2.8497854 | G93: =G91/F91-1 -> 0.055684455 | H93: =H91/G91-1 -> -0.6072333 | I93: =I91/H91-1 -> -1.4423194 | J93: =J91/I91-1 -> 1.4013305 | K93: =K91/J91-1 -> 0.32271746 | L93: =L91/K91-1 -> 0.36389961 | M93: =M91/L91-1 -> 0.20535828 | ... Q93: =Q91/P91-1 -> 0.085119048
C95: (-) Lease Interest Element: | D95: £ M | F95: =-SUM(EZJ!G193:H193) -> -24 | G95: =-SUM(EZJ!I193:J193) -> -42 | H95: =-AVERAGE(EZJ!J130,EZJ!K130)*EZJ!$K$192 -> -48.015 | I95: =-AVERAGE(EZJ!L130,EZJ!M130)*EZJ!$K$192 -> -48.01502 | J95: =-AVERAGE(EZJ!N130,EZJ!O130)*EZJ!$K$192 -> -50.369361 | K95: =-EZJ!P130*EZJ!$K$192 -> -52.667461 | L95: =-EZJ!Q130*EZJ!$K$192 -> -56.855252 | M95: =-M69*M45/Units -> -57.582128 | N95: =-N69*N45/Units -> -73.897064 | O95: =-O69*O45/Units -> -79.439344 | P95: =-P69*P45/Units -> -95.327213 | Q95: =-Q69*Q45/Units -> -100.09357
C97: EBIT After Full Lease Expense Deduction: | D97: £ M | E97: =E91+E95 -> 466 | F97: =F91+F95 -> -886 | G97: =G91+G95 -> -952 | H97: =H91+H95 -> -405.4327 | I97: =I91+I95 -> 110.07775 | J97: =J91+J95 -> 329.26362 | K97: =K91+K95 -> 449.47972 | L97: =L91+L95 -> 628.02309 | ... Q97: =Q91+Q95 -> 1040.3476
C99: Beginning NOL Balance: | D99: £ M | H99: =G102 -> 1878.7698 | I99: =H102 -> 2284.2025 | J99: =I102 -> 2174.1248 | K99: =J102 -> 1844.8612 | L99: =K102 -> 1395.3815 | M99: =L102 -> 767.35837 | N99: =M102 -> 0 | O99: =N102 -> 0 | ... Q99: =P102 -> 0
C100: (+) NOLs Created: | D100: £ M | H100: =MAX(0,-H97) -> 405.4327 | I100: =MAX(0,-I97) -> 0 | J100: =MAX(0,-J97) -> 0 | K100: =MAX(0,-K97) -> 0 | L100: =MAX(0,-L97) -> 0 | M100: =MAX(0,-M97) -> 0 | N100: =MAX(0,-N97) -> 0 | O100: =MAX(0,-O97) -> 0 | ... Q100: =MAX(0,-Q97) -> 0
C101: (-) NOLs Used: | D101: £ M | H101: =-MIN(H99+H100,MAX(H97,0)) -> 0 | I101: =-MIN(I99+I100,MAX(I97,0)) -> -110.07775 | J101: =-MIN(J99+J100,MAX(J97,0)) -> -329.26362 | K101: =-MIN(K99+K100,MAX(K97,0)) -> -449.47972 | L101: =-MIN(L99+L100,MAX(L97,0)) -> -628.02309 | M101: =-MIN(M99+M100,MAX(M97,0)) -> -767.35837 | N101: =-MIN(N99+N100,MAX(N97,0)) -> 0 | O101: =-MIN(O99+O100,MAX(O97,0)) -> 0 | ... Q101: =-MIN(Q99+Q100,MAX(Q97,0)) -> 0
C102: Ending NOL Balance: | D102: £ M | G102: =EZJ!K80 -> 1878.7698 | H102: =SUM(H99:H101) -> 2284.2025 | I102: =SUM(I99:I101) -> 2174.1248 | J102: =SUM(J99:J101) -> 1844.8612 | K102: =SUM(K99:K101) -> 1395.3815 | L102: =SUM(L99:L101) -> 767.35837 | M102: =SUM(M99:M101) -> 0 | N102: =SUM(N99:N101) -> 0 | O102: =SUM(O99:O101) -> 0 | ... Q102: =SUM(Q99:Q101) -> 0
C104: NOL-Adjusted Operating Income (EBIT): | D104: £ M | E104: =E97+E101 -> 466 | F104: =F97+F101 -> -886 | G104: =G97+G101 -> -952 | H104: =H97+H101 -> -405.4327 | I104: =I97+I101 -> 0 | J104: =J97+J101 -> 0 | K104: =K97+K101 -> 0 | L104: =L97+L101 -> 0 | ... Q104: =Q97+Q101 -> 1040.3476
C106: (-) Cash Taxes, Excluding Effect of Non-Lease Debt: | D106: £ M | E106: =(EZJ!T113+EZJ!T147)/EZJ!T112*E104 -> -62.855814 | F106: =(EZJ!U113+EZJ!U147)/EZJ!U112*F104 -> 9.0479183 | G106: =(EZJ!V113+EZJ!V147)/EZJ!V112*G104 -> 0.91891892 | H106: =-MAX(H104,0)*Tax_Rate -> 0 | I106: =-MAX(I104,0)*Tax_Rate -> 0 | J106: =-MAX(J104,0)*Tax_Rate -> 0 | K106: =-MAX(K104,0)*Tax_Rate -> 0 | L106: =-MAX(L104,0)*Tax_Rate -> 0 | M106: =-MAX(M104,0)*Tax_Rate -> -0.14582078 | N106: =-MAX(N104,0)*Tax_Rate -> -230.79637 | O106: =-MAX(O104,0)*Tax_Rate -> -233.35307 | ... Q106: =-MAX(Q104,0)*Tax_Rate -> -260.08689
C108: Net Operating Profit After Taxes (NOPAT): | D108: £ M | E108: =E97+E106 -> 403.14419 | F108: =F97+F106 -> -876.95208 | G108: =G97+G106 -> -951.08108 | H108: =H97+H106 -> -405.4327 | I108: =I97+I106 -> 110.07775 | J108: =J97+J106 -> 329.26362 | K108: =K97+K106 -> 449.47972 | L108: =L97+L106 -> 628.02309 | ... Q108: =Q97+Q106 -> 780.26068
C110: Adjustments for Non-Cash Charges:
C111: (+) Depreciation & Amortisation (PP&E/Intangibles): | D111: £ M | E111: =-E88 -> 257 | F111: =-F88 -> 275 | G111: =-G88 -> 263 | H111: =-H88 -> 303.3802 | I111: =-I88 -> 288.94572 | J111: =-J88 -> 319.76036 | K111: =-K88 -> 356.73776 | L111: =-L88 -> 401.32998 | ... Q111: =-Q88 -> 625.58483
C112: D&A % Revenue: | D112: % | E112: =E111/E79 -> 0.040250587 | F112: =F111/F79 -> 0.091392489 | G112: =G111/G79 -> 0.18038409 | H112: =H111/H79 -> 0.073109503 | I112: =I111/I79 -> 0.047478916 | J112: =J111/J79 -> 0.043525535 | K112: =K111/K79 -> 0.041789689 | L112: =L111/L79 -> 0.040762074 | ... Q112: =Q111/Q79 -> 0.041012181
C114: (+/-) Change in Working Capital: | D114: £ M | E114: =EZJ!T149 -> 118 | F114: =EZJ!U149 -> -192 | G114: =EZJ!V149 -> -306 | H114: =EZJ!W149 -> 1542.3852 | I114: =EZJ!X149 -> 38.192982 | J114: =EZJ!Y149 -> -485.12352 | K114: =EZJ!Z149 -> 598.33295 | L114: =EZJ!AA149 -> 634.4649 | M114: =(M79-L79)*M115 -> 561.89933 | N114: =(N79-M79)*N115 -> 605.80537 | O114: =(O79-N79)*O115 -> 495.45012 | P114: =(P79-O79)*P115 -> 374.12527 | Q114: =(Q79-P79)*Q115 -> 396.30352
C115: % Change in Revenue: | D115: % | F115: =F114/(F$79-E$79) -> 0.056872038 | G115: =G114/(G$79-F$79) -> 0.19729207 | H115: =H114/(H$79-G$79) -> 0.57302198 | I115: =I114/(I$79-H$79) -> 0.019726755 | J115: =J114/(J$79-I$79) -> -0.38479528 | K115: =K114/(K$79-J$79) -> 0.50280018 | L115: =L114/(L$79-K$79) -> 0.48463162 | M115: 0.45 | N115: 0.45 | O115: 0.45 | P115: 0.45 | Q115: 0.45
C116: % Revenue: | D116: % | E116: =E114/E79 -> 0.018480814 | F116: =F114/F79 -> -0.063808574 | G116: =G114/G79 -> -0.20987654 | H116: =H114/H79 -> 0.37168878 | I116: =I114/I79 -> 0.0062757856 | J116: =J114/J79 -> -0.06603464 | K116: =K114/K79 -> 0.070091115 | L116: =L114/L79 -> 0.064440998 | ... Q116: =Q114/Q79 -> 0.025980923
C118: (-) Capital Expenditures & Intangible Purchases: | D118: £ M | E118: =EZJ!T153 -> -984 | F118: =EZJ!U153 -> -695 | G118: =EZJ!V153 -> -149 | H118: =EZJ!W153 -> -573.3592 | I118: =EZJ!X153 -> -773.72022 | J118: =EZJ!Y153 -> -1040.3448 | K118: =EZJ!Z153 -> -1395.9304 | L118: =EZJ!AA153 -> -1622.7691 | M118: =-M71*M45/Units -> -1535.5234 | N118: =-N71*N45/Units -> -1266.8068 | O118: =-O71*O45/Units -> -907.87822 | P118: =-P71*P45/Units -> -953.27213 | Q118: =-Q71*Q45/Units -> -1000.9357
C119: % Change in Revenue: | D119: % | F119: =F118/(F$79-E$79) -> 0.20586493 | G119: =G118/(G$79-F$79) -> 0.096067054 | H119: =H118/(H$79-G$79) -> -0.21301256 | I119: =I118/(I$79-H$79) -> -0.39962811 | J119: =J118/(J$79-I$79) -> -0.82519145 | K119: =K118/(K$79-J$79) -> -1.1730493 | L119: =L118/(L$79-K$79) -> -1.2395409 | M119: =M118/(M$79-L$79) -> -1.2297319 | ... Q119: =Q118/(Q$79-P$79) -> -1.1365558
C120: % Revenue: | D120: % | E120: =-E118/E79 -> 0.1541112 | F120: =-F118/F79 -> 0.23097375 | G120: =-G118/G79 -> 0.10219479 | H120: =-H118/H79 -> 0.13816988 | I120: =-I118/I79 -> 0.12713598 | J120: =-J118/J79 -> 0.14161094 | K120: =-K118/K79 -> 0.16352487 | L120: =-L118/L79 -> 0.16482056 | ... Q120: =-Q118/Q79 -> 0.065619489
C122: Unlevered Free Cash Flow: | D122: £ M | E122: =E108+E111+E114+E118 -> -205.85581 | F122: =F108+F111+F114+F118 -> -1488.9521 | G122: =G108+G111+G114+G118 -> -1143.0811 | H122: =H108+H111+H114+H118 -> 866.97353 | I122: =I108+I111+I114+I118 -> -336.50377 | J122: =J108+J111+J114+J118 -> -876.44436 | K122: =K108+K111+K114+K118 -> 8.6200492 | L122: =L108+L111+L114+L118 -> 41.048906 | ... Q122: =Q108+Q111+Q114+Q118 -> 801.21331
C123: Growth Rate: | D123: % | F123: =F122/E122-1 -> 6.2329853 | G123: =G122/F122-1 -> -0.23229156 | H123: =H122/G122-1 -> -1.7584532 | I123: =I122/H122-1 -> -1.3881362 | J123: =J122/I122-1 -> 1.6045603 | K123: =K122/J122-1 -> -1.0098352 | L123: =L122/K122-1 -> 3.7620269 | M123: =M122/L122-1 -> 5.2079308 | ... Q123: =Q122/P122-1 -> 0.092479632
C125: Unlevered Free Cash Flow for Remainder: | D125: £ M | H125: =H122-(EZJ!K105-EZJ!K192*EZJ!J130/2+EZJ!K145+EZJ!K148+EZJ!K149+EZJ!K153) -> 681.25103 | I125: =I122 -> -336.50377 | J125: =J122 -> -876.44436 | K125: =K122 -> 8.6200492 | L125: =L122 -> 41.048906 | M125: =M122 -> 254.82877 | N125: =N122 -> 538.11038 | O125: =O122 -> 855.05501 | P125: =P122 -> 733.3897 | Q125: =Q122 -> 801.21331
C127: PV of Unlevered Free Cash Flow: | D127: £ M | H127: =H125*H130 -> 783.47491 | I127: =I125*I130 -> -421.32888 | J127: =J125*J130 -> -983.43697 | K127: =K125*K130 -> 8.668078 | L127: =L125*L130 -> 36.991806 | M127: =M125*M130 -> 205.79902 | N127: =N125*N130 -> 389.45483 | O127: =O125*O130 -> 554.58826 | ... Q127: =Q125*Q130 -> 417.35588
C129: Cumulative Discount Factor - Normal: | D129: # | H129: =1/((1+Discount_Rate)^H132) -> 1.3226223 | I129: =1/((1+Discount_Rate)^I132) -> 1.1852958 | J129: =1/((1+Discount_Rate)^J132) -> 1.0622277 | K129: =1/((1+Discount_Rate)^K132) -> 0.95193766 | L129: =1/((1+Discount_Rate)^L132) -> 0.85309892 | M129: =1/((1+Discount_Rate)^M132) -> 0.76452252 | N129: =1/((1+Discount_Rate)^N132) -> 0.68514291 | O129: =1/((1+Discount_Rate)^O132) -> 0.61400521 | ... Q129: =1/((1+Discount_Rate)^Q132) -> 0.49312137
C130: Cumulative Discount Factor - Mid-Year: | D130: # | H130: =1/((1+Discount_Rate)^H133) -> 1.1500532 | I130: =1/((1+Discount_Rate)^I133) -> 1.2520777 | J130: =1/((1+Discount_Rate)^J133) -> 1.1220758 | K130: =1/((1+Discount_Rate)^K133) -> 1.0055718 | L130: =1/((1+Discount_Rate)^L133) -> 0.90116424 | M130: =1/((1+Discount_Rate)^M133) -> 0.80759726 | N130: =1/((1+Discount_Rate)^N133) -> 0.72374525 | O130: =1/((1+Discount_Rate)^O133) -> 0.6485995 | ... Q130: =1/((1+Discount_Rate)^Q133) -> 0.52090483
C132: Normal Discount Period: | D132: # | H132: =Stub_Period -> -2.5506849 | I132: =H132+1 -> -1.5506849 | J132: =I132+1 -> -0.55068493 | K132: =J132+1 -> 0.44931507 | L132: =K132+1 -> 1.4493151 | M132: =L132+1 -> 2.4493151 | N132: =M132+1 -> 3.4493151 | O132: =N132+1 -> 4.4493151 | P132: =O132+1 -> 5.4493151 | Q132: =P132+1 -> 6.4493151
C133: Mid-Year Discount Period: | D133: # | H133: =H132/2 -> -1.2753425 | I133: =I132-0.5 -> -2.0506849 | J133: =J132-0.5 -> -1.0506849 | K133: =K132-0.5 -> -0.050684932 | L133: =L132-0.5 -> 0.94931507 | M133: =M132-0.5 -> 1.9493151 | N133: =N132-0.5 -> 2.9493151 | O133: =O132-0.5 -> 3.9493151 | P133: =P132-0.5 -> 4.9493151 | Q133: =Q132-0.5 -> 5.9493151
C135: EBITDAR: | D135: £ M | E135: =E82 -> 970 | F135: =F82 -> -358 | G135: =G82 -> -425 | H135: =H82 -> 222.9445 | I135: =I82 -> 701.42619 | J135: =J82 -> 978.69196 | K135: =K82 -> 1169.0917 | L135: =L82 -> 1435.1909 | ... Q135: =Q82 -> 2316.5406
C136: Growth Rate: | D136: % | F136: =F135/E135-1 -> -1.3690722 | G136: =G135/F135-1 -> 0.18715084 | H136: =H135/G135-1 -> -1.5245753 | I136: =I135/H135-1 -> 2.1461919 | J136: =J135/I135-1 -> 0.3952886 | K136: =K135/J135-1 -> 0.1945451 | L136: =L135/K135-1 -> 0.22761194 | M136: =M135/L135-1 -> 0.17702508 | ... Q136: =Q135/P135-1 -> 0.067000549
...

Sheet Graphs
B2: =Company_Name&" - Valuation Graphs and Analysis" -> easyJet plc - Valuation Graphs and Analysis
P4: ="Annual Revenue, "&Public_Comps!$P$8&" - "&Public_Comps!$Q$8 -> Annual Revenue, CY 23 - CY 24 | Q4: =Public_Comps!P8 -> CY 23 | R4: =Public_Comps!Q8 -> CY 24
P5: ="Annual EBITDA, "&Public_Comps!$P$8&" - "&Public_Comps!$Q$8 -> Annual EBITDA, CY 23 - CY 24 | Q5: =Public_Comps!S8 -> CY 23 | R5: =Public_Comps!T8 -> CY 24
P19: ="2-Year Revenue CAGR, "&Public_Comps!$O$8&" - "&Public_Comps!$Q$8 -> 2-Year Revenue CAGR, CY 22 - CY 24
P20: ="2-Year EBITDA CAGR, "&Public_Comps!$O$8&" - "&Public_Comps!$Q$8 -> 2-Year EBITDA CAGR, CY 22 - CY 24
P22: =Public_Comps!$Q$8&" Revenue Multiples" -> CY 24 Revenue Multiples
P23: =Public_Comps!$Q$8&" EBITDA Multiples" -> CY 24 EBITDA Multiples
P29: Supporting Data (Sorted by revenue in ascending order):
Q30: Revenue: | T30: EBITDA: | W30: Rev. Multiples: | Z30: EBITDA Multiples:
Q31: =Public_Comps!P8 -> CY 23 | R31: =Public_Comps!Q8 -> CY 24 | T31: =Public_Comps!S8 -> CY 23 | U31: =Public_Comps!T8 -> CY 24 | W31: =Public_Comps!P27 -> CY 23 | X31: =Public_Comps!Q27 -> CY 24 | Z31: =Public_Comps!S27 -> CY 23 | AA31: =Public_Comps!T27 -> CY 24
P32: ISE:RYA | Q32: =Public_Comps!P9 -> 10051.66 | R32: =Public_Comps!Q9 -> 11420.625 | T32: =Public_Comps!S9 -> 2036.42 | U32: =Public_Comps!T9 -> 2520.765 | W32: =Public_Comps!P28 -> 1.3227395 | X32: =Public_Comps!Q28 -> 1.1641857 | Z32: =Public_Comps!S28 -> 6.5289714 | AA32: =Public_Comps!T28 -> 5.2744814
P33: =Ticker -> LSE:EZJ | Q33: =Public_Comps!P23 -> 6310.6335 | R33: =Public_Comps!Q23 -> 6940.9992 | T33: =Public_Comps!S23 -> 715.0827 | U33: =Public_Comps!T23 -> 853.71559 | W33: =Public_Comps!P42 -> 0.54290691 | X33: =Public_Comps!Q42 -> 0.49360134 | Z33: =Public_Comps!S42 -> 4.7911753 | AA33: =Public_Comps!T42 -> 4.0131475
P34: AIM:JET2 | Q34: =Public_Comps!P11 -> 5088.5175 | R34: =Public_Comps!Q11 -> 5518.4125 | T34: =Public_Comps!S11 -> 552.4775 | U34: =Public_Comps!T11 -> 612.495 | W34: =Public_Comps!P30 -> 0.28336257 | X34: =Public_Comps!Q30 -> 0.26128808 | Z34: =Public_Comps!S30 -> 2.6098717 | AA34: =Public_Comps!T30 -> 2.3541342
P35: LSE:WIZZ | Q35: =Public_Comps!P10 -> 4282.335 | R35: =Public_Comps!Q10 -> 5352.865 | T35: =Public_Comps!S10 -> 731.735 | U35: =Public_Comps!T10 -> 1154.165 | W35: =Public_Comps!P29 -> 1.1623855 | X35: =Public_Comps!Q29 -> 0.92991772 | Z35: =Public_Comps!S29 -> 6.8026321 | AA35: =Public_Comps!T29 -> 4.3128357
P36: IBSE:PGSUS | Q36: =Public_Comps!P13 -> 2412.22 | R36: =Public_Comps!Q13 -> 2915.87 | T36: =Public_Comps!S13 -> 755.68 | U36: =Public_Comps!T13 -> 1038.98 | W36: =Public_Comps!P32 -> 1.1298667 | X36: =Public_Comps!Q32 -> 0.93470799 | Z36: =Public_Comps!S32 -> 3.6066682 | AA36: =Public_Comps!T32 -> 2.6232334
P37: OB:NAS | Q37: =Public_Comps!P14 -> 2070.58 | R37: =Public_Comps!Q14 -> 2295.52 | T37: =Public_Comps!S14 -> 282.04 | U37: =Public_Comps!T14 -> 416.77 | W37: =Public_Comps!P33 -> 0.49092525 | X37: =Public_Comps!Q33 -> 0.44281906 | Z37: =Public_Comps!S33 -> 3.6040987 | AA37: =Public_Comps!T33 -> 2.4389951
P38: DFM:AIRARABIA | Q38: =Public_Comps!P12 -> 1214.1 | R38: =Public_Comps!Q12 -> 1259.29 | T38: =Public_Comps!S12 -> 366.08 | U38: =Public_Comps!T12 -> 380.18 | W38: =Public_Comps!P31 -> 1.7719718 | X38: =Public_Comps!Q31 -> 1.7083841 | Z38: =Public_Comps!S31 -> 5.8767237 | AA38: =Public_Comps!T31 -> 5.6587695
P39: KWSE:JAZEERA | Q39: =Public_Comps!P15 -> 484.55 | R39: =Public_Comps!Q15 -> 538.03 | T39: =Public_Comps!S15 -> 144.55 | U39: =Public_Comps!T15 -> 181.01 | W39: =Public_Comps!P34 -> 3.1771747 | X39: =Public_Comps!Q34 -> 2.8613646 | Z39: =Public_Comps!S34 -> 10.650294 | AA39: =Public_Comps!T34 -> 8.505055
P41: Data for Graphs (Sorted by Revenue CAGR in ascending order):
Q42: 2-Year Revenue CAGR: | T42: 2-Year EBITDA CAGR: | W42: Year 2 Rev. Multiple: | Z42: Year 2 EBITDA Multiple:
Q43: =Public_Comps!X8 -> CAGR | T43: =Public_Comps!Y8 -> CAGR | W43: =Public_Comps!Q27 -> CY 24 | Z43: =Public_Comps!T27 -> CY 24
P44: LSE:WIZZ | Q44: =Public_Comps!X10 -> 0.35609389 | R44: =IF($P44=Ticker,Q44,NA()) -> #N/A | T44: =Public_Comps!Y10 -> 2.2150308 | U44: =IF($P44=Ticker,T44,NA()) -> #N/A | W44: =Public_Comps!Q29 -> 0.92991772 | X44: =IF($P44=Ticker,W44,NA()) -> #N/A | Z44: =Public_Comps!T29 -> 4.3128357 | AA44: =IF($P44=Ticker,Z44,NA()) -> #N/A
P45: IBSE:PGSUS | Q45: =Public_Comps!X13 -> 0.33824061 | R45: =IF($P45=Ticker,Q45,NA()) -> #N/A | T45: =Public_Comps!Y13 -> 0.50914411 | U45: =IF($P45=Ticker,T45,NA()) -> #N/A | W45: =Public_Comps!Q32 -> 0.93470799 | X45: =IF($P45=Ticker,W45,NA()) -> #N/A | Z45: =Public_Comps!T32 -> 2.6232334 | AA45: =IF($P45=Ticker,Z45,NA()) -> #N/A
P46: LSE:EZJ | Q46: =Public_Comps!X23 -> 0.23664954 | R46: =IF($P46=Ticker,Q46,NA()) -> 0.23664954 | T46: =Public_Comps!Y23 -> 0.64730732 | U46: =IF($P46=Ticker,T46,NA()) -> 0.64730732 | W46: =Public_Comps!Q42 -> 0.49360134 | X46: =IF($P46=Ticker,W46,NA()) -> 0.49360134 | Z46: =Public_Comps!T42 -> 4.0131475 | AA46: =IF($P46=Ticker,Z46,NA()) -> 4.0131475
P47: ISE:RYA | Q47: =Public_Comps!X9 -> 0.22872902 | R47: =IF($P47=Ticker,Q47,NA()) -> #N/A | T47: =Public_Comps!Y9 -> 0.28648528 | U47: =IF($P47=Ticker,T47,NA()) -> #N/A | W47: =Public_Comps!Q28 -> 1.1641857 | X47: =IF($P47=Ticker,W47,NA()) -> #N/A | Z47: =Public_Comps!T28 -> 5.2744814 | AA47: =IF($P47=Ticker,Z47,NA()) -> #N/A
P48: OB:NAS | Q48: =Public_Comps!X14 -> 0.21358172 | R48: =IF($P48=Ticker,Q48,NA()) -> #N/A | T48: =Public_Comps!Y14 -> N/A | U48: =IF($P48=Ticker,T48,NA()) -> #N/A | W48: =Public_Comps!Q33 -> 0.44281906 | X48: =IF($P48=Ticker,W48,NA()) -> #N/A | Z48: =Public_Comps!T33 -> 2.4389951 | AA48: =IF($P48=Ticker,Z48,NA()) -> #N/A
P49: AIM:JET2 | Q49: =Public_Comps!X11 -> 0.19873318 | R49: =IF($P49=Ticker,Q49,NA()) -> #N/A | T49: =Public_Comps!Y11 -> 0.32795467 | U49: =IF($P49=Ticker,T49,NA()) -> #N/A | W49: =Public_Comps!Q30 -> 0.26128808 | X49: =IF($P49=Ticker,W49,NA()) -> #N/A | Z49: =Public_Comps!T30 -> 2.3541342 | AA49: =IF($P49=Ticker,Z49,NA()) -> #N/A
P50: KWSE:JAZEERA | Q50: =Public_Comps!X15 -> 0.15806679 | R50: =IF($P50=Ticker,Q50,NA()) -> #N/A | T50: =Public_Comps!Y15 -> 0.24836527 | U50: =IF($P50=Ticker,T50,NA()) -> #N/A | W50: =Public_Comps!Q34 -> 2.8613646 | X50: =IF($P50=Ticker,W50,NA()) -> #N/A | Z50: =Public_Comps!T34 -> 8.505055 | AA50: =IF($P50=Ticker,Z50,NA()) -> #N/A
P51: DFM:AIRARABIA | Q51: =Public_Comps!X12 -> 0.07199625 | R51: =IF($P51=Ticker,Q51,NA()) -> #N/A | T51: =Public_Comps!Y12 -> 0.03259097 | U51: =IF($P51=Ticker,T51,NA()) -> #N/A | W51: =Public_Comps!Q31 -> 1.7083841 | X51: =IF($P51=Ticker,W51,NA()) -> #N/A | Z51: =Public_Comps!T31 -> 5.6587695 | AA51: =IF($P51=Ticker,Z51,NA()) -> #N/A
B82: =DCF!E43 -> 43738 | C82: =DCF!F43 -> 44104 | D82: =DCF!G43 -> 44469 | E82: =DCF!H43 -> 44834 | F82: =DCF!I43 -> 45199 | G82: =DCF!J43 -> 45565 | H82: =DCF!K43 -> 45930 | I82: =DCF!L43 -> 46295 | ... N82: =DCF!Q43 -> 48121
B83: 116056 | C83: 62830 | D83: 33348 | E83: 82281 | F83: 115193.4 | G83: 134872.5 | H83: 155103.37 | I83: 174491.3 | J83: 191940.43 | K83: 211134.47 | L83: 226969.55 | M83: 238318.03 | N83: 250233.93
B84: 116056 | C84: 62830 | D84: 33348 | E84: 69651 | F84: 92260.65 | G84: 115325.81 | H84: 135507.83 | I84: 152446.31 | J84: 167690.94 | K84: 184460.03 | L84: 198294.54 | M84: 213166.63 | N84: 223824.96
B85: 116056 | C85: 62830 | D85: 33348 | E85: 67125 | F85: 85620.6 | G85: 100692.34 | H85: 113278.89 | I85: 124606.78 | J85: 137067.45 | K85: 150774.2 | L85: 165851.62 | M85: 182436.78 | N85: 196119.54
B117: =DCF!E43 -> 43738 | C117: =DCF!F43 -> 44104 | D117: =DCF!G43 -> 44469 | E117: =DCF!H43 -> 44834 | F117: =DCF!I43 -> 45199 | G117: =DCF!J43 -> 45565 | H117: =DCF!K43 -> 45930 | I117: =DCF!L43 -> 46295 | ... N117: =DCF!Q43 -> 48121
B118: 970 | C118: -358 | D118: -425 | E118: 222.9445 | F118: 701.42619 | G118: 978.69196 | H118: 1169.0917 | I118: 1435.1909 | J118: 1689.2557 | K118: 1947.1876 | L118: 2079.6085 | M118: 2171.0773 | N118: 2316.5406
B119: 970 | C119: -358 | D119: -425 | E119: 99.0442 | F119: 335.55186 | G119: 542.39064 | H119: 777.81494 | I119: 932.97141 | J119: 1140.4556 | K119: 1276.9246 | L119: 1420.2846 | M119: 1558.248 | N119: 1669.1746
B120: 970 | C120: -358 | D120: -425 | E120: 66.3325 | F120: 213.4941 | G120: 228.4144 | H120: 402.14005 | I120: 561.97656 | J120: 795.11974 | K120: 892.9602 | L120: 1022.0606 | M120: 1151.1761 | N120: 1266.4419

Sheet WACC
B2: ="WACC Analysis - "&Company_Name -> WACC Analysis - easyJet plc
B3: =Public_Comps!$B$3 -> (£ GBP in Millions Except Per Share Amounts in GBP as Stated)
B5: Discount Rate Calculations - Assumptions:
B6: Risk-Free Rate: | F6: 0.0452
B7: Equity Risk Premium: | F7: 0.065
B8: Pre-Tax Cost of Debt: | F8: =EZJ!K187 -> 0.05
B9: Cost of Preferred Stock: | F9: 0
B11: =Public_Comps!$B$8 -> Company Name | D11: =Public_Comps!$G$8 -> Beta | E11: =Public_Comps!$J$8 -> Debt | G11: =Public_Comps!$L$8 -> Preferred | I11: =Public_Comps!$F$8 -> Value | K11: =Public_Comps!$H$8 -> Tax Rate
B12: Comparable Companies - Unlevered Beta Calculation:
D13: Levered | G13: Preferred | I13: Equity | L13: Unlevered
B14: Name | C14: Ticker | D14: Beta | E14: Debt | F14: % Debt | G14: Stock | H14: % Preferred | I14: Value | J14: % Equity | K14: Tax Rate | L14: Beta
B15: =INDEX(Pub_Comps_Data,MATCH(WACC!$C15,Ticker_Range,0),MATCH(WACC!B$11,Pub_Comps_Info_Range,0)) -> Ryanair Holdings plc | C15: ISE:RYA | D15: =INDEX(Pub_Comps_Data,MATCH(WACC!$C15,Ticker_Range,0),MATCH(WACC!D$11,Pub_Comps_Info_Range,0)) -> 1.48 | E15: =INDEX(Pub_Comps_Data,MATCH(WACC!$C15,Ticker_Range,0),MATCH(WACC!E$11,Pub_Comps_Info_Range,0)) -> 4253.5 | F15: =E15/($E15+$G15+$I15) -> 0.24753501 | G15: =INDEX(Pub_Comps_Data,MATCH(WACC!$C15,Ticker_Range,0),MATCH(WACC!G$11,Pub_Comps_Info_Range,0)) -> 0 | H15: =G15/($E15+$G15+$I15) -> 0 | I15: =INDEX(Pub_Comps_Data,MATCH(WACC!$C15,Ticker_Range,0),MATCH(WACC!I$11,Pub_Comps_Info_Range,0)) -> 12929.928 | J15: =I15/($E15+$G15+$I15) -> 0.75246499 | K15: =INDEX(Pub_Comps_Data,MATCH(WACC!$C15,Ticker_Range,0),MATCH(WACC!K$11,Pub_Comps_Info_Range,0)) -> 0.15 | L15: =D15/(1+E15/I15*(1-K15)+G15/I15) -> 1.1565928
B16: =INDEX(Pub_Comps_Data,MATCH(WACC!$C16,Ticker_Range,0),MATCH(WACC!B$11,Pub_Comps_Info_Range,0)) -> Wizz Air Holdings Plc | C16: LSE:WIZZ | D16: =INDEX(Pub_Comps_Data,MATCH(WACC!$C16,Ticker_Range,0),MATCH(WACC!D$11,Pub_Comps_Info_Range,0)) -> 1.94 | E16: =INDEX(Pub_Comps_Data,MATCH(WACC!$C16,Ticker_Range,0),MATCH(WACC!E$11,Pub_Comps_Info_Range,0)) -> 897.08 | F16: =E16/($E16+$G16+$I16) -> 0.25557078 | G16: =INDEX(Pub_Comps_Data,MATCH(WACC!$C16,Ticker_Range,0),MATCH(WACC!G$11,Pub_Comps_Info_Range,0)) -> 0 | H16: =G16/($E16+$G16+$I16) -> 0 | I16: =INDEX(Pub_Comps_Data,MATCH(WACC!$C16,Ticker_Range,0),MATCH(WACC!I$11,Pub_Comps_Info_Range,0)) -> 2613.024 | J16: =I16/($E16+$G16+$I16) -> 0.74442922 | K16: =INDEX(Pub_Comps_Data,MATCH(WACC!$C16,Ticker_Range,0),MATCH(WACC!K$11,Pub_Comps_Info_Range,0)) -> 0.15 | L16: =D16/(1+E16/I16*(1-K16)+G16/I16) -> 1.5017637
B17: =INDEX(Pub_Comps_Data,MATCH(WACC!$C17,Ticker_Range,0),MATCH(WACC!B$11,Pub_Comps_Info_Range,0)) -> Jet2 plc | C17: AIM:JET2 | D17: =INDEX(Pub_Comps_Data,MATCH(WACC!$C17,Ticker_Range,0),MATCH(WACC!D$11,Pub_Comps_Info_Range,0)) -> 2.21 | E17: =INDEX(Pub_Comps_Data,MATCH(WACC!$C17,Ticker_Range,0),MATCH(WACC!E$11,Pub_Comps_Info_Range,0)) -> 991.7 | F17: =E17/($E17+$G17+$I17) -> 0.32074177 | G17: =INDEX(Pub_Comps_Data,MATCH(WACC!$C17,Ticker_Range,0),MATCH(WACC!G$11,Pub_Comps_Info_Range,0)) -> 0 | H17: =G17/($E17+$G17+$I17) -> 0 | I17: =INDEX(Pub_Comps_Data,MATCH(WACC!$C17,Ticker_Range,0),MATCH(WACC!I$11,Pub_Comps_Info_Range,0)) -> 2100.1954 | J17: =I17/($E17+$G17+$I17) -> 0.67925823 | K17: =INDEX(Pub_Comps_Data,MATCH(WACC!$C17,Ticker_Range,0),MATCH(WACC!K$11,Pub_Comps_Info_Range,0)) -> 0.25 | L17: =D17/(1+E17/I17*(1-K17)+G17/I17) -> 1.6320254
B18: =INDEX(Pub_Comps_Data,MATCH(WACC!$C18,Ticker_Range,0),MATCH(WACC!B$11,Pub_Comps_Info_Range,0)) -> Pegasus Hava Tasimaciligi Anonim Sirketi | C18: IBSE:PGSUS | D18: =INDEX(Pub_Comps_Data,MATCH(WACC!$C18,Ticker_Range,0),MATCH(WACC!D$11,Pub_Comps_Info_Range,0)) -> 1.69 | E18: =INDEX(Pub_Comps_Data,MATCH(WACC!$C18,Ticker_Range,0),MATCH(WACC!E$11,Pub_Comps_Info_Range,0)) -> 445.98496 | F18: =E18/($E18+$G18+$I18) -> 0.33407815 | G18: =INDEX(Pub_Comps_Data,MATCH(WACC!$C18,Ticker_Range,0),MATCH(WACC!G$11,Pub_Comps_Info_Range,0)) -> 0 | H18: =G18/($E18+$G18+$I18) -> 0 | I18: =INDEX(Pub_Comps_Data,MATCH(WACC!$C18,Ticker_Range,0),MATCH(WACC!I$11,Pub_Comps_Info_Range,0)) -> 888.987 | J18: =I18/($E18+$G18+$I18) -> 0.66592185 | K18: =INDEX(Pub_Comps_Data,MATCH(WACC!$C18,Ticker_Range,0),MATCH(WACC!K$11,Pub_Comps_Info_Range,0)) -> 0.2 | L18: =D18/(1+E18/I18*(1-K18)+G18/I18) -> 1.2059867
B19: =INDEX(Pub_Comps_Data,MATCH(WACC!$C19,Ticker_Range,0),MATCH(WACC!B$11,Pub_Comps_Info_Range,0)) -> Air Arabia PJSC | C19: DFM:AIRARABIA | D19: =INDEX(Pub_Comps_Data,MATCH(WACC!$C19,Ticker_Range,0),MATCH(WACC!D$11,Pub_Comps_Info_Range,0)) -> 0.67 | E19: =INDEX(Pub_Comps_Data,MATCH(WACC!$C19,Ticker_Range,0),MATCH(WACC!E$11,Pub_Comps_Info_Range,0)) -> 23.3344 | F19: =E19/($E19+$G19+$I19) -> 0.0093461515 | G19: =INDEX(Pub_Comps_Data,MATCH(WACC!$C19,Ticker_Range,0),MATCH(WACC!G$11,Pub_Comps_Info_Range,0)) -> 0 | H19: =G19/($E19+$G19+$I19) -> 0 | I19: =INDEX(Pub_Comps_Data,MATCH(WACC!$C19,Ticker_Range,0),MATCH(WACC!I$11,Pub_Comps_Info_Range,0)) -> 2473.351 | J19: =I19/($E19+$G19+$I19) -> 0.99065385 | K19: =INDEX(Pub_Comps_Data,MATCH(WACC!$C19,Ticker_Range,0),MATCH(WACC!K$11,Pub_Comps_Info_Range,0)) -> 0.09 | L19: =D19/(1+E19/I19*(1-K19)+G19/I19) -> 0.66429685
B20: =INDEX(Pub_Comps_Data,MATCH(WACC!$C20,Ticker_Range,0),MATCH(WACC!B$11,Pub_Comps_Info_Range,0)) -> Norwegian Air Shuttle ASA | C20: OB:NAS | D20: =INDEX(Pub_Comps_Data,MATCH(WACC!$C20,Ticker_Range,0),MATCH(WACC!D$11,Pub_Comps_Info_Range,0)) -> 0.99 | E20: =INDEX(Pub_Comps_Data,MATCH(WACC!$C20,Ticker_Range,0),MATCH(WACC!E$11,Pub_Comps_Info_Range,0)) -> 360.7504 | F20: =E20/($E20+$G20+$I20) -> 0.31590724 | G20: =INDEX(Pub_Comps_Data,MATCH(WACC!$C20,Ticker_Range,0),MATCH(WACC!G$11,Pub_Comps_Info_Range,0)) -> 0 | H20: =G20/($E20+$G20+$I20) -> 0 | I20: =INDEX(Pub_Comps_Data,MATCH(WACC!$C20,Ticker_Range,0),MATCH(WACC!I$11,Pub_Comps_Info_Range,0)) -> 781.2 | J20: =I20/($E20+$G20+$I20) -> 0.68409276 | K20: =INDEX(Pub_Comps_Data,MATCH(WACC!$C20,Ticker_Range,0),MATCH(WACC!K$11,Pub_Comps_Info_Range,0)) -> 0.22 | L20: =D20/(1+E20/I20*(1-K20)+G20/I20) -> 0.72783615
B21: =INDEX(Pub_Comps_Data,MATCH(WACC!$C21,Ticker_Range,0),MATCH(WACC!B$11,Pub_Comps_Info_Range,0)) -> Jazeera Airways K.S.C.P. | C21: KWSE:JAZEERA | D21: =INDEX(Pub_Comps_Data,MATCH(WACC!$C21,Ticker_Range,0),MATCH(WACC!D$11,Pub_Comps_Info_Range,0)) -> 0.85 | E21: =INDEX(Pub_Comps_Data,MATCH(WACC!$C21,Ticker_Range,0),MATCH(WACC!E$11,Pub_Comps_Info_Range,0)) -> 60.3684 | F21: =E21/($E21+$G21+$I21) -> 0.047768563 | G21: =INDEX(Pub_Comps_Data,MATCH(WACC!$C21,Ticker_Range,0),MATCH(WACC!G$11,Pub_Comps_Info_Range,0)) -> 0 | H21: =G21/($E21+$G21+$I21) -> 0 | I21: =INDEX(Pub_Comps_Data,MATCH(WACC!$C21,Ticker_Range,0),MATCH(WACC!I$11,Pub_Comps_Info_Range,0)) -> 1203.4 | J21: =I21/($E21+$G21+$I21) -> 0.95223144 | K21: =INDEX(Pub_Comps_Data,MATCH(WACC!$C21,Ticker_Range,0),MATCH(WACC!K$11,Pub_Comps_Info_Range,0)) -> 0.15 | L21: =D21/(1+E21/I21*(1-K21)+G21/I21) -> 0.81523813
B23: Median: | D23: =MEDIAN(D15:D21) -> 1.48 | E23: =MEDIAN(E15:E21) -> 445.98496 | F23: =MEDIAN(F15:F21) -> 0.25557078 | G23: =MEDIAN(G15:G21) -> 0 | H23: =MEDIAN(H15:H21) -> 0 | I23: =MEDIAN(I15:I21) -> 2100.1954 | J23: =MEDIAN(J15:J21) -> 0.74442922 | K23: =MEDIAN(K15:K21) -> 0.15 | L23: =MEDIAN(L15:L21) -> 1.1565928
B25: =Company_Name -> easyJet plc | C25: =Ticker -> LSE:EZJ | D25: =Public_Comps!G23 -> 2.45
B27: =TEXT(Company_Name,"")& " - Levered Beta & WACC Calculation:" -> easyJet plc - Levered Beta & WACC Calculation:
D28: Unlevered | G28: Preferred | I28: Equity | L28: Levered
C29: Ticker | D29: Beta | E29: Debt | F29: % Debt | G29: Stock | H29: % Preferred | I29: Value | J29: % Equity | K29: Tax Rate | L29: Beta
B30: Current Capital Structure: | C30: =Ticker -> LSE:EZJ | D30: =L23 -> 1.1565928 | E30: =INDEX(Pub_Comps_Data,MATCH(WACC!$C30,Ticker_Range,0),MATCH(WACC!E$11,Pub_Comps_Info_Range,0)) -> 3046 | F30: =E30/($E30+$G30+$I30) -> 0.46969721 | G30: =INDEX(Pub_Comps_Data,MATCH(WACC!$C30,Ticker_Range,0),MATCH(WACC!G$11,Pub_Comps_Info_Range,0)) -> 0 | H30: =G30/($E30+$G30+$I30) -> 0 | I30: =INDEX(Pub_Comps_Data,MATCH(WACC!$C30,Ticker_Range,0),MATCH(WACC!I$11,Pub_Comps_Info_Range,0)) -> 3439.029 | J30: =I30/($E30+$G30+$I30) -> 0.53030279 | K30: =INDEX(Pub_Comps_Data,MATCH(WACC!$C30,Ticker_Range,0),MATCH(WACC!K$11,Pub_Comps_Info_Range,0)) -> 0.25 | L30: =D30*(1+E30/I30*(1-K30)+G30/I30) -> 1.9249015
B31: "Optimal" Capital Structure: | C31: =Ticker -> LSE:EZJ | D31: =L23 -> 1.1565928 | E31: =($E$30+$G$30+$I$30)*F31 -> 1657.3839 | F31: =1-J31-H31 -> 0.25557078 | G31: =($E$30+$G$30+$I$30)*H31 -> 0 | H31: =H23 -> 0 | I31: =($E$30+$G$30+$I$30)*J31 -> 4827.6451 | J31: =J23 -> 0.74442922 | K31: =INDEX(Pub_Comps_Data,MATCH(WACC!$C31,Ticker_Range,0),MATCH(WACC!K$11,Pub_Comps_Info_Range,0)) -> 0.25 | L31: =D31*(1+E31/I31*(1-K31)+G31/I31) -> 1.4543961
B33: Cost of Equity Based on Comparables, Current Capital Structure: | L33: =Risk_Free_Rate+Equity_Risk_Premium*L30 -> 0.1703186
B34: Cost of Equity Based on Comparables, "Optimal" Capital Structure: | L34: =Risk_Free_Rate+Equity_Risk_Premium*L31 -> 0.13973574
B35: Cost of Equity Based on Historical Beta: | L35: =Risk_Free_Rate+Equity_Risk_Premium*D25 -> 0.20445
B37: WACC, Current Capital Structure: | L37: =L33*J30+Cost_of_Debt*(1-Tax_Rate)*F30+Cost_of_Preferred*H30 -> 0.10793408
B38: WACC, "Optimal" Capital Structure: | L38: =L34*J31+Cost_of_Debt*(1-Tax_Rate)*F31+Cost_of_Preferred*H31 -> 0.11360728
B39: WACC, Current Capital Structure and Historical Cost of Equity: | L39: =L35*J30+Cost_of_Debt*(1-Tax_Rate)*F30+Cost_of_Preferred*H30 -> 0.12603405
B41: Average WACC Produced by All Methods: | L41: =AVERAGE(L37:L39) -> 0.11585847

Sheet Public_Comps
B2: Comparable Public Companies - EMEA Low-Cost Carriers (LCCs) with LTM Revenue Above £100 Million
B3: (£ GBP in Millions Except Per Share Amounts in GBP as Stated)
B4: (Enterprise Value Includes Operating Lease and Finance Lease Liabilities; EBITDA Excludes Entire Lease Expense with IFRS Accounting)
B6: Operating Statistics: | F6: Capitalisation | X6: 2-Year | Y6: 2-Year
D7: Share | E7: Diluted | F7: Equity | K7: Total | M7: Other & | N7: Enterprise | O7: Revenue | R7: EBITDA | U7: Net Income | X7: Revenue | Y7: EBITDA | Z7: EBITDA Margin
B8: Company Name | C8: Ticker | D8: Price | E8: Shares | F8: Value | G8: Beta | H8: Tax Rate | I8: Cash | J8: Debt | K8: Leases | L8: Preferred | M8: NCI | N8: Value | O8: ="CY "&TEXT(DCF!H43,"YY") -> CY 22 | P8: ="CY "&TEXT(DCF!I43,"YY") -> CY 23 | Q8: ="CY "&TEXT(DCF!J43,"YY") -> CY 24 | R8: =$O$8 -> CY 22 | S8: =$P$8 -> CY 23 | T8: =$Q$8 -> CY 24 | U8: =$O$8 -> CY 22 | V8: =$P$8 -> CY 23 | W8: =$Q$8 -> CY 24 | X8: CAGR | Y8: CAGR | Z8: =$O$8 -> CY 22 | AA8: =$P$8 -> CY 23 | AB8: =$Q$8 -> CY 24
B9: Ryanair Holdings plc | C9: ISE:RYA | D9: 11.39 | E9: 1135.2 | F9: =D9*E9 -> 12929.928 | G9: 1.48 | H9: 0.15 | I9: -4001.3 | J9: 4253.5 | K9: 113.6 | L9: 0 | M9: 0 | N9: =F9+I9+J9+K9+L9+M9 -> 13295.728 | O9: =4154.1*(1/4)+8701.24*(3/4) -> 7564.455 | P9: =8701.24*(1/4)+10501.8*(3/4) -> 10051.66 | Q9: =10501.8*(1/4)+11726.9*(3/4) -> 11420.625 | R9: =281.5*(1/4)+1936.94*(3/4) -> 1523.08 | S9: =1936.94*(1/4)+2069.58*(3/4) -> 2036.42 | T9: =2069.58*(1/4)+2671.16*(3/4) -> 2520.765 | U9: =-208.4*(1/4)+1062.92*(3/4) -> 745.09 | V9: =1062.92*(1/4)+1131.45*(3/4) -> 1114.3175 | W9: =1131.45*(1/4)+1573.37*(3/4) -> 1462.89 | X9: =IFERROR((Q9/O9)^(1/2)-1,"N/A") -> 0.22872902 | Y9: =IFERROR((T9/R9)^(1/2)-1,"N/A") -> 0.28648528 | Z9: =R9/O9 -> 0.20134696 | AA9: =S9/P9 -> 0.20259539 | AB9: =T9/Q9 -> 0.22072041
B10: Wizz Air Holdings Plc | C10: LSE:WIZZ | D10: 25.32 | E10: 103.2 | F10: =D10*E10 -> 2613.024 | G10: 1.94 | H10: 0.15 | I10: -1052.7 | J10: 897.08 | K10: 2533.62 | L10: 0 | M10: -13.3 | N10: =F10+I10+J10+K10+L10+M10 -> 4977.724 | O10: =1439.3*(1/4)+3401.25*(3/4) -> 2910.7625 | P10: =3401.25*(1/4)+4576.03*(3/4) -> 4282.335 | Q10: =4576.03*(1/4)+5611.81*(3/4) -> 5352.865 | R10: =-342*(1/4)+262.88*(3/4) -> 111.66 | S10: =262.88*(1/4)+888.02*(3/4) -> 731.735 | T10: =888.02*(1/4)+1242.88*(3/4) -> 1154.165 | U10: =-546.7*(1/4)-495.32*(3/4) -> -508.165 | V10: =-495.32*(1/4)+233.04*(3/4) -> 50.95 | W10: =233.04*(1/4)+484.23*(3/4) -> 421.4325 | X10: =IFERROR((Q10/O10)^(1/2)-1,"N/A") -> 0.35609389 | Y10: =IFERROR((T10/R10)^(1/2)-1,"N/A") -> 2.2150308 | Z10: =R10/O10 -> 0.038361082 | AA10: =S10/P10 -> 0.1708729 | AB10: =T10/Q10 -> 0.21561631
B11: Jet2 plc | C11: AIM:JET2 | D11: 9.782 | E11: 214.7 | F11: =D11*E11 -> 2100.1954 | G11: 2.21 | H11: 0.25 | I11: -2228.5 | J11: =134.5+857.2 -> 991.7 | K11: =74.8+503.7 -> 578.5 | L11: 0 | M11: 0 | N11: =F11+I11+J11+K11+L11+M11 -> 1441.8954 | O11: =1231.7*(1/4)+4709.88*(3/4) -> 3840.335 | P11: =4709.88*(1/4)+5214.73*(3/4) -> 5088.5175 | Q11: =5214.73*(1/4)+5619.64*(3/4) -> 5518.4125 | R11: =-218.7*(1/4)+536*(3/4) -> 347.325 | S11: =536*(1/4)+557.97*(3/4) -> 552.4775 | T11: =557.97*(1/4)+630.67*(3/4) -> 612.495 | U11: =-315.4*(1/4)+227.98*(3/4) -> 92.135 | V11: =227.98*(1/4)+230.46*(3/4) -> 229.84 | W11: =230.46*(1/4)+280.1*(3/4) -> 267.69 | X11: =IFERROR((Q11/O11)^(1/2)-1,"N/A") -> 0.19873318 | Y11: =IFERROR((T11/R11)^(1/2)-1,"N/A") -> 0.32795467 | Z11: =R11/O11 -> 0.090441329 | AA11: =S11/P11 -> 0.10857337 | AB11: =T11/Q11 -> 0.11099116
B12: Air Arabia PJSC | C12: DFM:AIRARABIA | D12: 0.53 | E12: 4666.7 | F12: =D12*E12 -> 2473.351 | G12: 0.67 | H12: 0.09 | I12: -1025.3 | J12: =703.3-K12 -> 23.3344 | K12: =(591.8+2241.39)*0.24 -> 679.9656 | L12: 0 | M12: 0 | N12: =F12+I12+J12+K12+L12+M12 -> 2151.351 | O12: 1095.82 | P12: 1214.1 | Q12: 1259.29 | R12: 356.56 | S12: 366.08 | T12: 380.18 | U12: 234.34 | V12: 229.93 | W12: 236.37 | X12: =IFERROR((Q12/O12)^(1/2)-1,"N/A") -> 0.07199625 | Y12: =IFERROR((T12/R12)^(1/2)-1,"N/A") -> 0.03259097 | Z12: =R12/O12 -> 0.32538191 | AA12: =S12/P12 -> 0.30152376 | AB12: =T12/Q12 -> 0.30190028
B13: Pegasus Hava Tasimaciligi Anonim Sirketi | C13: IBSE:PGSUS | D13: 8.69 | E13: 102.3 | F13: =D13*E13 -> 888.987 | G13: 1.69 | H13: 0.2 | I13: -488.6 | J13: =2325.1-K13 -> 445.98496 | K13: =(33012.1+6136.13)*0.048 -> 1879.115 | L13: 0 | M13: 0 | N13: =F13+I13+J13+K13+L13+M13 -> 2725.487 | O13: 1628.17 | P13: 2412.22 | Q13: 2915.87 | R13: 456.19 | S13: 755.68 | T13: 1038.98 | U13: 48.29 | V13: 154.96 | W13: 490.11 | X13: =IFERROR((Q13/O13)^(1/2)-1,"N/A") -> 0.33824061 | Y13: =IFERROR((T13/R13)^(1/2)-1,"N/A") -> 0.50914411 | Z13: =R13/O13 -> 0.28018573 | AA13: =S13/P13 -> 0.31327159 | AB13: =T13/Q13 -> 0.35631904
B14: Norwegian Air Shuttle ASA | C14: OB:NAS | D14: 0.84 | E14: 930 | F14: =D14*E14 -> 781.2 | G14: 0.99 | H14: 0.22 | I14: -649.5 | J14: =884.8-K14 -> 360.7504 | K14: =(1103.3+4990.3)*0.086 -> 524.0496 | L14: 0 | M14: 0 | N14: =F14+I14+J14+K14+L14+M14 -> 1016.5 | O14: 1558.63 | P14: 2070.58 | Q14: 2295.52 | R14: -23.16 | S14: 282.04 | T14: 416.77 | U14: 15.01 | V14: 42.59 | W14: 96.54 | X14: =IFERROR((Q14/O14)^(1/2)-1,"N/A") -> 0.21358172 | Y14: =IFERROR((T14/R14)^(1/2)-1,"N/A") -> N/A | Z14: =R14/O14 -> -0.014859203 | AA14: =S14/P14 -> 0.13621304 | AB14: =T14/Q14 -> 0.18155799
B15: Jazeera Airways K.S.C.P. | C15: KWSE:JAZEERA | D15: 5.47 | E15: 220 | F15: =D15*E15 -> 1203.4 | G15: 0.85 | H15: 0.15 | I15: -124.3 | J15: =460.4-K15 -> 60.3684 | K15: =(21.27+121.09)*2.81 -> 400.0316 | L15: 0 | M15: 0 | N15: =F15+I15+J15+K15+L15+M15 -> 1539.5 | O15: 401.18 | P15: 484.55 | Q15: 538.03 | R15: 116.15 | S15: 144.55 | T15: 181.01 | U15: 44.89 | V15: 66.34 | W15: 77.71 | X15: =IFERROR((Q15/O15)^(1/2)-1,"N/A") -> 0.15806679 | Y15: =IFERROR((T15/R15)^(1/2)-1,"N/A") -> 0.24836527 | Z15: =R15/O15 -> 0.28952091 | AA15: =S15/P15 -> 0.29831803 | AB15: =T15/Q15 -> 0.33643105
B17: Maximum | D17: =MAX(D9:D15) -> 25.32 | F17: =MAX(F9:F15) -> 12929.928 | G17: =MAX(G9:G15) -> 2.21 | N17: =MAX(N9:N15) -> 13295.728 | O17: =MAX(O9:O15) -> 7564.455 | P17: =MAX(P9:P15) -> 10051.66 | Q17: =MAX(Q9:Q15) -> 11420.625 | R17: =MAX(R9:R15) -> 1523.08 | S17: =MAX(S9:S15) -> 2036.42 | T17: =MAX(T9:T15) -> 2520.765 | U17: =MAX(U9:U15) -> 745.09 | ... AB17: =MAX(AB9:AB15) -> 0.35631904
B18: 75th Percentile | D18: =QUARTILE(D9:D15,3) -> 10.586 | F18: =QUARTILE(F9:F15,3) -> 2543.1875 | G18: =QUARTILE(G9:G15,3) -> 1.815 | N18: =QUARTILE(N9:N15,3) -> 3851.6055 | O18: =QUARTILE(O9:O15,3) -> 3375.5487 | P18: =QUARTILE(P9:P15,3) -> 4685.4263 | Q18: =QUARTILE(Q9:Q15,3) -> 5435.6388 | R18: =QUARTILE(R9:R15,3) -> 406.375 | S18: =QUARTILE(S9:S15,3) -> 743.7075 | T18: =QUARTILE(T9:T15,3) -> 1096.5725 | U18: =QUARTILE(U9:U15,3) -> 163.2375 | ... AB18: =QUARTILE(AB9:AB15,3) -> 0.31916567
B19: Median | D19: =MEDIAN(D9:D15) -> 8.69 | F19: =MEDIAN(F9:F15) -> 2100.1954 | G19: =MEDIAN(G9:G15) -> 1.48 | N19: =MEDIAN(N9:N15) -> 2151.351 | O19: =MEDIAN(O9:O15) -> 1628.17 | P19: =MEDIAN(P9:P15) -> 2412.22 | Q19: =MEDIAN(Q9:Q15) -> 2915.87 | R19: =MEDIAN(R9:R15) -> 347.325 | S19: =MEDIAN(S9:S15) -> 552.4775 | T19: =MEDIAN(T9:T15) -> 612.495 | U19: =MEDIAN(U9:U15) -> 48.29 | ... AB19: =MEDIAN(AB9:AB15) -> 0.22072041
B20: 25th Percentile | D20: =QUARTILE(D9:D15,1) -> 3.155 | F20: =QUARTILE(F9:F15,1) -> 1046.1935 | G20: =QUARTILE(G9:G15,1) -> 0.92 | N20: =QUARTILE(N9:N15,1) -> 1490.6977 | O20: =QUARTILE(O9:O15,1) -> 1327.225 | P20: =QUARTILE(P9:P15,1) -> 1642.34 | Q20: =QUARTILE(Q9:Q15,1) -> 1777.405 | R20: =QUARTILE(R9:R15,1) -> 113.905 | S20: =QUARTILE(S9:S15,1) -> 324.06 | T20: =QUARTILE(T9:T15,1) -> 398.475 | U20: =QUARTILE(U9:U15,1) -> 29.95 | ... AB20: =QUARTILE(AB9:AB15,1) -> 0.19858715
B21: Minimum | D21: =MIN(D9:D15) -> 0.53 | F21: =MIN(F9:F15) -> 781.2 | G21: =MIN(G9:G15) -> 0.67 | N21: =MIN(N9:N15) -> 1016.5 | O21: =MIN(O9:O15) -> 401.18 | P21: =MIN(P9:P15) -> 484.55 | Q21: =MIN(Q9:Q15) -> 538.03 | R21: =MIN(R9:R15) -> -23.16 | S21: =MIN(S9:S15) -> 144.55 | T21: =MIN(T9:T15) -> 181.01 | U21: =MIN(U9:U15) -> -508.165 | ... AB21: =MIN(AB9:AB15) -> 0.11099116
B23: =Company_Name -> easyJet plc | C23: =Ticker -> LSE:EZJ | D23: =Share_Price -> 4.531 | E23: =Diluted_Shares -> 759 | F23: =D23*E23 -> 3439.029 | G23: 2.45 | H23: =Tax_Rate -> 0.25 | I23: =DCF!E20 -> -3505 | J23: =DCF!E22 -> 3046 | K23: =DCF!E24 -> 1055 | L23: =DCF!E23 -> 0 | M23: =DCF!E21+SUM(DCF!E25:E26) -> -608.94246 | N23: =F23+I23+J23+K23+L23+M23 -> 3426.0865 | O23: =EZJ!K94*0.5+EZJ!L94+EZJ!M94*0.5 -> 4538.6712 | P23: =EZJ!M94*0.5+EZJ!N94+EZJ!O94*0.5 -> 6310.6335 | Q23: =EZJ!N94*0.5+EZJ!O94+EZJ!P94*0.5 -> 6940.9992 | R23: =EZJ!K97*0.5+EZJ!L97+EZJ!M97*0.5 -> 314.60379 | S23: =EZJ!M97*0.5+EZJ!N97+EZJ!O97*0.5 -> 715.0827 | T23: =EZJ!N97*0.5+EZJ!O97+EZJ!P97*0.5 -> 853.71559 | U23: =EZJ!K114+EZJ!L114*0.5+EZJ!M114*0.5 -> -504.72648 | V23: =EZJ!M114*0.5+EZJ!N114+EZJ!O114*0.5 -> 111.90475 | W23: =EZJ!N114*0.5+EZJ!O114+EZJ!P114*0.5 -> 199.9336 | X23: =IFERROR((Q23/O23)^(1/2)-1,"N/A") -> 0.23664954 | Y23: =IFERROR((T23/R23)^(1/2)-1,"N/A") -> 0.64730732 | Z23: =R23/O23 -> 0.069316278 | AA23: =S23/P23 -> 0.11331393
B25: Valuation Statistics: | F25: Capitalisation | O25: Enterprise Value / | R25: Enterprise Value /
F26: Equity | N26: Enterprise | O26: Revenue | R26: EBITDA | U26: P / E Multiple
B27: Company Name | F27: Value | N27: Value | O27: =$O$8 -> CY 22 | P27: =$P$8 -> CY 23 | Q27: =$Q$8 -> CY 24 | R27: =$O$8 -> CY 22 | S27: =$P$8 -> CY 23 | T27: =$Q$8 -> CY 24 | U27: =$O$8 -> CY 22 | V27: =$P$8 -> CY 23 | W27: =$Q$8 -> CY 24
B28: =B9 -> Ryanair Holdings plc | C28: =C9 -> ISE:RYA | F28: =F9 -> 12929.928 | N28: =N9 -> 13295.728 | O28: =IFERROR(IF(OR(+$N9/O9<0,+$N9/O9>=100),"NM",+$N9/O9),"N/A") -> 1.7576584 | P28: =IFERROR(IF(OR(+$N9/P9<0,+$N9/P9>=100),"NM",+$N9/P9),"N/A") -> 1.3227395 | Q28: =IFERROR(IF(OR(+$N9/Q9<0,+$N9/Q9>=100),"NM",+$N9/Q9),"N/A") -> 1.1641857 | R28: =IFERROR(IF(OR(+$N9/R9<0,+$N9/R9>=100),"NM",+$N9/R9),"N/A") -> 8.7295007 | S28: =IFERROR(IF(OR(+$N9/S9<0,+$N9/S9>=100),"NM",+$N9/S9),"N/A") -> 6.5289714 | T28: =IFERROR(IF(OR(+$N9/T9<0,+$N9/T9>=100),"NM",+$N9/T9),"N/A") -> 5.2744814 | U28: =IFERROR(IF(OR(+$F9/U9<0,+$F9/U9>=100),"NM",+$F9/U9),"N/A") -> 17.353512 | V28: =IFERROR(IF(OR(+$F9/V9<0,+$F9/V9>=100),"NM",+$F9/V9),"N/A") -> 11.603451 | W28: =IFERROR(IF(OR(+$F9/W9<0,+$F9/W9>=100),"NM",+$F9/W9),"N/A") -> 8.8386194
B29: =B10 -> Wizz Air Holdings Plc | C29: =C10 -> LSE:WIZZ | F29: =F10 -> 2613.024 | N29: =N10 -> 4977.724 | O29: =IFERROR(IF(OR(+$N10/O10<0,+$N10/O10>=100),"NM",+$N10/O10),"N/A") -> 1.71011 | P29: =IFERROR(IF(OR(+$N10/P10<0,+$N10/P10>=100),"NM",+$N10/P10),"N/A") -> 1.1623855 | Q29: =IFERROR(IF(OR(+$N10/Q10<0,+$N10/Q10>=100),"NM",+$N10/Q10),"N/A") -> 0.92991772 | R29: =IFERROR(IF(OR(+$N10/R10<0,+$N10/R10>=100),"NM",+$N10/R10),"N/A") -> 44.579294 | S29: =IFERROR(IF(OR(+$N10/S10<0,+$N10/S10>=100),"NM",+$N10/S10),"N/A") -> 6.8026321 | T29: =IFERROR(IF(OR(+$N10/T10<0,+$N10/T10>=100),"NM",+$N10/T10),"N/A") -> 4.3128357 | U29: =IFERROR(IF(OR(+$F10/U10<0,+$F10/U10>=100),"NM",+$F10/U10),"N/A") -> NM | V29: =IFERROR(IF(OR(+$F10/V10<0,+$F10/V10>=100),"NM",+$F10/V10),"N/A") -> 51.286045 | W29: =IFERROR(IF(OR(+$F10/W10<0,+$F10/W10>=100),"NM",+$F10/W10),"N/A") -> 6.2003381
B30: =B11 -> Jet2 plc | C30: =C11 -> AIM:JET2 | F30: =F11 -> 2100.1954 | N30: =N11 -> 1441.8954 | O30: =IFERROR(IF(OR(+$N11/O11<0,+$N11/O11>=100),"NM",+$N11/O11),"N/A") -> 0.37546084 | P30: =IFERROR(IF(OR(+$N11/P11<0,+$N11/P11>=100),"NM",+$N11/P11),"N/A") -> 0.28336257 | Q30: =IFERROR(IF(OR(+$N11/Q11<0,+$N11/Q11>=100),"NM",+$N11/Q11),"N/A") -> 0.26128808 | R30: =IFERROR(IF(OR(+$N11/R11<0,+$N11/R11>=100),"NM",+$N11/R11),"N/A") -> 4.1514299 | S30: =IFERROR(IF(OR(+$N11/S11<0,+$N11/S11>=100),"NM",+$N11/S11),"N/A") -> 2.6098717 | T30: =IFERROR(IF(OR(+$N11/T11<0,+$N11/T11>=100),"NM",+$N11/T11),"N/A") -> 2.3541342 | U30: =IFERROR(IF(OR(+$F11/U11<0,+$F11/U11>=100),"NM",+$F11/U11),"N/A") -> 22.794762 | V30: =IFERROR(IF(OR(+$F11/V11<0,+$F11/V11>=100),"NM",+$F11/V11),"N/A") -> 9.137641 | W30: =IFERROR(IF(OR(+$F11/W11<0,+$F11/W11>=100),"NM",+$F11/W11),"N/A") -> 7.8456252
B31: =B12 -> Air Arabia PJSC | C31: =C12 -> DFM:AIRARABIA | F31: =F12 -> 2473.351 | N31: =N12 -> 2151.351 | O31: =IFERROR(IF(OR(+$N12/O12<0,+$N12/O12>=100),"NM",+$N12/O12),"N/A") -> 1.9632339 | P31: =IFERROR(IF(OR(+$N12/P12<0,+$N12/P12>=100),"NM",+$N12/P12),"N/A") -> 1.7719718 | Q31: =IFERROR(IF(OR(+$N12/Q12<0,+$N12/Q12>=100),"NM",+$N12/Q12),"N/A") -> 1.7083841 | R31: =IFERROR(IF(OR(+$N12/R12<0,+$N12/R12>=100),"NM",+$N12/R12),"N/A") -> 6.0336297 | S31: =IFERROR(IF(OR(+$N12/S12<0,+$N12/S12>=100),"NM",+$N12/S12),"N/A") -> 5.8767237 | T31: =IFERROR(IF(OR(+$N12/T12<0,+$N12/T12>=100),"NM",+$N12/T12),"N/A") -> 5.6587695 | U31: =IFERROR(IF(OR(+$F12/U12<0,+$F12/U12>=100),"NM",+$F12/U12),"N/A") -> 10.55454 | V31: =IFERROR(IF(OR(+$F12/V12<0,+$F12/V12>=100),"NM",+$F12/V12),"N/A") -> 10.756974 | W31: =IFERROR(IF(OR(+$F12/W12<0,+$F12/W12>=100),"NM",+$F12/W12),"N/A") -> 10.463896
B32: =B13 -> Pegasus Hava Tasimaciligi Anonim Sirketi | C32: =C13 -> IBSE:PGSUS | F32: =F13 -> 888.987 | N32: =N13 -> 2725.487 | O32: =IFERROR(IF(OR(+$N13/O13<0,+$N13/O13>=100),"NM",+$N13/O13),"N/A") -> 1.6739573 | P32: =IFERROR(IF(OR(+$N13/P13<0,+$N13/P13>=100),"NM",+$N13/P13),"N/A") -> 1.1298667 | Q32: =IFERROR(IF(OR(+$N13/Q13<0,+$N13/Q13>=100),"NM",+$N13/Q13),"N/A") -> 0.93470799 | R32: =IFERROR(IF(OR(+$N13/R13<0,+$N13/R13>=100),"NM",+$N13/R13),"N/A") -> 5.9744558 | S32: =IFERROR(IF(OR(+$N13/S13<0,+$N13/S13>=100),"NM",+$N13/S13),"N/A") -> 3.6066682 | T32: =IFERROR(IF(OR(+$N13/T13<0,+$N13/T13>=100),"NM",+$N13/T13),"N/A") -> 2.6232334 | U32: =IFERROR(IF(OR(+$F13/U13<0,+$F13/U13>=100),"NM",+$F13/U13),"N/A") -> 18.409339 | V32: =IFERROR(IF(OR(+$F13/V13<0,+$F13/V13>=100),"NM",+$F13/V13),"N/A") -> 5.7368805 | W32: =IFERROR(IF(OR(+$F13/W13<0,+$F13/W13>=100),"NM",+$F13/W13),"N/A") -> 1.813852
B33: =B14 -> Norwegian Air Shuttle ASA | C33: =C14 -> OB:NAS | F33: =F14 -> 781.2 | N33: =N14 -> 1016.5 | O33: =IFERROR(IF(OR(+$N14/O14<0,+$N14/O14>=100),"NM",+$N14/O14),"N/A") -> 0.65217531 | P33: =IFERROR(IF(OR(+$N14/P14<0,+$N14/P14>=100),"NM",+$N14/P14),"N/A") -> 0.49092525 | Q33: =IFERROR(IF(OR(+$N14/Q14<0,+$N14/Q14>=100),"NM",+$N14/Q14),"N/A") -> 0.44281906 | R33: =IFERROR(IF(OR(+$N14/R14<0,+$N14/R14>=100),"NM",+$N14/R14),"N/A") -> NM | S33: =IFERROR(IF(OR(+$N14/S14<0,+$N14/S14>=100),"NM",+$N14/S14),"N/A") -> 3.6040987 | T33: =IFERROR(IF(OR(+$N14/T14<0,+$N14/T14>=100),"NM",+$N14/T14),"N/A") -> 2.4389951 | U33: =IFERROR(IF(OR(+$F14/U14<0,+$F14/U14>=100),"NM",+$F14/U14),"N/A") -> 52.045303 | V33: =IFERROR(IF(OR(+$F14/V14<0,+$F14/V14>=100),"NM",+$F14/V14),"N/A") -> 18.342334 | W33: =IFERROR(IF(OR(+$F14/W14<0,+$F14/W14>=100),"NM",+$F14/W14),"N/A") -> 8.0919826
B34: =B15 -> Jazeera Airways K.S.C.P. | C34: =C15 -> KWSE:JAZEERA | F34: =F15 -> 1203.4 | N34: =N15 -> 1539.5 | O34: =IFERROR(IF(OR(+$N15/O15<0,+$N15/O15>=100),"NM",+$N15/O15),"N/A") -> 3.8374296 | P34: =IFERROR(IF(OR(+$N15/P15<0,+$N15/P15>=100),"NM",+$N15/P15),"N/A") -> 3.1771747 | Q34: =IFERROR(IF(OR(+$N15/Q15<0,+$N15/Q15>=100),"NM",+$N15/Q15),"N/A") -> 2.8613646 | R34: =IFERROR(IF(OR(+$N15/R15<0,+$N15/R15>=100),"NM",+$N15/R15),"N/A") -> 13.254412 | S34: =IFERROR(IF(OR(+$N15/S15<0,+$N15/S15>=100),"NM",+$N15/S15),"N/A") -> 10.650294 | T34: =IFERROR(IF(OR(+$N15/T15<0,+$N15/T15>=100),"NM",+$N15/T15),"N/A") -> 8.505055 | U34: =IFERROR(IF(OR(+$F15/U15<0,+$F15/U15>=100),"NM",+$F15/U15),"N/A") -> 26.807752 | V34: =IFERROR(IF(OR(+$F15/V15<0,+$F15/V15>=100),"NM",+$F15/V15),"N/A") -> 18.139885 | W34: =IFERROR(IF(OR(+$F15/W15<0,+$F15/W15>=100),"NM",+$F15/W15),"N/A") -> 15.48578
B36: Maximum | F36: =MAX(F28:F34) -> 12929.928 | N36: =MAX(N28:N34) -> 13295.728 | O36: =MAX(O28:O34) -> 3.8374296 | P36: =MAX(P28:P34) -> 3.1771747 | Q36: =MAX(Q28:Q34) -> 2.8613646 | R36: =MAX(R28:R34) -> 44.579294 | S36: =MAX(S28:S34) -> 10.650294 | T36: =MAX(T28:T34) -> 8.505055 | U36: =MAX(U28:U34) -> 52.045303 | ... W36: =MAX(W28:W34) -> 15.48578
B37: 75th Percentile | F37: =QUARTILE(F28:F34,3) -> 2543.1875 | N37: =QUARTILE(N28:N34,3) -> 3851.6055 | O37: =QUARTILE(O28:O34,3) -> 1.8604462 | P37: =QUARTILE(P28:P34,3) -> 1.5473557 | Q37: =QUARTILE(Q28:Q34,3) -> 1.4362849 | R37: =QUARTILE(R28:R34,3) -> 12.123184 | S37: =QUARTILE(S28:S34,3) -> 6.6658018 | T37: =QUARTILE(T28:T34,3) -> 5.4666254 | U37: =QUARTILE(U28:U34,3) -> 25.804505 | ... W37: =QUARTILE(W28:W34,3) -> 9.6512575
B38: Median | F38: =MEDIAN(F28:F34) -> 2100.1954 | N38: =MEDIAN(N28:N34) -> 2151.351 | O38: =MEDIAN(O28:O34) -> 1.71011 | P38: =MEDIAN(P28:P34) -> 1.1623855 | Q38: =MEDIAN(Q28:Q34) -> 0.93470799 | R38: =MEDIAN(R28:R34) -> 7.3815652 | S38: =MEDIAN(S28:S34) -> 5.8767237 | T38: =MEDIAN(T28:T34) -> 4.3128357 | U38: =MEDIAN(U28:U34) -> 20.602051 | ... W38: =MEDIAN(W28:W34) -> 8.0919826
B39: 25th Percentile | F39: =QUARTILE(F28:F34,1) -> 1046.1935 | N39: =QUARTILE(N28:N34,1) -> 1490.6977 | O39: =QUARTILE(O28:O34,1) -> 1.1630663 | P39: =QUARTILE(P28:P34,1) -> 0.81039596 | Q39: =QUARTILE(Q28:Q34,1) -> 0.68636839 | R39: =QUARTILE(R28:R34,1) -> 5.9892493 | S39: =QUARTILE(S28:S34,1) -> 3.6053834 | T39: =QUARTILE(T28:T34,1) -> 2.5311142 | U39: =QUARTILE(U28:U34,1) -> 17.617469 | ... W39: =QUARTILE(W28:W34,1) -> 7.0229816
B40: Minimum | F40: =MIN(F28:F34) -> 781.2 | N40: =MIN(N28:N34) -> 1016.5 | O40: =MIN(O28:O34) -> 0.37546084 | P40: =MIN(P28:P34) -> 0.28336257 | Q40: =MIN(Q28:Q34) -> 0.26128808 | R40: =MIN(R28:R34) -> 4.1514299 | S40: =MIN(S28:S34) -> 2.6098717 | T40: =MIN(T28:T34) -> 2.3541342 | U40: =MIN(U28:U34) -> 10.55454 | ... W40: =MIN(W28:W34) -> 1.813852
B42: =Company_Name -> easyJet plc | C42: =Ticker -> LSE:EZJ | F42: =F23 -> 3439.029 | N42: =N23 -> 3426.0865 | O42: =IFERROR(IF(OR(+$N23/O23<0,+$N23/O23>=100),"NM",+$N23/O23),"N/A") -> 0.75486556 | P42: =IFERROR(IF(OR(+$N23/P23<0,+$N23/P23>=100),"NM",+$N23/P23),"N/A") -> 0.54290691 | Q42: =IFERROR(IF(OR(+$N23/Q23<0,+$N23/Q23>=100),"NM",+$N23/Q23),"N/A") -> 0.49360134 | R42: =IFERROR(IF(OR(+$N23/R23<0,+$N23/R23>=100),"NM",+$N23/R23),"N/A") -> 10.890163 | S42: =IFERROR(IF(OR(+$N23/S23<0,+$N23/S23>=100),"NM",+$N23/S23),"N/A") -> 4.7911753 | T42: =IFERROR(IF(OR(+$N23/T23<0,+$N23/T23>=100),"NM",+$N23/T23),"N/A") -> 4.0131475 | U42: =IFERROR(IF(OR(+$F23/U23<0,+$F23/U23>=100),"NM",+$F23/U23),"N/A") -> NM | V42: =IFERROR(IF(OR(+$F23/V23<0,+$F23/V23>=100),"NM",+$F23/V23),"N/A") -> 30.731753 | W42: =IFERROR(IF(OR(+$F23/W23<0,+$F23/W23>=100),"NM",+$F23/W23),"N/A") -> 17.200856

Sheet MA_Comps
B2: Precedent Transactions - EMEA Airline Sellers with Transaction Enterprise Values Above £500 Million
B3: Announced Between January 1st, 2002, and August 15th, 2024
B4: =Public_Comps!$B$3 -> (£ GBP in Millions Except Per Share Amounts in GBP as Stated)
B5: (Only >= 50% Acquisitions; Asset Sales and Divestitures Also Included)
B7: =Company_Name&" - Comparable M&A Transactions:" -> easyJet plc - Comparable M&A Transactions: | I7: Valuation Multiples
F8: Transaction | I8: TEV / | J8: TEV /
D9: Announcement | E9: Percentage | F9: Enterprise | G9: NTM | H9: NTM | I9: NTM | J9: NTM
B10: Acquirer Name | C10: Target Name | D10: Date | E10: Acquired | F10: Value | G10: Revenue | H10: EBITDA | I10: Revenue | J10: EBITDA
B11: Air France SA (nka:Air France-KLM SA (ENXTPA:AF)) | C11: KLM Royal Dutch Airlines (OTCPK:KLMR) | D11: 37894 | E11: 1 | F11: 3021.44 | G11: 4316.3429 | H11: 348.49366 | I11: =IFERROR(IF(OR(+$F11/G11<0,+$F11/G11>=100),"NM",+$F11/G11),"N/A") -> 0.7 | J11: =IFERROR(IF(OR(+$F11/H11<0,+$F11/H11>=100),"NM",+$F11/H11),"N/A") -> 8.67
B12: British Airways Plc | C12: IBERIA LAE SA | D12: 40129 | E12: 0.8685 | F12: 763.25 | G12: 4240.2778 | H12: 30.714286 | I12: =IFERROR(IF(OR(+$F12/G12<0,+$F12/G12>=100),"NM",+$F12/G12),"N/A") -> 0.18 | J12: =IFERROR(IF(OR(+$F12/H12<0,+$F12/H12>=100),"NM",+$F12/H12),"N/A") -> 24.85
B13: International Consolidated Airlines Group S.A. (LSE:IAG) | C13: Aer Lingus Group DAC | D13: 41991 | E13: 1 | F13: 869.58 | G13: 1175.1081 | H13: 131.75455 | I13: =IFERROR(IF(OR(+$F13/G13<0,+$F13/G13>=100),"NM",+$F13/G13),"N/A") -> 0.74 | J13: =IFERROR(IF(OR(+$F13/H13<0,+$F13/H13>=100),"NM",+$F13/H13),"N/A") -> 6.6
B14: Deutsche Lufthansa AG (XTRA:LHA) | C14: Austrian Airlines AG | D14: 39871 | E14: 0.584 | F14: 1162.4 | G14: 2152.5926 | H14: 212.11679 | I14: =IFERROR(IF(OR(+$F14/G14<0,+$F14/G14>=100),"NM",+$F14/G14),"N/A") -> 0.54 | J14: =IFERROR(IF(OR(+$F14/H14<0,+$F14/H14>=100),"NM",+$F14/H14),"N/A") -> 5.48
B15: Deutsche Lufthansa AG (XTRA:LHA) | C15: Swiss International Air Lines AG | D15: 38433 | E15: 0.846 | F15: =(319/49%-493.3+71.2+177+145.4+699.7+11.2)*0.87 -> 1098.1318 | G15: 3273.9 | H15: 312.9 | I15: =IFERROR(IF(OR(+$F15/G15<0,+$F15/G15>=100),"NM",+$F15/G15),"N/A") -> 0.33542007 | J15: =IFERROR(IF(OR(+$F15/H15<0,+$F15/H15>=100),"NM",+$F15/H15),"N/A") -> 3.5095294
B16: DGN Corporation; Hpgb, SGPS S.A | C16: TAP - Transportes Aéreos Portugueses, SGPS, S.A. | D16: 42166 | E16: 0.61 | F16: 687.41 | G16: 2088.2 | H16: 57.6 | I16: =IFERROR(IF(OR(+$F16/G16<0,+$F16/G16>=100),"NM",+$F16/G16),"N/A") -> 0.32918782 | J16: =IFERROR(IF(OR(+$F16/H16<0,+$F16/H16>=100),"NM",+$F16/H16),"N/A") -> 11.934201
B17: Blue-Sky Transport Holding ; Langflug ehf ; Naust ehf | C17: Icelandair Group hf. (ICSE:ICEAIR) | D17: 39006 | E17: 0.505 | F17: 744.51 | G17: 385.5 | H17: 33.3 | I17: =IFERROR(IF(OR(+$F17/G17<0,+$F17/G17>=100),"NM",+$F17/G17),"N/A") -> 1.931284 | J17: =IFERROR(IF(OR(+$F17/H17<0,+$F17/H17>=100),"NM",+$F17/H17),"N/A") -> 22.357658
C19: Maximum | F19: =MAX(F11:F17) -> 3021.44 | G19: =MAX(G11:G17) -> 4316.3429 | H19: =MAX(H11:H17) -> 348.49366 | I19: =MAX(I11:I17) -> 1.931284 | J19: =MAX(J11:J17) -> 24.85
C20: 75th Percentile | F20: =QUARTILE(F11:F17,3) -> 1130.2659 | G20: =QUARTILE(G11:G17,3) -> 3757.0889 | H20: =QUARTILE(H11:H17,3) -> 262.50839 | I20: =QUARTILE(I11:I17,3) -> 0.72 | J20: =QUARTILE(J11:J17,3) -> 17.14593
C21: Median | F21: =MEDIAN(F11:F17) -> 869.58 | G21: =MEDIAN(G11:G17) -> 2152.5926 | H21: =MEDIAN(H11:H17) -> 131.75455 | I21: =MEDIAN(I11:I17) -> 0.54 | J21: =MEDIAN(J11:J17) -> 8.67
C22: 25th Percentile | F22: =QUARTILE(F11:F17,1) -> 753.88 | G22: =QUARTILE(G11:G17,1) -> 1631.6541 | H22: =QUARTILE(H11:H17,1) -> 45.45 | I22: =QUARTILE(I11:I17,1) -> 0.33230394 | J22: =QUARTILE(J11:J17,1) -> 6.04
C23: Minimum | F23: =MIN(F11:F17) -> 687.41 | G23: =MIN(G11:G17) -> 385.5 | H23: =MIN(H11:H17) -> 30.714286 | I23: =MIN(I11:I17) -> 0.18 | J23: =MIN(J11:J17) -> 3.5095294

Sheet ValSum
B2: ="Valuation Summary - "&Company_Name -> Valuation Summary - easyJet plc
B3: =Public_Comps!$B$3 -> (£ GBP in Millions Except Per Share Amounts in GBP as Stated)
B5: ="Valuation Summary - "&TEXT(Company_Name,"") -> Valuation Summary - easyJet plc | C5: =TEXT(Company_Name,"")&" - Range of Valuation Multiples / Premiums" -> easyJet plc - Range of Valuation Multiples / Premiums | I5: =TEXT(Company_Name,"")&" - Implied Per Share Value Range" -> easyJet plc - Implied Per Share Value Range
D7: 75th | F7: 25th | H7: Applicable | J7: 25th | L7: 75th
C8: Maximum | D8: Percentile | E8: Median | F8: Percentile | G8: Minimum | H8: Company | I8: Minimum | J8: Percentile | K8: Median | L8: Percentile | M8: Maximum
B9: Methodology Name | C9: Multiple | D9: Multiple | E9: Multiple | F9: Multiple | G9: Multiple | H9: Figure | I9: Multiple | J9: Multiple | K9: Multiple | L9: Multiple | M9: Multiple
B11: Public Company Comparables:
B12: =Public_Comps!$O$27&" TEV / Revenue:" -> CY 22 TEV / Revenue: | C12: {=TRANSPOSE(Public_Comps!O36:W40)} -> 3.8374296 | D12: 1.8604462 | E12: 1.71011 | F12: 1.1630663 | G12: 0.37546084 | H12: {=TRANSPOSE(Public_Comps!O23:W23)} -> 4538.6712 | I12: =MAX(0,(I31+SUM($E$30:$E$36))/$E$39) -> 2.2622342 | J12: =MAX(0,(J31+SUM($E$30:$E$36))/$E$39) -> 6.9719603 | K12: =MAX(0,(K31+SUM($E$30:$E$36))/$E$39) -> 10.243174 | L12: =MAX(0,(L31+SUM($E$30:$E$36))/$E$39) -> 11.142155 | M12: =MAX(0,(M31+SUM($E$30:$E$36))/$E$39) -> 22.964128
B13: =Public_Comps!$P$27&" TEV / Revenue:" -> CY 23 TEV / Revenue: | C13: 3.1771747 | D13: 1.5473557 | E13: 1.1623855 | F13: 0.81039596 | G13: 0.28336257 | H13: 6310.6335 | I13: =MAX(0,(I32+SUM($E$30:$E$36))/$E$39) -> 2.3730432 | J13: =MAX(0,(J32+SUM($E$30:$E$36))/$E$39) -> 6.7550124 | K13: =MAX(0,(K32+SUM($E$30:$E$36))/$E$39) -> 9.6815957 | L13: =MAX(0,(L32+SUM($E$30:$E$36))/$E$39) -> 12.882394 | M13: =MAX(0,(M32+SUM($E$30:$E$36))/$E$39) -> 26.43337
B14: =Public_Comps!$Q$27&" TEV / Revenue:" -> CY 24 TEV / Revenue: | C14: 2.8613646 | D14: 1.4362849 | E14: 0.93470799 | F14: 0.68636839 | G14: 0.26128808 | H14: 6940.9992 | I14: =MAX(0,(I33+SUM($E$30:$E$36))/$E$39) -> 2.4065123 | J14: =MAX(0,(J33+SUM($E$30:$E$36))/$E$39) -> 6.2938405 | K14: =MAX(0,(K33+SUM($E$30:$E$36))/$E$39) -> 8.5648879 | L14: =MAX(0,(L33+SUM($E$30:$E$36))/$E$39) -> 13.151772 | M14: =MAX(0,(M33+SUM($E$30:$E$36))/$E$39) -> 26.184021
B15: =Public_Comps!$O$27&" TEV / EBITDA:" -> CY 22 TEV / EBITDA: | C15: 44.579294 | D15: 12.123184 | E15: 7.3815652 | F15: 5.9892493 | G15: 4.1514299 | H15: 314.60379 | I15: =MAX(0,(I34+SUM($E$30:$E$36))/$E$39) -> 1.7378104 | J15: =MAX(0,(J34+SUM($E$30:$E$36))/$E$39) -> 2.4995824 | K15: =MAX(0,(K34+SUM($E$30:$E$36))/$E$39) -> 3.0766942 | L15: =MAX(0,(L34+SUM($E$30:$E$36))/$E$39) -> 5.0420847 | M15: =MAX(0,(M34+SUM($E$30:$E$36))/$E$39) -> 18.495069
B16: =Public_Comps!$P$27&" TEV / EBITDA:" -> CY 23 TEV / EBITDA: | C16: 10.650294 | D16: 6.6658018 | E16: 5.8767237 | F16: 3.6053834 | G16: 2.6098717 | H16: 715.0827 | I16: =MAX(0,(I35+SUM($E$30:$E$36))/$E$39) -> 2.4759112 | J16: =MAX(0,(J35+SUM($E$30:$E$36))/$E$39) -> 3.4138205 | K16: =MAX(0,(K35+SUM($E$30:$E$36))/$E$39) -> 5.5537363 | L16: =MAX(0,(L35+SUM($E$30:$E$36))/$E$39) -> 6.2971568 | M16: =MAX(0,(M35+SUM($E$30:$E$36))/$E$39) -> 10.051098
B17: =Public_Comps!$Q$27&" TEV / EBITDA:" -> CY 24 TEV / EBITDA: | C17: 8.505055 | D17: 5.4666254 | E17: 4.3128357 | F17: 2.5311142 | G17: 2.3541342 | H17: 853.71559 | I17: =MAX(0,(I36+SUM($E$30:$E$36))/$E$39) -> 2.6649585 | J17: =MAX(0,(J36+SUM($E$30:$E$36))/$E$39) -> 2.8640239 | K17: =MAX(0,(K36+SUM($E$30:$E$36))/$E$39) -> 4.8680863 | L17: =MAX(0,(L36+SUM($E$30:$E$36))/$E$39) -> 6.1658575 | M17: =MAX(0,(M36+SUM($E$30:$E$36))/$E$39) -> 9.5834525
B18: =Public_Comps!$O$27&" P / E:" -> CY 22 P / E: | C18: 52.045303 | D18: 25.804505 | E18: 20.602051 | F18: 17.617469 | G18: 10.55454 | H18: -504.72648 | I18: =MAX(0,I37/$E$39) -> 0 | J18: =MAX(0,J37/$E$39) -> 0 | K18: =MAX(0,K37/$E$39) -> 0 | L18: =MAX(0,L37/$E$39) -> 0 | M18: =MAX(0,M37/$E$39) -> 0
B19: =Public_Comps!$P$27&" P / E:" -> CY 23 P / E: | C19: 51.286045 | D19: 18.24111 | E19: 11.603451 | F19: 9.9473074 | G19: 5.7368805 | H19: 111.90475 | I19: =MAX(0,I38/$E$39) -> 0.84582892 | J19: =MAX(0,J38/$E$39) -> 1.466602 | K19: =MAX(0,K38/$E$39) -> 1.7107789 | L19: =MAX(0,L38/$E$39) -> 2.689416 | M19: =MAX(0,M38/$E$39) -> 7.5614648
B20: =Public_Comps!$Q$27&" P / E:" -> CY 24 P / E: | C20: 15.48578 | D20: 9.6512575 | E20: 8.0919826 | F20: 7.0229816 | G20: 1.813852 | H20: 199.9336 | I20: =MAX(0,I39/$E$39) -> 0.47779968 | J20: =MAX(0,J39/$E$39) -> 1.8499736 | K20: =MAX(0,K39/$E$39) -> 2.1315668 | L20: =MAX(0,L39/$E$39) -> 2.5423065 | M20: =MAX(0,M39/$E$39) -> 4.0792198
B22: Precedent Transactions:
B23: NTM TEV / Revenue: | C23: {=TRANSPOSE(MA_Comps!I19:J23)} -> 1.931284 | D23: 0.72 | E23: 0.54 | F23: 0.33230394 | G23: 0.18 | H23: =SUM(EZJ!L94:M94) -> 4927.6738 | I23: =MAX(0,(I41-SUM(DCF!$E$20:$E$26))/$E$39) -> 1.1856703 | J23: =MAX(0,(J41-SUM(DCF!$E$20:$E$26))/$E$39) -> 2.1744768 | K23: =MAX(0,(K41-SUM(DCF!$E$20:$E$26))/$E$39) -> 3.5229069 | L23: =MAX(0,(L41-SUM(DCF!$E$20:$E$26))/$E$39) -> 4.6915252 | M23: =MAX(0,(M41-SUM(DCF!$E$20:$E$26))/$E$39) -> 12.555574
B24: NTM TEV / EBITDA: | C24: 24.85 | D24: 17.14593 | E24: 8.67 | F24: 6.04 | G24: 3.5095294 | H24: =SUM(EZJ!L97:M97) -> 406.26309 | I24: =MAX(0,(I42-SUM(DCF!$E$20:$E$26))/$E$39) -> 1.8955662 | J24: =MAX(0,(J42-SUM(DCF!$E$20:$E$26))/$E$39) -> 3.2500283 | K24: =MAX(0,(K42-SUM(DCF!$E$20:$E$26))/$E$39) -> 4.6577647 | L24: =MAX(0,(L42-SUM(DCF!$E$20:$E$26))/$E$39) -> 9.1945991 | M24: =MAX(0,(M42-SUM(DCF!$E$20:$E$26))/$E$39) -> 13.318287
B26: Discounted Cash Flow Analysis:
B27: =TEXT(DCF!E162,"0.0%")&" - "&TEXT(DCF!Q162,"0.0%")&" Discount Rate, "&TEXT(DCF!D173,"0.0%")&" - "&TEXT(DCF!D163,"0.0%")&" Terminal FCF Growth Rate:" -> 7.0% - 10.0% Discount Rate, 0.0% - 1.0% Terminal FCF Growth Rate: | I27: =DCF!Q173 -> 8.6401228 | J27: =DCF!N170 -> 9.7310215 | K27: =DCF!K168 -> 10.997059 | L27: =DCF!H165 -> 12.751316 | M27: =DCF!E163 -> 14.911928
B29: Implied Enterprise Value Incl. Op. Leases: | E29: =I31 -> 1704.0933 | G29: Implied Enterprise Value or Equity Value at a Range of Multiples:
B30: (+) Cash & Investments: | E30: =-DCF!E20 -> 3505
B31: (+) Net Operating Losses: | E31: =-DCF!E21 -> 608.94246 | G31: Enterprise Value --> | I31: =G12*$H12 -> 1704.0933 | J31: =F12*$H12 -> 5278.7754 | K31: =E12*$H12 -> 7761.6269 | L31: =D12*$H12 -> 8443.9534 | M31: =C12*$H12 -> 17416.831
B32: (-) Total Debt: | E32: =-DCF!E22 -> -3046 | G32: Enterprise Value --> | I32: =G13*$H13 -> 1788.1973 | J32: =F13*$H13 -> 5114.1119 | K32: =E13*$H13 -> 7335.3887 | L32: =D13*$H13 -> 9764.7946 | M32: =C13*$H13 -> 20049.985
B33: (-) Preferred Stock: | E33: =-DCF!E23 -> 0 | G33: Enterprise Value --> | I33: =G14*$H14 -> 1813.6004 | J33: =F14*$H14 -> 4764.0824 | K33: =E14*$H14 -> 6487.8075 | L33: =D14*$H14 -> 9969.2523 | M33: =C14*$H14 -> 19860.73
B34: (-) Finance & Operating Leases: | E34: =-DCF!E24 -> -1055 | G34: Enterprise Value --> | I34: =G15*$H15 -> 1306.0556 | J34: =F15*$H15 -> 1884.2405 | K34: =E15*$H15 -> 2322.2684 | L34: =D15*$H15 -> 3813.9998 | M34: =C15*$H15 -> 14024.815
B35: (-) Noncontrolling Interests: | E35: =-DCF!E25 -> 0 | G35: Enterprise Value --> | I35: =G16*$H16 -> 1866.2741 | J35: =F16*$H16 -> 2578.1473 | K35: =E16*$H16 -> 4202.3434 | L35: =D16*$H16 -> 4766.5995 | M35: =C16*$H16 -> 7615.841
B36: (-) Unfunded Pensions: | E36: =-DCF!E26 -> 0 | G36: Enterprise Value --> | I36: =G17*$H17 -> 2009.761 | J36: =F17*$H17 -> 2160.8517 | K36: =E17*$H17 -> 3681.9351 | L36: =D17*$H17 -> 4666.9434 | M36: =C17*$H17 -> 7260.898
B37: Implied Equity Value: | E37: =SUM(E29:E36) -> 1717.0357 | G37: Equity Value --> | I37: =G18*$H18 -> -5327.156 | J37: =F18*$H18 -> -8892.0028 | K37: =E18*$H18 -> -10398.4 | L37: =D18*$H18 -> -13024.217 | M37: =C18*$H18 -> -26268.642
G38: Equity Value --> | I38: =G19*$H19 -> 641.98415 | J38: =F19*$H19 -> 1113.1509 | K38: =E19*$H19 -> 1298.4812 | L38: =D19*$H19 -> 2041.2667 | M38: =C19*$H19 -> 5739.1518
B39: Diluted Shares Outstanding: | E39: =Diluted_Shares -> 759 | G39: Equity Value --> | I39: =G20*$H20 -> 362.64995 | J39: =F20*$H20 -> 1404.13 | K39: =E20*$H20 -> 1617.8592 | L39: =D20*$H20 -> 1929.6106 | M39: =C20*$H20 -> 3096.1278
B41: Implied Share Price: | E41: =MAX(0,E37/E39) -> 2.2622342 | G41: Enterprise Value --> | I41: =G23*$H23 -> 886.98129 | J41: =F23*$H23 -> 1637.4854 | K41: =E23*$H23 -> 2660.9439 | L41: =D23*$H23 -> 3547.9252 | M41: =C23*$H23 -> 9516.7379
B42: Premium / (Discount) to Current: | E42: =E41/Share_Price-1 -> -0.50072077 | G42: Enterprise Value --> | I42: =G24*$H24 -> 1425.7923 | J42: =F24*$H24 -> 2453.829 | K42: =E24*$H24 -> 3522.301 | L42: =D24*$H24 -> 6965.7583 | M42: =C24*$H24 -> 10095.638

Sheet ValGraph
W2: =Company_Name&" Valuation - Range of Implied Share Prices" -> easyJet plc Valuation - Range of Implied Share Prices
I32: Min. | J32: 25th | K32: Median | L32: 75th | M32: Max | N32: Min Point | O32: 25th Point | P32: Median Point | Q32: 75th Point | R32: Max Point
B34: =ValSum!B27 -> 7.0% - 10.0% Discount Rate, 0.0% - 1.0% Terminal FCF Growth Rate: | I34: =ValSum!I27 -> 8.6401228 | J34: =ValSum!J27 -> 9.7310215 | K34: =ValSum!K27 -> 10.997059 | L34: =ValSum!L27 -> 12.751316 | M34: =ValSum!M27 -> 14.911928 | N34: =I34 -> 8.6401228 | O34: =J34-I34 -> 1.0908987 | P34: =K34-J34 -> 1.2660371 | Q34: =L34-K34 -> 1.7542571 | R34: =M34-L34 -> 2.1606122
B35: =ValSum!B24 -> NTM TEV / EBITDA: | I35: =ValSum!I24 -> 1.8955662 | J35: =ValSum!J24 -> 3.2500283 | K35: =ValSum!K24 -> 4.6577647 | L35: =ValSum!L24 -> 9.1945991 | M35: =ValSum!M24 -> 13.318287 | N35: =I35 -> 1.8955662 | O35: =J35-I35 -> 1.3544622 | P35: =K35-J35 -> 1.4077364 | Q35: =L35-K35 -> 4.5368344 | R35: =M35-L35 -> 4.1236883
B36: =ValSum!B23 -> NTM TEV / Revenue: | I36: =ValSum!I23 -> 1.1856703 | J36: =ValSum!J23 -> 2.1744768 | K36: =ValSum!K23 -> 3.5229069 | L36: =ValSum!L23 -> 4.6915252 | M36: =ValSum!M23 -> 12.555574 | N36: =I36 -> 1.1856703 | O36: =J36-I36 -> 0.98880652 | P36: =K36-J36 -> 1.3484301 | Q36: =L36-K36 -> 1.1686183 | R36: =M36-L36 -> 7.8640484
B37: =ValSum!B20 -> CY 24 P / E: | I37: =ValSum!I20 -> 0.47779968 | J37: =ValSum!J20 -> 1.8499736 | K37: =ValSum!K20 -> 2.1315668 | L37: =ValSum!L20 -> 2.5423065 | M37: =ValSum!M20 -> 4.0792198 | N37: =I37 -> 0.47779968 | O37: =J37-I37 -> 1.372174 | P37: =K37-J37 -> 0.28159316 | Q37: =L37-K37 -> 0.41073972 | R37: =M37-L37 -> 1.5369133
B38: =ValSum!B19 -> CY 23 P / E: | I38: =ValSum!I19 -> 0.84582892 | J38: =ValSum!J19 -> 1.466602 | K38: =ValSum!K19 -> 1.7107789 | L38: =ValSum!L19 -> 2.689416 | M38: =ValSum!M19 -> 7.5614648 | N38: =I38 -> 0.84582892 | O38: =J38-I38 -> 0.62077306 | P38: =K38-J38 -> 0.24417691 | Q38: =L38-K38 -> 0.97863709 | R38: =M38-L38 -> 4.8720489
B39: =ValSum!B18 -> CY 22 P / E: | I39: =ValSum!I18 -> 0 | J39: =ValSum!J18 -> 0 | K39: =ValSum!K18 -> 0 | L39: =ValSum!L18 -> 0 | M39: =ValSum!M18 -> 0 | N39: =I39 -> 0 | O39: =J39-I39 -> 0 | P39: =K39-J39 -> 0 | Q39: =L39-K39 -> 0 | R39: =M39-L39 -> 0
B40: =ValSum!B17 -> CY 24 TEV / EBITDA: | I40: =ValSum!I17 -> 2.6649585 | J40: =ValSum!J17 -> 2.8640239 | K40: =ValSum!K17 -> 4.8680863 | L40: =ValSum!L17 -> 6.1658575 | M40: =ValSum!M17 -> 9.5834525 | N40: =I40 -> 2.6649585 | O40: =J40-I40 -> 0.19906543 | P40: =K40-J40 -> 2.0040624 | Q40: =L40-K40 -> 1.2977711 | R40: =M40-L40 -> 3.4175951
B41: =ValSum!B16 -> CY 23 TEV / EBITDA: | I41: =ValSum!I16 -> 2.4759112 | J41: =ValSum!J16 -> 3.4138205 | K41: =ValSum!K16 -> 5.5537363 | L41: =ValSum!L16 -> 6.2971568 | M41: =ValSum!M16 -> 10.051098 | N41: =I41 -> 2.4759112 | O41: =J41-I41 -> 0.93790937 | P41: =K41-J41 -> 2.1399158 | Q41: =L41-K41 -> 0.74342042 | R41: =M41-L41 -> 3.7539413
B42: =ValSum!B15 -> CY 22 TEV / EBITDA: | I42: =ValSum!I15 -> 1.7378104 | J42: =ValSum!J15 -> 2.4995824 | K42: =ValSum!K15 -> 3.0766942 | L42: =ValSum!L15 -> 5.0420847 | M42: =ValSum!M15 -> 18.495069 | N42: =I42 -> 1.7378104 | O42: =J42-I42 -> 0.76177199 | P42: =K42-J42 -> 0.57711182 | Q42: =L42-K42 -> 1.9653905 | R42: =M42-L42 -> 13.452985
B43: =ValSum!B14 -> CY 24 TEV / Revenue: | I43: =ValSum!I14 -> 2.4065123 | J43: =ValSum!J14 -> 6.2938405 | K43: =ValSum!K14 -> 8.5648879 | L43: =ValSum!L14 -> 13.151772 | M43: =ValSum!M14 -> 26.184021 | N43: =I43 -> 2.4065123 | O43: =J43-I43 -> 3.8873282 | P43: =K43-J43 -> 2.2710475 | Q43: =L43-K43 -> 4.5868838 | R43: =M43-L43 -> 13.032249
B44: =ValSum!B13 -> CY 23 TEV / Revenue: | I44: =ValSum!I13 -> 2.3730432 | J44: =ValSum!J13 -> 6.7550124 | K44: =ValSum!K13 -> 9.6815957 | L44: =ValSum!L13 -> 12.882394 | M44: =ValSum!M13 -> 26.43337 | N44: =I44 -> 2.3730432 | O44: =J44-I44 -> 4.3819691 | P44: =K44-J44 -> 2.9265834 | Q44: =L44-K44 -> 3.2007983 | R44: =M44-L44 -> 13.550976
B45: =ValSum!B12 -> CY 22 TEV / Revenue: | I45: =ValSum!I12 -> 2.2622342 | J45: =ValSum!J12 -> 6.9719603 | K45: =ValSum!K12 -> 10.243174 | L45: =ValSum!L12 -> 11.142155 | M45: =ValSum!M12 -> 22.964128 | N45: =I45 -> 2.2622342 | O45: =J45-I45 -> 4.7097261 | P45: =K45-J45 -> 3.271214 | Q45: =L45-K45 -> 0.89898095 | R45: =M45-L45 -> 11.821973
B46: Current Share Price | I46: =Share_Price -> 4.531 | J46: =Share_Price -> 4.531 | K46: =Share_Price -> 4.531 | L46: =Share_Price -> 4.531 | M46: =Share_Price -> 4.531 | N46: 1000 | O46: 0 | P46: =O46 -> 0 | Q46: =P46 -> 0 | R46: =Q46 -> 0
